Workbook
Name Invoices: #REF!
Name Invoices: Wrapup31[]
Name Invoices: Wrapup[]
Name Summary: #REF!
Name Summary: Wrapup31[]
Name Summary: Wrapup[]

Sheet Summary
A1: Invoices Process Report - Design Projects
A4: Consultant | B4: Framework status | C4: Framework ID | D4: Frame Work Contract | E4: Value | F4: Duration | G4: Start Date | H4: Finsih Date | I4: Committed | J4: Remaining from framework | K4: Invoices w/out VAT | L4: Earned value | M4: Remaining to Invoice
A5: Dorsch food | B5: Closed | C5: MLTX-01-085 | D5: 2547 | E5: =22992640/1.15 -> 19993600 | F5: 24M | G5: 45085 | H5: 45816 | I5: =SUMIF(Maindata[Framework ID],Wrapup31[[#This Row],[Framework ID]],Maindata[Project Total amount]) -> 19558881 | J5: =E5-I5 -> 434719 | K5: =SUMIF(Currentinvoices[Framework ID],Wrapup31[[#This Row],[Framework ID]],Currentinvoices[Invoices Submitted Without VAT]) -> 18891266 | L5: =SUMIF(Currentinvoices[Framework ID],Wrapup31[[#This Row],[Framework ID]],Currentinvoices[Earned Value]) -> 19558881 | M5: =Wrapup31[[#This Row],[Earned value]]-Wrapup31[[#This Row],[Invoices w/out VAT]] -> 667615.42
A6: SYSTRA | B6: Closed | C6: MLTX-01-102 | D6: 2672 | E6: 15054089 | F6: 24M | G6: =EDATE(Wrapup31[[#This Row],[Finsih Date]], - 24) -> 45342 | H6: 46073 | I6: =SUMIF(Maindata[Framework ID],Wrapup31[[#This Row],[Framework ID]],Maindata[Project Total amount]) -> 15054089 | J6: =E6-I6 -> 0 | K6: =SUMIF(Currentinvoices[Framework ID],Wrapup31[[#This Row],[Framework ID]],Currentinvoices[Invoices Submitted Without VAT]) -> 15054089 | L6: =SUMIF(Currentinvoices[Framework ID],Wrapup31[[#This Row],[Framework ID]],Currentinvoices[Earned Value]) -> 15054089 | M6: =Wrapup31[[#This Row],[Earned value]]-Wrapup31[[#This Row],[Invoices w/out VAT]] -> 0
A7: EGEC - NIS2 | B7: Ongoing | C7: MLTX-01-099 | D7: 2709 | E7: 19979840 | F7: 48M | G7: 45421 | H7: 46882 | I7: =SUMIF(Maindata[Framework ID],Wrapup31[[#This Row],[Framework ID]],Maindata[Project Total amount]) -> 18497269 | J7: =E7-I7 -> 1482571 | K7: =SUMIF(Currentinvoices[Framework ID],Wrapup31[[#This Row],[Framework ID]],Currentinvoices[Invoices Submitted Without VAT]) -> 18147018 | L7: =SUMIF(Currentinvoices[Framework ID],Wrapup31[[#This Row],[Framework ID]],Currentinvoices[Earned Value]) -> 18467769 | M7: =Wrapup31[[#This Row],[Earned value]]-Wrapup31[[#This Row],[Invoices w/out VAT]] -> 320751.45
A8: ENGICON | B8: Closed | C8: RDH4-00-001 | D8: 2666 | E8: 27837620 | F8: 10M | G8: =EDATE(Wrapup31[[#This Row],[Finsih Date]], - 10) -> 45444 | H8: 45748 | I8: =SUMIF(Maindata[Framework ID],Wrapup31[[#This Row],[Framework ID]],Maindata[Project Total amount]) -> 27837620 | J8: =E8-I8 -> 0 | K8: =SUMIF(Currentinvoices[Framework ID],Wrapup31[[#This Row],[Framework ID]],Currentinvoices[Invoices Submitted Without VAT]) -> 25053858 | L8: =SUMIF(Currentinvoices[Framework ID],Wrapup31[[#This Row],[Framework ID]],Currentinvoices[Earned Value]) -> 27837620 | M8: =Wrapup31[[#This Row],[Earned value]]-Wrapup31[[#This Row],[Invoices w/out VAT]] -> 2783762
A9: EGEC - WAS | B9: Ongoing | C9: WAS1-01-039 | D9: TBA | E9: 9799000 | F9: 24M | G9: 45608 | H9: 46338 | I9: =SUMIF(Maindata[Framework ID],Wrapup31[[#This Row],[Framework ID]],Maindata[Project Total amount]) -> 7075670 | J9: =E9-I9 -> 2723330 | K9: =SUMIF(Currentinvoices[Framework ID],Wrapup31[[#This Row],[Framework ID]],Currentinvoices[Invoices Submitted Without VAT]) -> 7075670.9 | L9: =SUMIF(Currentinvoices[Framework ID],Wrapup31[[#This Row],[Framework ID]],Currentinvoices[Earned Value]) -> 7075670 | M9: =Wrapup31[[#This Row],[Earned value]]-Wrapup31[[#This Row],[Invoices w/out VAT]] -> -0.9
A10: ENGICON - Package1 | B10: Ongoing | C10: MLTX-01-098 | D10: 2891 | E10: 19856000 | F10: 60M | G10: 45700 | H10: 47526 | I10: =SUMIF(Maindata[Framework ID],Wrapup31[[#This Row],[Framework ID]],Maindata[Project Total amount]) -> 16551382 | J10: =E10-I10 -> 3304618 | K10: =SUMIF(Currentinvoices[Framework ID],Wrapup31[[#This Row],[Framework ID]],Currentinvoices[Invoices Submitted Without VAT]) -> 14962621 | L10: =SUMIF(Currentinvoices[Framework ID],Wrapup31[[#This Row],[Framework ID]],Currentinvoices[Earned Value]) -> 15549823 | M10: =Wrapup31[[#This Row],[Earned value]]-Wrapup31[[#This Row],[Invoices w/out VAT]] -> 587202.15 | BP10: a | BQ10: b | BR10: c
A11: ENGICON - RDH4 | B11: Closed | C11: RDH4-01-002 | D11: TBA | E11: 7025000 | F11: 24M | G11: =EDATE(Wrapup31[[#This Row],[Finsih Date]], - 24) -> 45617 | H11: 46347 | I11: =SUMIF(Maindata[Framework ID],Wrapup31[[#This Row],[Framework ID]],Maindata[Project Total amount]) -> 7025000 | J11: =E11-I11 -> 0 | K11: =SUMIF(Currentinvoices[Framework ID],Wrapup31[[#This Row],[Framework ID]],Currentinvoices[Invoices Submitted Without VAT]) -> 7024999.8 | L11: =SUMIF(Currentinvoices[Framework ID],Wrapup31[[#This Row],[Framework ID]],Currentinvoices[Earned Value]) -> 14050000 | M11: =Wrapup31[[#This Row],[Earned value]]-Wrapup31[[#This Row],[Invoices w/out VAT]] -> 7025000.2 | BO11: a | BP11: 15 | BQ11: 13 | BR11: 15
A12: Dar AlRiyadh 2 | B12: Ongoing | C12: MLTX-01-100 | D12: 2814 | E12: 59999686 | F12: 60M | G12: 45567 | H12: 47393 | I12: =SUMIF(Maindata[Framework ID],Wrapup31[[#This Row],[Framework ID]],Maindata[Project Total amount]) -> 0 | J12: =E12-I12 -> 59999686 | K12: =SUMIF(Currentinvoices[Framework ID],Wrapup31[[#This Row],[Framework ID]],Currentinvoices[Invoices Submitted Without VAT]) -> 22554552 | L12: =SUMIF(Currentinvoices[Framework ID],Wrapup31[[#This Row],[Framework ID]],Currentinvoices[Earned Value]) -> 0 | M12: =Wrapup31[[#This Row],[Earned value]]-Wrapup31[[#This Row],[Invoices w/out VAT]] -> -22554552
A13: Meinhardt (KHJ - FOOD) | B13: Ongoing | C13: KHJ1-01-020 | D13: 2966 | E13: 14990000 | F13: 24M | G13: 45832 | H13: 46562 | I13: =SUMIF(Maindata[Framework ID],Wrapup31[[#This Row],[Framework ID]],Maindata[Project Total amount]) -> 11685630 | J13: =E13-I13 -> 3304370 | K13: =SUMIF(Currentinvoices[Framework ID],Wrapup31[[#This Row],[Framework ID]],Currentinvoices[Invoices Submitted Without VAT]) -> 3939904.9 | L13: =SUMIF(Currentinvoices[Framework ID],Wrapup31[[#This Row],[Framework ID]],Currentinvoices[Earned Value]) -> 4469255 | M13: =Wrapup31[[#This Row],[Earned value]]-Wrapup31[[#This Row],[Invoices w/out VAT]] -> 529350.07
A14: Meinhardt (RDH1-01-006) | B14: Ongoing | C14: RDH1-01-006 | D14: 3172 | E14: 25298852 | G14: 46057 | H14: 46602 | I14: =SUMIF(Maindata[Framework ID],Wrapup31[[#This Row],[Framework ID]],Maindata[Project Total amount]) -> 25298852 | J14: =E14-I14 -> 0.17 | K14: =SUMIF(Currentinvoices[Framework ID],Wrapup31[[#This Row],[Framework ID]],Currentinvoices[Invoices Submitted Without VAT]) -> 7469770.1 | L14: =SUMIF(Currentinvoices[Framework ID],Wrapup31[[#This Row],[Framework ID]],Currentinvoices[Earned Value]) -> 12009587 | M14: =Wrapup31[[#This Row],[Earned value]]-Wrapup31[[#This Row],[Invoices w/out VAT]] -> 4539816.6
A15: ENGICON - RDH4 PH2 | B15: Ongoing | C15: RDH4-01-003 | D15: 3026 | E15: 59500000 | F15: 36M | G15: 45858 | H15: 46954 | I15: =SUMIF(Maindata[Framework ID],Wrapup31[[#This Row],[Framework ID]],Maindata[Project Total amount]) -> 39471610 | J15: =E15-I15 -> 20028390 | K15: =SUMIF(Currentinvoices[Framework ID],Wrapup31[[#This Row],[Framework ID]],Currentinvoices[Invoices Submitted Without VAT]) -> 27536518 | L15: =SUMIF(Currentinvoices[Framework ID],Wrapup31[[#This Row],[Framework ID]],Currentinvoices[Earned Value]) -> 28199915 | M15: =Wrapup31[[#This Row],[Earned value]]-Wrapup31[[#This Row],[Invoices w/out VAT]] -> 663396.91 | BP15: =MOD(SUM(BP11:BR11),2) -> 1
A16: AlDar International (KHJ - FOOD2) | B16: Ongoing | C16: KHJ-01-027 | D16: 3041 | E16: 11637180 | F16: 24M | G16: =EDATE(Wrapup31[[#This Row],[Finsih Date]], - 24) -> 45879 | H16: 46609 | I16: =SUMIF(Maindata[Framework ID],Wrapup31[[#This Row],[Framework ID]],Maindata[Project Total amount]) -> 7146100 | J16: =E16-I16 -> 4491080 | K16: =SUMIF(Currentinvoices[Framework ID],Wrapup31[[#This Row],[Framework ID]],Currentinvoices[Invoices Submitted Without VAT]) -> 6043100.3 | L16: =SUMIF(Currentinvoices[Framework ID],Wrapup31[[#This Row],[Framework ID]],Currentinvoices[Earned Value]) -> 7146100 | M16: =Wrapup31[[#This Row],[Earned value]]-Wrapup31[[#This Row],[Invoices w/out VAT]] -> 1102999.7
A17: ENGICON - Logistics | B17: Ongoing | C17: MLTX-01-117 | D17: 3042 | E17: 27800000 | F17: 24M | G17: =EDATE(Wrapup31[[#This Row],[Finsih Date]], - 24) -> 45868 | H17: 46598 | I17: =SUMIF(Maindata[Framework ID],Wrapup31[[#This Row],[Framework ID]],Maindata[Project Total amount]) -> 23907174 | J17: =E17-I17 -> 3892826 | K17: =SUMIF(Currentinvoices[Framework ID],Wrapup31[[#This Row],[Framework ID]],Currentinvoices[Invoices Submitted Without VAT]) -> 19924325 | L17: =SUMIF(Currentinvoices[Framework ID],Wrapup31[[#This Row],[Framework ID]],Currentinvoices[Earned Value]) -> 22967072 | M17: =Wrapup31[[#This Row],[Earned value]]-Wrapup31[[#This Row],[Invoices w/out VAT]] -> 3042746.9
A18: EGEC - NIS3 | B18: Ongoing | D18: 3020 | E18: 19955000 | F18: 48M | G18: =EDATE(Wrapup31[[#This Row],[Finsih Date]], - 48) -> 45848 | H18: 47309 | I18: =SUMIF(Maindata[Framework ID],Wrapup31[[#This Row],[Framework ID]],Maindata[Project Total amount]) -> 0 | J18: =E18-I18 -> 19955000 | K18: =SUMIF(Currentinvoices[Framework ID],Wrapup31[[#This Row],[Framework ID]],Currentinvoices[Invoices Submitted Without VAT]) -> 0 | L18: =SUMIF(Currentinvoices[Framework ID],Wrapup31[[#This Row],[Framework ID]],Currentinvoices[Earned Value]) -> 0 | M18: =Wrapup31[[#This Row],[Earned value]]-Wrapup31[[#This Row],[Invoices w/out VAT]] -> 0
A19: TYPSA- (KHJ-AMIC) | B19: Ongoing | C19: KHJ2-01-001 | E19: 57332139 | I19: =SUMIF(Maindata[Framework ID],Wrapup31[[#This Row],[Framework ID]],Maindata[Project Total amount]) -> 51542409 | J19: =E19-I19 -> 5789730.5 | K19: =SUMIF(Currentinvoices[Framework ID],Wrapup31[[#This Row],[Framework ID]],Currentinvoices[Invoices Submitted Without VAT]) -> 7579488.4 | L19: =SUMIF(Currentinvoices[Framework ID],Wrapup31[[#This Row],[Framework ID]],Currentinvoices[Earned Value]) -> 5647031.9 | M19: =Wrapup31[[#This Row],[Earned value]]-Wrapup31[[#This Row],[Invoices w/out VAT]] -> -1932456.5
A20: Total | E20: =SUBTOTAL(109,Wrapup31[Value]) -> 3.261477e+08 | I20: =SUBTOTAL(109,Wrapup31[[Committed ]]) -> 2.011761e+08 | J20: =SUBTOTAL(109,Wrapup31[Remaining from framework]) -> 1.249716e+08 | K20: =SUBTOTAL(109,Wrapup31[Invoices w/out VAT]) -> 1.3523297e+08 | L20: =SUBTOTAL(109,Wrapup31[Earned value]) -> 1.2153222e+08

Sheet Invoices (2)
A1: CASH FLOW OVERVIEW OF RUNNING PROJECTS
A3: Consultant | B3: Framework ID | C3: S/No. | D3: Projects | E3: Project ID | F3: Task Value | G3: Invoice # 1 date | H3: Invoice # 1 amount | I3: Invoice # 1 vat | J3: Invoice # 1 total | K3: Invoice # 2 date | L3: Invoice # 2 amount | M3: Invoice # 2 vat | N3: Invoice # 2 total | O3: Invoice # 3 date | P3: Invoice # 3 amount | Q3: Invoice # 3 vat | R3: Invoice # 3 total | S3: Invoice # 4 date | T3: Invoice # 4 amount | U3: Invoice # 4 vat | V3: Invoice # 4 total | W3: Invoice # 5 date | X3: Invoice # 5 amount | Y3: Invoice # 5 vat | Z3: Invoice # 5 total | AA3: Invoice # 6 date | AB3: Invoice # 6 amount | AC3: Invoice # 6 vat | AD3: Invoice # 6 total | AE3: Invoice # 7 date | AF3: Invoice # 7 amount | AG3: Invoice # 7 vat | AH3: Invoice # 7 total | AI3: Invoice # 8 date | AJ3: Invoice # 8 amount | AK3: Invoice # 8 vat | AL3: Invoice # 8 total | AM3: Invoice # 9 date | AN3: Invoice # 9 amount | AO3: Invoice # 9 vat | AP3: Invoice # 9 total | AQ3: Invoice # 10 date | AR3: Invoice # 10 amount | AS3: Invoice # 10 vat | AT3: Invoice # 10 total | AU3: Invoice # 11 date | AV3: Invoice # 11 amount | AW3: Invoice # 11 vat | AX3: Invoice # 11 total | AY3: Invoice # 12 date | AZ3: Invoice # 12 amount | BA3: Invoice # 12 vat | BB3: Invoice # 12 total | BC3: Invoice # 13 date | BD3: Invoice # 13 amount | BE3: Invoice # 13 vat | BF3: Invoice # 13 total | BG3: Invoice # 14 date | BH3: Invoice # 14 amount | BI3: Invoice # 14 vat | BJ3: Invoice # 14 total | BK3: Invoice # 15 date | BL3: Invoice # 15 amount | BM3: Invoice # 15 vat | BN3: Invoice # 15 total | BO3: Invoice # 16 date | BP3: Invoice # 16 amount | BQ3: Invoice # 16 vat | BR3: Invoice # 16 total | BS3: Invoice # 17 date | BT3: Invoice # 17 amount | BU3: Invoice # 17 vat | BV3: Invoice # 17 total | BW3: Invoice # 18 date | BX3: Invoice # 18 amount | BY3: Invoice # 18 vat | BZ3: Invoice # 18 total | CA3: Invoice # 19 date | CB3: Invoice # 19 amount | CC3: Invoice # 19 vat | CD3: Invoice # 19 total | CE3: Invoice # 20 date | CF3: Invoice # 20 amount | CG3: Invoice # 20 vat | CH3: Invoice # 20 total | CI3: Invoice # 21 date | CJ3: Invoice # 21 amount | CK3: Invoice # 21 vat | CL3: Invoice # 21 total | CM3: Invoice # 22 date | CN3: Invoice # 22 amount | CO3: Invoice # 22 vat | CP3: Invoice # 22 total | CQ3: Invoice # 23 date | CR3: Invoice # 23 amount | CS3: Invoice # 23 vat | CT3: Invoice # 23 total | CU3: Invoice # 24 date | CV3: Invoice # 24 amount | CW3: Invoice # 24 vat | CX3: Invoice # 24 total | CY3: Invoice # 25 date | CZ3: Invoice # 25 amount | DA3: Invoice # 25 vat | DB3: Invoice # 25 total | DC3: Remarks | DD3: Task Value2 | DE3: VAT | DF3: Total | DG3: Invoices Submitted Without VAT | DH3: Invoices Submitted With VAT | DI3: % Completion | DJ3: Earned Value | DK3: Remaining Value
A4: Dorsch food | B4: MLTX-01-085 | C4: 1 | D4: Jeddah 2 - Food Cluster - RBF 450 & 900 m2 | E4: JDH2-01-016 | F4: 877779 | G4: 45225 | H4: 416905 | I4: =H4*15% -> 62535.75 | J4: =H4+I4 -> 479440.75 | O4: 45398 | P4: 368699 | Q4: =P4*15% -> 55304.85 | R4: =P4+Q4 -> 424003.85 | DD4: =F4 -> 877779 | DE4: =DD4*15% -> 131666.85 | DF4: =DD4+DE4 -> 1009445.8 | DG4: =SUMPRODUCT((MOD(COLUMN(G4:DB4)-COLUMN(G4),4)=1)*G4:DB4) -> 785604 | DH4: =SUMPRODUCT((MOD(COLUMN(G4:DB4)-COLUMN(H4),4)=2)*G4:DB4) -> 903444.6 | DI4: 1 | DJ4: =DI4*DD4 -> 877779 | DK4: =DJ4-DG4 -> 92175
A5: Dorsch food | B5: MLTX-01-085 | C5: 2 | D5: Jeddah Food Cluster - Masterplan Update & Lands Selection at Jeddah 2nd & 3rd Ind. Cities | E5: MLTX-01-093 | F5: 1403611 | G5: 45225 | H5: 1403611 | I5: =H5*15% -> 210541.65 | J5: =H5+I5 -> 1614152.6 | DD5: =F5 -> 1403611 | DE5: =DD5*15% -> 210541.65 | DF5: =DD5+DE5 -> 1614152.6 | DG5: =SUMPRODUCT((MOD(COLUMN(G5:DB5)-COLUMN(G5),4)=1)*G5:DB5) -> 1403611 | DH5: =SUMPRODUCT((MOD(COLUMN(G5:DB5)-COLUMN(H5),4)=2)*G5:DB5) -> 1614152.6 | DI5: 1 | DJ5: =DI5*DD5 -> 1403611 | DK5: =DJ5-DG5 -> 0
A6: Dorsch food | B6: MLTX-01-085 | C6: 3 | D6: Jeddah 3 - Design of Shared Dry & Cold Storage Warehouses in Jeddah 3 Ind. City | E6: JDH3-01-021 | F6: 2999654 | G6: 45225 | H6: 1377997 | I6: =H6*15% -> 206699.55 | J6: =H6+I6 -> 1584696.6 | O6: 45398 | P6: 1297326 | Q6: =P6*15% -> 194598.9 | R6: =P6+Q6 -> 1491924.9 | DD6: =F6 -> 2999654 | DE6: =DD6*15% -> 449948.1 | DF6: =DD6+DE6 -> 3449602.1 | DG6: =SUMPRODUCT((MOD(COLUMN(G6:DB6)-COLUMN(G6),4)=1)*G6:DB6) -> 2675323 | DH6: =SUMPRODUCT((MOD(COLUMN(G6:DB6)-COLUMN(H6),4)=2)*G6:DB6) -> 3076621.5 | DI6: 1 | DJ6: =DI6*DD6 -> 2999654 | DK6: =DJ6-DG6 -> 324331
A7: Dorsch food | B7: MLTX-01-085 | C7: 4 | D7: Master planning a logistic area in Dammam 2 | E7: DAM2-01-026 | F7: 4125000 | K7: 45370 | L7: 682683 | M7: =L7*15% -> 102402.45 | N7: =L7+M7 -> 785085.45 | S7: 45435 | T7: 1379810.1 | U7: =T7*15% -> 206971.52 | V7: =T7+U7 -> 1586781.6 | AA7: 45471 | AB7: 2062506.5 | AC7: =AB7*15% -> 309375.98 | AD7: =AB7+AC7 -> 2371882.5 | DD7: =F7 -> 4125000 | DE7: =DD7*15% -> 618750 | DF7: =DD7+DE7 -> 4743750 | DG7: =SUMPRODUCT((MOD(COLUMN(G7:DB7)-COLUMN(G7),4)=1)*G7:DB7) -> 4124999.6 | DH7: =SUMPRODUCT((MOD(COLUMN(G7:DB7)-COLUMN(H7),4)=2)*G7:DB7) -> 4743749.6 | DI7: 1 | DJ7: =DI7*DD7 -> 4125000 | DK7: =DJ7-DG7 -> 0.37
A8: Dorsch food | B8: MLTX-01-085 | C8: 5 | D8: Hydrology Study for preventing Jeddah 4th Industrial City from floods and stormwater | E8: JDH4-01-040 | F8: 404258 | S8: 45435 | T8: 125226 | U8: =T8*15% -> 18783.9 | V8: =T8+U8 -> 144009.9 | AE8: 45537 | AF8: 279032 | AG8: =AF8*15% -> 41854.8 | AH8: =AF8+AG8 -> 320886.8 | DD8: =F8 -> 404258 | DE8: =DD8*15% -> 60638.7 | DF8: =DD8+DE8 -> 464896.7 | DG8: =SUMPRODUCT((MOD(COLUMN(G8:DB8)-COLUMN(G8),4)=1)*G8:DB8) -> 404258 | DH8: =SUMPRODUCT((MOD(COLUMN(G8:DB8)-COLUMN(H8),4)=2)*G8:DB8) -> 464896.7 | DI8: 1 | DJ8: =DI8*DD8 -> 404258 | DK8: =DJ8-DG8 -> 0
A9: Dorsch food | B9: MLTX-01-085 | C9: 6 | D9: Completing the infrastructure networks and residential neighborhood in the 2nd industrial city in Dammam | E9: DAM2-02-027 | F9: 6968306 | W9: 45451 | X9: 2539503 | Y9: =X9*15% -> 380925.45 | Z9: =X9+Y9 -> 2920428.5 | AI9: 45540 | AJ9: 1602086 | AK9: =AJ9*15% -> 240312.9 | AL9: =AJ9+AK9 -> 1842398.9 | BC9: 45728 | BD9: 2826718 | BE9: =BD9*15% -> 424007.69 | BF9: =BD9+BE9 -> 3250725.6 | DD9: =F9 -> 6968306 | DE9: =DD9*15% -> 1045245.9 | DF9: =DD9+DE9 -> 8013551.9 | DG9: =SUMPRODUCT((MOD(COLUMN(G9:DB9)-COLUMN(G9),4)=1)*G9:DB9) -> 6968307 | DH9: =SUMPRODUCT((MOD(COLUMN(G9:DB9)-COLUMN(H9),4)=2)*G9:DB9) -> 8013553 | DI9: 1 | DJ9: =DI9*DD9 -> 6968306 | DK9: =DJ9-DG9 -> -0.95
A10: Dorsch food | B10: MLTX-01-085 | C10: 7 | D10: Reviewing the masterplan for alkhrj nd. City | F10: 174000 | W10: 45451 | X10: 58000.11 | Y10: =X10*15% -> 8700.0165 | Z10: =X10+Y10 -> 66700.126 | AA10: 45471 | AB10: 115999.89 | AC10: =AB10*15% -> 17399.983 | AD10: =AB10+AC10 -> 133399.87 | DD10: =F10 -> 174000 | DE10: =DD10*15% -> 26100 | DF10: =DD10+DE10 -> 200100 | DG10: =SUMPRODUCT((MOD(COLUMN(G10:DB10)-COLUMN(G10),4)=1)*G10:DB10) -> 174000 | DH10: =SUMPRODUCT((MOD(COLUMN(G10:DB10)-COLUMN(H10),4)=2)*G10:DB10) -> 200100 | DI10: 1 | DJ10: =DI10*DD10 -> 174000 | DK10: =DJ10-DG10 -> 0
A11: Dorsch food | B11: MLTX-01-085 | C11: 8 | D11: Detail MPL and infra Design for the multi-use area in Dammam2 | E11: DAM2-01-029 | F11: 836000 | AM11: 45572 | AN11: 302500.8 | AO11: =AN11*15% -> 45375.12 | AP11: =AN11+AO11 -> 347875.92 | AQ11: 45650 | AR11: 533499.2 | AS11: =AR11*15% -> 80024.88 | AT11: =AR11+AS11 -> 613524.08 | DD11: =F11 -> 836000 | DE11: =DD11*15% -> 125400 | DF11: =DD11+DE11 -> 961400 | DG11: =SUMPRODUCT((MOD(COLUMN(G11:DB11)-COLUMN(G11),4)=1)*G11:DB11) -> 836000 | DH11: =SUMPRODUCT((MOD(COLUMN(G11:DB11)-COLUMN(H11),4)=2)*G11:DB11) -> 961400 | DI11: 1 | DJ11: =DI11*DD11 -> 836000 | DK11: =DJ11-DG11 -> 0
A12: Dorsch food | B12: MLTX-01-085 | C12: 9 | D12: Design shared services center - Food cluster | E12: JDH2-01-023 | F12: 1505768 | AM12: 45572 | AN12: 499280 | AO12: =AN12*15% -> 74892 | AP12: =AN12+AO12 -> 574172 | AU12: 45693 | AV12: 500302 | AW12: =AV12*15% -> 75045.3 | AX12: =AV12+AW12 -> 575347.3 | AY12: 45720 | AZ12: 255076 | BA12: =AZ12*15% -> 38261.4 | BB12: =AZ12+BA12 -> 293337.4 | DD12: =F12 -> 1505768 | DE12: =DD12*15% -> 225865.2 | DF12: =DD12+DE12 -> 1731633.2 | DG12: =SUMPRODUCT((MOD(COLUMN(G12:DB12)-COLUMN(G12),4)=1)*G12:DB12) -> 1254658 | DH12: =SUMPRODUCT((MOD(COLUMN(G12:DB12)-COLUMN(H12),4)=2)*G12:DB12) -> 1442856.7 | DI12: 1 | DJ12: =DI12*DD12 -> 1505768 | DK12: =DJ12-DG12 -> 251110
A13: Dorsch food | B13: MLTX-01-085 | C13: 10 | D13: الدراسه القيميه لمشاريع المصانع الجاهزة | F13: 264505 | AQ13: 45650 | AR13: 264505 | AS13: =AR13*15% -> 39675.75 | AT13: =AR13+AS13 -> 304180.75 | DD13: =F13 -> 264505 | DE13: =DD13*15% -> 39675.75 | DF13: =DD13+DE13 -> 304180.75 | DG13: =SUMPRODUCT((MOD(COLUMN(G13:DB13)-COLUMN(G13),4)=1)*G13:DB13) -> 264505 | DH13: =SUMPRODUCT((MOD(COLUMN(G13:DB13)-COLUMN(H13),4)=2)*G13:DB13) -> 304180.75 | DI13: 1 | DJ13: =DI13*DD13 -> 264505 | DK13: =DJ13-DG13 -> 0
A14: SYSTRA | B14: MLTX-01-102 | C14: 1 | D14: Masterplan & Infrstructure Detailed Design For Technology Zones (Jenadryah) | E14: JNDT-01-001 | F14: 6726972 | G14: 45504 | H14: =SYSTRA!H12 -> 672697.82 | I14: =H14*15% -> 100904.67 | J14: =H14+I14 -> 773602.49 | K14: 45511 | L14: =SYSTRA!J12 -> 1681772 | M14: =L14*15% -> 252265.8 | N14: =L14+M14 -> 1934037.8 | O14: 45641 | P14: =SYSTRA!L12 -> 1345449 | Q14: =P14*15% -> 201817.35 | R14: =P14+Q14 -> 1547266.4 | S14: 45727 | T14: =SYSTRA!N12 -> 1681658.8 | U14: =T14*15% -> 252248.82 | V14: =T14+U14 -> 1933907.6 | AA14: 45839 | AB14: =SYSTRA!R12 -> 1345394.4 | AC14: =AB14*15% -> 201809.16 | AD14: =AB14+AC14 -> 1547203.6 | DD14: =F14 -> 6726972 | DE14: =DD14*15% -> 1009045.8 | DF14: =DD14+DE14 -> 7736017.8 | DG14: =SUMPRODUCT((MOD(COLUMN(G14:DB14)-COLUMN(G14),4)=1)*G14:DB14) -> 6726972 | DH14: =SUMPRODUCT((MOD(COLUMN(G14:DB14)-COLUMN(H14),4)=2)*G14:DB14) -> 7736017.8 | DI14: 1 | DJ14: =DI14*DD14 -> 6726972 | DK14: =DJ14-DG14 -> 0
A15: SYSTRA | B15: MLTX-01-102 | C15: 2 | D15: Masterplan & Infrstructure Detailed Design For Technology Zones (Dammam) | E15: DAMT-01-001 | F15: 3300435 | S15: 45727 | T15: =SYSTRA!N27 -> 330043.5 | U15: =T15*15% -> 49506.525 | V15: =T15+U15 -> 379550.03 | W15: 45788 | X15: =SYSTRA!P27 -> 1072641.4 | Y15: =X15*15% -> 160896.21 | Z15: =X15+Y15 -> 1233537.6 | AA15: 45839 | AB15: =SYSTRA!R27 -> 577576.13 | AC15: =AB15*15% -> 86636.42 | AD15: =AB15+AC15 -> 664212.55 | AE15: 46152 | AF15: 1320174 | AG15: =Currentinvoices[[#This Row],[Invoice '# 7 amount]]*15% -> 198026.1 | AH15: =Currentinvoices[[#This Row],[Invoice '# 7 vat]]+Currentinvoices[[#This Row],[Invoice '# 7 amount]] -> 1518200.1 | DD15: =F15 -> 3300435 | DE15: =DD15*15% -> 495065.25 | DF15: =DD15+DE15 -> 3795500.2 | DG15: =SUMPRODUCT((MOD(COLUMN(G15:DB15)-COLUMN(G15),4)=1)*G15:DB15) -> 3300435 | DH15: =SUMPRODUCT((MOD(COLUMN(G15:DB15)-COLUMN(H15),4)=2)*G15:DB15) -> 3795500.2 | DI15: 1 | DJ15: =DI15*DD15 -> 3300435 | DK15: =DJ15-DG15 -> 0
A16: SYSTRA | B16: MLTX-01-102 | C16: 3 | D16: Masterplan & Infrstructure Detailed Design For Technology Zones (Dhahran) | E16: DHRT-01-001 | F16: 3300435 | S16: 45727 | T16: =SYSTRA!N42 -> 330043.5 | U16: =T16*15% -> 49506.525 | V16: =T16+U16 -> 379550.03 | W16: 45788 | X16: =SYSTRA!P42 -> 1072641.4 | Y16: =X16*15% -> 160896.21 | Z16: =X16+Y16 -> 1233537.6 | AA16: 45839 | AB16: =SYSTRA!R42 -> 577576.12 | AC16: =AB16*15% -> 86636.418 | AD16: =AB16+AC16 -> 664212.54 | AE16: 46152 | AF16: 1320174 | AG16: =Currentinvoices[[#This Row],[Invoice '# 7 amount]]*15% -> 198026.1 | AH16: =Currentinvoices[[#This Row],[Invoice '# 7 vat]]+Currentinvoices[[#This Row],[Invoice '# 7 amount]] -> 1518200.1 | DD16: =F16 -> 3300435 | DE16: =DD16*15% -> 495065.25 | DF16: =DD16+DE16 -> 3795500.2 | DG16: =SUMPRODUCT((MOD(COLUMN(G16:DB16)-COLUMN(G16),4)=1)*G16:DB16) -> 3300435 | DH16: =SUMPRODUCT((MOD(COLUMN(G16:DB16)-COLUMN(H16),4)=2)*G16:DB16) -> 3795500.2 | DI16: 1 | DJ16: =DI16*DD16 -> 3300435 | DK16: =DJ16-DG16 -> 0
A17: SYSTRA | B17: MLTX-01-102 | C17: 4 | D17: Technical review and transport planning expertise support for Riyadh Industrial cities 1 & 4 | E17: MLTX-01-111 | F17: 1726247 | W17: 45788 | X17: =SYSTRA!P57 -> 1208358 | Y17: =X17*15% -> 181253.7 | Z17: =X17+Y17 -> 1389611.7 | AA17: 45839 | AB17: =SYSTRA!R57 -> 517889.02 | AC17: =AB17*15% -> 77683.353 | AD17: =AB17+AC17 -> 595572.37 | DD17: =F17 -> 1726247 | DE17: =DD17*15% -> 258937.05 | DF17: =DD17+DE17 -> 1985184.1 | DG17: =SUMPRODUCT((MOD(COLUMN(G17:DB17)-COLUMN(G17),4)=1)*G17:DB17) -> 1726247 | DH17: =SUMPRODUCT((MOD(COLUMN(G17:DB17)-COLUMN(H17),4)=2)*G17:DB17) -> 1985184 | DI17: 1 | DJ17: =DI17*DD17 -> 1726247 | DK17: =DJ17-DG17 -> 0
A18: EGEC - NIS2 | B18: MLTX-01-099 | C18: 1 | D18: Updated concept masterplan & Infrastructure designs for Tabouk ind. City | E18: TAB-01-009 | F18: 4360270 | G18: 45496 | H18: ='EGEC - NIS2'!M17 -> 1395290.5 | I18: =H18*15% -> 209293.57 | J18: =H18+I18 -> 1604584.1 | K18: 45532 | L18: ='EGEC - NIS2'!O17 -> 1874916.4 | M18: =L18*15% -> 281237.46 | N18: =L18+M18 -> 2156153.8 | W18: 45626 | X18: ='EGEC - NIS2'!Q17 -> 872049.61 | Y18: =X18*15% -> 130807.44 | Z18: =X18+Y18 -> 1002857.1 | AA18: 45651 | AB18: ='EGEC - NIS2'!S17 -> 218013.5 | AC18: =AB18*15% -> 32702.025 | AD18: =AB18+AC18 -> 250715.52 | DD18: =F18 -> 4360270 | DE18: =DD18*15% -> 654040.5 | DF18: =DD18+DE18 -> 5014310.5 | DG18: =SUMPRODUCT((MOD(COLUMN(G18:DB18)-COLUMN(G18),4)=1)*G18:DB18) -> 4360270 | DH18: =SUMPRODUCT((MOD(COLUMN(G18:DB18)-COLUMN(H18),4)=2)*G18:DB18) -> 5014310.5 | DI18: 1 | DJ18: =DI18*DD18 -> 4360270 | DK18: =DJ18-DG18 -> 5.0002709e-06
A19: EGEC - NIS2 | B19: MLTX-01-099 | C19: 2 | D19: Project support services (6 months) (Masterplan) | F19: 744150 | K19: 45532 | L19: ='EGEC - NIS2'!O32 -> 372075 | M19: =L19*15% -> 55811.25 | N19: =L19+M19 -> 427886.25 | S19: 45596 | T19: ='EGEC - NIS2'!Q32 -> 372075 | U19: =T19*15% -> 55811.25 | V19: =T19+U19 -> 427886.25 | DD19: =F19 -> 744150 | DE19: =DD19*15% -> 111622.5 | DF19: =DD19+DE19 -> 855772.5 | DG19: =SUMPRODUCT((MOD(COLUMN(G19:DB19)-COLUMN(G19),4)=1)*G19:DB19) -> 744150 | DH19: =SUMPRODUCT((MOD(COLUMN(G19:DB19)-COLUMN(H19),4)=2)*G19:DB19) -> 855772.5 | DI19: 1 | DJ19: =DI19*DD19 -> 744150 | DK19: =DJ19-DG19 -> 0
A20: EGEC - NIS2 | B20: MLTX-01-099 | C20: 3 | D20: Project support services (6 months) (VRO) | F20: 744150 | AE20: 45688 | AF20: ='EGEC - NIS2'!U32 -> 372075 | AG20: =AF20*15% -> 55811.25 | AH20: =AF20+AG20 -> 427886.25 | AU20: 45807 | AV20: ='EGEC - NIS2'!W32 -> 372075 | AW20: =AV20*15% -> 55811.25 | AX20: =AV20+AW20 -> 427886.25 | DD20: =F20 -> 744150 | DE20: =DD20*15% -> 111622.5 | DF20: =DD20+DE20 -> 855772.5 | DG20: =SUMPRODUCT((MOD(COLUMN(G20:DB20)-COLUMN(G20),4)=1)*G20:DB20) -> 744150 | DH20: =SUMPRODUCT((MOD(COLUMN(G20:DB20)-COLUMN(H20),4)=2)*G20:DB20) -> 855772.5 | DI20: 1 | DJ20: =DI20*DD20 -> 744150 | DK20: =DJ20-DG20 -> 0
A21: EGEC - NIS2 | B21: MLTX-01-099 | C21: 4 | D21: Testing and evaluating concrete structure | F21: 153002 | K21: 45532 | L21: ='EGEC - NIS2'!O47 -> 107101.54 | M21: =L21*15% -> 16065.231 | N21: =L21+M21 -> 123166.77 | O21: 45586 | P21: ='EGEC - NIS2'!Q47 -> 45900.66 | Q21: =P21*15% -> 6885.099 | R21: =P21+Q21 -> 52785.759 | DD21: =F21 -> 153002 | DE21: =DD21*15% -> 22950.3 | DF21: =DD21+DE21 -> 175952.3 | DG21: =SUMPRODUCT((MOD(COLUMN(G21:DB21)-COLUMN(G21),4)=1)*G21:DB21) -> 153002.2 | DH21: =SUMPRODUCT((MOD(COLUMN(G21:DB21)-COLUMN(H21),4)=2)*G21:DB21) -> 175952.53 | DI21: 1 | DJ21: =DI21*DD21 -> 153002 | DK21: =DJ21-DG21 -> -0.2
A22: EGEC - NIS2 | B22: MLTX-01-099 | C22: 5 | D22: Preliminary designs for the expansion of the industrial city in riyadh | F22: 156177 | O22: 45586 | P22: ='EGEC - NIS2'!Q64 -> 109323.9 | Q22: =P22*15% -> 16398.585 | R22: =P22+Q22 -> 125722.48 | W22: 45626 | X22: 46853.1 | Y22: =X22*15% -> 7027.965 | Z22: =X22+Y22 -> 53881.065 | DD22: =F22 -> 156177 | DE22: =DD22*15% -> 23426.55 | DF22: =DD22+DE22 -> 179603.55 | DG22: =SUMPRODUCT((MOD(COLUMN(G22:DB22)-COLUMN(G22),4)=1)*G22:DB22) -> 156177 | DH22: =SUMPRODUCT((MOD(COLUMN(G22:DB22)-COLUMN(H22),4)=2)*G22:DB22) -> 179603.55 | DI22: 1 | DJ22: =DI22*DD22 -> 156177 | DK22: =DJ22-DG22 -> 0
A23: EGEC - NIS2 | B23: MLTX-01-099 | C23: 6 | D23: Incubators in Al-Qassim Oasis | E23: QSM3-01-014 | F23: 1656100 | W23: 45626 | X23: 248415 | Y23: =X23*15% -> 37262.25 | Z23: =X23+Y23 -> 285677.25 | AA23: 45651 | AB23: ='EGEC - NIS2'!M82 -> 828050 | AC23: =AB23*15% -> 124207.5 | AD23: =AB23+AC23 -> 952257.5 | AE23: 45688 | AF23: ='EGEC - NIS2'!O82 -> 579635 | AG23: =AF23*15% -> 86945.25 | AH23: =AF23+AG23 -> 666580.25 | DD23: =F23 -> 1656100 | DE23: =DD23*15% -> 248415 | DF23: =DD23+DE23 -> 1904515 | DG23: =SUMPRODUCT((MOD(COLUMN(G23:DB23)-COLUMN(G23),4)=1)*G23:DB23) -> 1656100 | DH23: =SUMPRODUCT((MOD(COLUMN(G23:DB23)-COLUMN(H23),4)=2)*G23:DB23) -> 1904515 | DI23: 1 | DJ23: =DI23*DD23 -> 1656100 | DK23: =DJ23-DG23 -> 0
A24: EGEC - NIS2 | B24: MLTX-01-099 | C24: 7 | D24: Site development and infrastructure design works for expansion in Jeddah 1 | E24: JDH1-01-021 | F24: 2560090 | AE24: 45688 | AF24: ='EGEC - NIS2'!O101 -> 384013.5 | AG24: =AF24*15% -> 57602.025 | AH24: =AF24+AG24 -> 441615.53 | AM24: 45760 | AN24: ='EGEC - NIS2'!S101 -> 384013.5 | AO24: =AN24*15% -> 57602.025 | AP24: =AN24+AO24 -> 441615.53 | AQ24: 45777 | AR24: ='EGEC - NIS2'!U101 -> 640022.5 | AS24: =AR24*15% -> 96003.375 | AT24: =AR24+AS24 -> 736025.88 | AU24: 45807 | AV24: ='EGEC - NIS2'!W101 -> 896032 | AW24: =AV24*15% -> 134404.8 | AX24: =AV24+AW24 -> 1030436.8 | AY24: 45865 | AZ24: ='EGEC - NIS2'!Y101 -> 256008.5 | BA24: =AZ24*15% -> 38401.275 | BB24: =AZ24+BA24 -> 294409.78 | DD24: =F24 -> 2560090 | DE24: =DD24*15% -> 384013.5 | DF24: =DD24+DE24 -> 2944103.5 | DG24: =SUMPRODUCT((MOD(COLUMN(G24:DB24)-COLUMN(G24),4)=1)*G24:DB24) -> 2560090 | DH24: =SUMPRODUCT((MOD(COLUMN(G24:DB24)-COLUMN(H24),4)=2)*G24:DB24) -> 2944103.5 | DI24: 1 | DJ24: =DI24*DD24 -> 2560090 | DK24: =DJ24-DG24 -> 0
A25: EGEC - NIS2 | B25: MLTX-01-099 | C25: 8 | D25: Detailed design of connection road (Fly Over) in Dammam 2 | E25: DAM2-01-033 | F25: 2310000 | AM25: 45760 | AN25: ='EGEC - NIS2'!S165 -> 693000 | AO25: =AN25*15% -> 103950 | AP25: =AN25+AO25 -> 796950 | CA25: 46140 | CB25: 577500 | CC25: =Currentinvoices[[#This Row],[Invoice '# 19 amount]]*15% -> 86625 | CD25: =Currentinvoices[[#This Row],[Invoice '# 19 vat]]+Currentinvoices[[#This Row],[Invoice '# 19 amount]] -> 664125 | CE25: 46190 | CF25: 808500 | CG25: =Currentinvoices[[#This Row],[Invoice '# 20 amount]]*15% -> 121275 | CH25: =Currentinvoices[[#This Row],[Invoice '# 20 amount]]+Currentinvoices[[#This Row],[Invoice '# 20 vat]] -> 929775 | DD25: =F25 -> 2310000 | DE25: =DD25*15% -> 346500 | DF25: =DD25+DE25 -> 2656500 | DG25: =SUMPRODUCT((MOD(COLUMN(G25:DB25)-COLUMN(G25),4)=1)*G25:DB25) -> 2079000 | DH25: =SUMPRODUCT((MOD(COLUMN(G25:DB25)-COLUMN(H25),4)=2)*G25:DB25) -> 2390850 | DI25: 1 | DJ25: =DI25*DD25 -> 2310000 | DK25: =DJ25-DG25 -> 231000
A26: EGEC - NIS2 | B26: MLTX-01-099 | C26: 9 | D26: Labour camp masterplan and infrastructure development in AlKharj | E26: KHJ-01-025 | F26: 350000 | AI26: 45718 | AJ26: ='EGEC - NIS2'!Q124 -> 175000 | AK26: =AJ26*15% -> 26250 | AL26: =AJ26+AK26 -> 201250 | AM26: 45760 | AN26: ='EGEC - NIS2'!S124 -> 175000 | AO26: =AN26*15% -> 26250 | AP26: =AN26+AO26 -> 201250 | DD26: =F26 -> 350000 | DE26: =DD26*15% -> 52500 | DF26: =DD26+DE26 -> 402500 | DG26: =SUMPRODUCT((MOD(COLUMN(G26:DB26)-COLUMN(G26),4)=1)*G26:DB26) -> 350000 | DH26: =SUMPRODUCT((MOD(COLUMN(G26:DB26)-COLUMN(H26),4)=2)*G26:DB26) -> 402500 | DI26: 1 | DJ26: =DI26*DD26 -> 350000 | DK26: =DJ26-DG26 -> 0
A27: EGEC - NIS2 | B27: MLTX-01-099 | C27: 10 | D27: Potable water pipeline supply and connection to alkharj 1st ind. City | E27: KHJ-01-026 | F27: 534490 | AM27: 45760 | AN27: ='EGEC - NIS2'!S146 -> 210000 | AO27: =AN27*15% -> 31500 | AP27: =AN27+AO27 -> 241500 | BC27: 45907 | BD27: ='EGEC - NIS2'!U146 -> 175000.64 | BE27: =BD27*15% -> 26250.096 | BF27: =BD27+BE27 -> 201250.74 | BO27: 45994 | BP27: ='EGEC - NIS2'!W146 -> 140000 | BQ27: ='Invoices (2)'!$BP27*15% -> 21000 | BR27: ='Invoices (2)'!$BQ27+'Invoices (2)'!$BP27 -> 161000 | BS27: 46014 | BT27: 9490 | BU27: =Currentinvoices[[#This Row],[Invoice '# 17 amount]]*15% -> 1423.5 | BV27: =Currentinvoices[[#This Row],[Invoice '# 17 amount]]+Currentinvoices[[#This Row],[Invoice '# 17 vat]] -> 10913.5 | DD27: =F27 -> 534490 | DE27: =DD27*15% -> 80173.5 | DF27: =DD27+DE27 -> 614663.5 | DG27: =SUMPRODUCT((MOD(COLUMN(G27:DB27)-COLUMN(G27),4)=1)*G27:DB27) -> 534490.64 | DH27: =SUMPRODUCT((MOD(COLUMN(G27:DB27)-COLUMN(H27),4)=2)*G27:DB27) -> 614664.24 | DI27: 1 | DJ27: =DI27*DD27 -> 534490 | DK27: =DJ27-DG27 -> -0.64
A28: EGEC - NIS2 | B28: MLTX-01-099 | C28: 11 | D28: Study design RBFs 900 & 450m2 SFDA requirements | F28: 170000 | AM28: 45760 | AN28: ='EGEC - NIS2'!S183 -> 85000 | AO28: =AN28*15% -> 12750 | AP28: =AN28+AO28 -> 97750 | BG28: 45929 | BH28: ='EGEC - NIS2'!W183 -> 85000 | BI28: ='Invoices (2)'!$BH28*15% -> 12750 | BJ28: ='Invoices (2)'!$BH28+'Invoices (2)'!$BI28 -> 97750 | DD28: =F28 -> 170000 | DE28: =DD28*15% -> 25500 | DF28: =DD28+DE28 -> 195500 | DG28: =SUMPRODUCT((MOD(COLUMN(G28:DB28)-COLUMN(G28),4)=1)*G28:DB28) -> 170000 | DH28: =SUMPRODUCT((MOD(COLUMN(G28:DB28)-COLUMN(H28),4)=2)*G28:DB28) -> 195500 | DI28: 1 | DJ28: =DI28*DD28 -> 170000 | DK28: =DJ28-DG28 -> 0
A29: EGEC - NIS2 | B29: MLTX-01-099 | C29: 12 | D29: Improving the entrances and exit points for Jeddah 1 | E29: JDH1-01-028 | F29: 1590000 | BK29: 45956 | BL29: ='EGEC - NIS2'!M247 -> 794999.1 | BM29: ='Invoices (2)'!$BL29*15% -> 119249.87 | BN29: ='Invoices (2)'!$BL29+'Invoices (2)'!$BM29 -> 914248.97 | BS29: 46014 | BT29: 556500 | BU29: =Currentinvoices[[#This Row],[Invoice '# 17 amount]]*15% -> 83475 | BV29: =Currentinvoices[[#This Row],[Invoice '# 17 amount]]+Currentinvoices[[#This Row],[Invoice '# 17 vat]] -> 639975 | CE29: 46190 | CF29: 119250 | CG29: =Currentinvoices[[#This Row],[Invoice '# 20 amount]]*15% -> 17887.5 | CH29: =Currentinvoices[[#This Row],[Invoice '# 20 amount]]+Currentinvoices[[#This Row],[Invoice '# 20 vat]] -> 137137.5 | DD29: =F29 -> 1590000 | DE29: =DD29*15% -> 238500 | DF29: =DD29+DE29 -> 1828500 | DG29: =SUMPRODUCT((MOD(COLUMN(G29:DB29)-COLUMN(G29),4)=1)*G29:DB29) -> 1470749.1 | DH29: =SUMPRODUCT((MOD(COLUMN(G29:DB29)-COLUMN(H29),4)=2)*G29:DB29) -> 1691361.5 | DI29: 1 | DJ29: =DI29*DD29 -> 1590000 | DK29: =DJ29-DG29 -> 119250.9
A30: EGEC - NIS2 | B30: MLTX-01-099 | C30: 13 | D30: Hydrology study for Jeddah 2 | E30: JDH2-01-028 | F30: 110500 | BK30: 45956 | BL30: ='EGEC - NIS2'!M232 -> 44199.17 | BM30: ='Invoices (2)'!$BL30*15% -> 6629.8755 | BN30: ='Invoices (2)'!$BL30+'Invoices (2)'!$BM30 -> 50829.046 | BW30: 46056 | BX30: 66300 | BY30: =Currentinvoices[[#This Row],[Invoice '# 18 amount]]*15% -> 9945 | BZ30: =Currentinvoices[[#This Row],[Invoice '# 18 vat]]+Currentinvoices[[#This Row],[Invoice '# 18 amount]] -> 76245 | DD30: =F30 -> 110500 | DE30: =DD30*15% -> 16575 | DF30: =DD30+DE30 -> 127075 | DG30: =SUMPRODUCT((MOD(COLUMN(G30:DB30)-COLUMN(G30),4)=1)*G30:DB30) -> 110499.17 | DH30: =SUMPRODUCT((MOD(COLUMN(G30:DB30)-COLUMN(H30),4)=2)*G30:DB30) -> 127074.05 | DI30: 1 | DJ30: =DI30*DD30 -> 110500 | DK30: =DJ30-DG30 -> 0.83
A31: EGEC - NIS2 | B31: MLTX-01-099 | C31: 14 | D31: Jenadriyadh Business Incubators | E31: JNDT-01-002 | F31: 500000 | BO31: 45994 | BP31: ='EGEC - NIS2'!M262 -> 100000 | BQ31: ='Invoices (2)'!$BP31*15% -> 15000 | BR31: ='Invoices (2)'!$BQ31+'Invoices (2)'!$BP31 -> 115000 | BS31: 46014 | BT31: 225000 | BU31: =Currentinvoices[[#This Row],[Invoice '# 17 amount]]*15% -> 33750 | BV31: =Currentinvoices[[#This Row],[Invoice '# 17 amount]]+Currentinvoices[[#This Row],[Invoice '# 17 vat]] -> 258750 | BW31: 46056 | BX31: 100000 | BY31: =Currentinvoices[[#This Row],[Invoice '# 18 amount]]*15% -> 15000 | BZ31: =Currentinvoices[[#This Row],[Invoice '# 18 vat]]+Currentinvoices[[#This Row],[Invoice '# 18 amount]] -> 115000 | CA31: 46140 | CB31: 75000 | CC31: =Currentinvoices[[#This Row],[Invoice '# 19 amount]]*15% -> 11250 | CD31: =Currentinvoices[[#This Row],[Invoice '# 19 vat]]+Currentinvoices[[#This Row],[Invoice '# 19 amount]] -> 86250 | DD31: =F31 -> 500000 | DE31: =DD31*15% -> 75000 | DF31: =DD31+DE31 -> 575000 | DG31: =SUMPRODUCT((MOD(COLUMN(G31:DB31)-COLUMN(G31),4)=1)*G31:DB31) -> 500000 | DH31: =SUMPRODUCT((MOD(COLUMN(G31:DB31)-COLUMN(H31),4)=2)*G31:DB31) -> 575000 | DI31: 1 | DJ31: =DI31*DD31 -> 500000 | DK31: =DJ31-DG31 -> 0
A32: EGEC - NIS2 | B32: MLTX-01-099 | C32: 15 | D32: Project support services 3 | F32: 1798340 | BC32: 45907 | BD32: ='EGEC - NIS2'!M202 -> 449585 | BE32: =BD32*15% -> 67437.75 | BF32: =BD32+BE32 -> 517022.75 | BG32: 45929 | BH32: ='EGEC - NIS2'!O202 -> 449585 | BI32: ='Invoices (2)'!$BH32*15% -> 67437.75 | BJ32: ='Invoices (2)'!$BH32+'Invoices (2)'!$BI32 -> 517022.75 | BS32: 46014 | BT32: 449585 | BU32: =Currentinvoices[[#This Row],[Invoice '# 17 amount]]*15% -> 67437.75 | BV32: =Currentinvoices[[#This Row],[Invoice '# 17 amount]]+Currentinvoices[[#This Row],[Invoice '# 17 vat]] -> 517022.75 | BW32: 46056 | BX32: 449585 | BY32: =Currentinvoices[[#This Row],[Invoice '# 18 amount]]*15% -> 67437.75 | BZ32: =Currentinvoices[[#This Row],[Invoice '# 18 vat]]+Currentinvoices[[#This Row],[Invoice '# 18 amount]] -> 517022.75 | DD32: ='Invoices (2)'!$F32 -> 1798340 | DE32: =DD32*15% -> 269751 | DF32: =DD32+DE32 -> 2068091 | DG32: =SUMPRODUCT((MOD(COLUMN(G32:DB32)-COLUMN(G32),4)=1)*G32:DB32) -> 1798340 | DH32: =SUMPRODUCT((MOD(COLUMN(G32:DB32)-COLUMN(H32),4)=2)*G32:DB32) -> 2068091 | DI32: 1 | DJ32: =DI32*DD32 -> 1798340 | DK32: =DJ32-DG32 -> 0
A33: EGEC - NIS2 | B33: MLTX-01-099 | C33: 16 | D33: Adaptation and Design of an Administrative Building Humanization in Riyadh 2 | E33: RDH2-01-031 | F33: 590000 | BG33: 45929 | BH33: ='EGEC - NIS2'!M217 -> 471999.23 | BI33: ='Invoices (2)'!$BH33*15% -> 70799.885 | BJ33: ='Invoices (2)'!$BH33+'Invoices (2)'!$BI33 -> 542799.11 | BO33: 45994 | BP33: ='EGEC - NIS2'!O217 -> 59000 | BQ33: ='Invoices (2)'!$BP33*15% -> 8850 | BR33: ='Invoices (2)'!$BQ33+'Invoices (2)'!$BP33 -> 67850 | BW33: 46056 | BX33: 59000 | BY33: =Currentinvoices[[#This Row],[Invoice '# 18 amount]]*15% -> 8850 | BZ33: =Currentinvoices[[#This Row],[Invoice '# 18 vat]]+Currentinvoices[[#This Row],[Invoice '# 18 amount]] -> 67850 | DD33: ='Invoices (2)'!$F33 -> 590000 | DE33: =DD33*15% -> 88500 | DF33: =DD33+DE33 -> 678500 | DG33: =SUMPRODUCT((MOD(COLUMN(G33:DB33)-COLUMN(G33),4)=1)*G33:DB33) -> 589999.23 | DH33: =SUMPRODUCT((MOD(COLUMN(G33:DB33)-COLUMN(H33),4)=2)*G33:DB33) -> 678499.11 | DI33: 0.95 | DJ33: =DI33*DD33 -> 560500 | DK33: =DJ33-DG33 -> -29499.23
A34: EGEC - NIS2 | B34: MLTX-01-099 | C34: 17 | D34: Ddevelopment The walkway In residential area Jeddah1 | F34: 170000 | CA34: 46140 | CB34: 119000 | CC34: =Currentinvoices[[#This Row],[Invoice '# 19 amount]]*15% -> 17850 | CD34: =Currentinvoices[[#This Row],[Invoice '# 19 vat]]+Currentinvoices[[#This Row],[Invoice '# 19 amount]] -> 136850 | CE34: 46190 | CF34: ='EGEC - NIS2'!O291 -> 51000.21 | CG34: =Currentinvoices[[#This Row],[Invoice '# 20 amount]]*15% -> 7650.0315 | CH34: =Currentinvoices[[#This Row],[Invoice '# 20 amount]]+Currentinvoices[[#This Row],[Invoice '# 20 vat]] -> 58650.241 | DD34: =Currentinvoices[[#This Row],[Task Value]] -> 170000 | DE34: =DD34*15% -> 25500 | DF34: =DD34+DE34 -> 195500 | DG34: =SUMPRODUCT((MOD(COLUMN(G34:DB34)-COLUMN(G34),4)=1)*G34:DB34) -> 170000.21 | DH34: =SUMPRODUCT((MOD(COLUMN(G34:DB34)-COLUMN(H34),4)=2)*G34:DB34) -> 195500.24 | DI34: 1 | DJ34: =DI34*DD34 -> 170000 | DK34: =DJ34-DG34 -> -0.21
A35: ENGICON | B35: RDH4-00-001 | C35: 1 | D35: Riyadh 4 Masterplan and Infrastructure concept design | F35: 27837620 | G35: 45480 | H35: =ENGICON!F45 -> 2361050.1 | I35: =H35*15% -> 354157.52 | J35: =H35+I35 -> 2715207.6 | K35: 45511 | L35: =ENGICON!H45 -> 3157746.7 | M35: =L35*15% -> 473662 | N35: =L35+M35 -> 3631408.6 | O35: 45535 | P35: =ENGICON!J45 -> 3983985.9 | Q35: =P35*15% -> 597597.89 | R35: =P35+Q35 -> 4581583.8 | S35: 45567 | T35: =ENGICON!L45 -> 3449998.3 | U35: =T35*15% -> 517499.74 | V35: =T35+U35 -> 3967498 | W35: 45636 | X35: =ENGICON!N45 -> 1820099.7 | Y35: =X35*15% -> 273014.96 | Z35: =X35+Y35 -> 2093114.7 | AA35: 45685 | AB35: =ENGICON!P45 -> 1000000 | AC35: =AB35*15% -> 150000 | AD35: =AB35+AC35 -> 1150000 | AE35: 45720 | AF35: =ENGICON!R45 -> 2695839.6 | AG35: =AF35*15% -> 404375.94 | AH35: =AF35+AG35 -> 3100215.6 | AI35: 45767 | AJ35: =ENGICON!T45 -> 2223402.9 | AK35: =AJ35*15% -> 333510.43 | AL35: =AJ35+AK35 -> 2556913.3 | AM35: 45789 | AN35: 1742432.4 | AO35: =AN35*15% -> 261364.86 | AP35: =AN35+AO35 -> 2003797.3 | AQ35: 45809 | AR35: 2619302.4 | AS35: =AR35*15% -> 392895.37 | AT35: =AR35+AS35 -> 3012197.8 | DD35: =F35 -> 27837620 | DE35: =DD35*15% -> 4175643 | DF35: =DD35+DE35 -> 32013263 | DG35: =SUMPRODUCT((MOD(COLUMN(G35:DB35)-COLUMN(G35),4)=1)*G35:DB35) -> 25053858 | DH35: =SUMPRODUCT((MOD(COLUMN(G35:DB35)-COLUMN(H35),4)=2)*G35:DB35) -> 28811937 | DI35: 1 | DJ35: =DI35*DD35 -> 27837620 | DK35: =DJ35-DG35 -> 2783762
A36: ENGICON | B36: RDH4-00-001 | DG36: =SUMPRODUCT((MOD(COLUMN(G36:DB36)-COLUMN(G36),4)=1)*G36:DB36) -> 0 | DH36: =SUMPRODUCT((MOD(COLUMN(G36:DB36)-COLUMN(H36),4)=2)*G36:DB36) -> 0
A37: EGEC - WAS | B37: WAS1-01-039 | C37: 1 | D37: Site development and buildings design for labour community area in WAS industrial city | E37: WAS1-01-035 | F37: 4421850 | G37: 45354 | H37: ='EGEC - WAS'!M17 -> 1726555 | I37: =H37*15% -> 258983.25 | J37: =H37+I37 -> 1985538.2 | O37: 45777 | P37: ='EGEC - WAS'!Q17 -> 1641704.7 | Q37: =P37*15% -> 246255.7 | R37: =P37+Q37 -> 1887960.4 | S37: 45807 | T37: ='EGEC - WAS'!S17 -> 611379 | U37: =T37*15% -> 91706.85 | V37: =T37+U37 -> 703085.85 | W37: 45865 | X37: ='EGEC - WAS'!U17 -> 221091 | Y37: =X37*15% -> 33163.65 | Z37: =X37+Y37 -> 254254.65 | AA37: 45901 | AB37: ='EGEC - WAS'!W17 -> 221120.33 | AC37: ='Invoices (2)'!$AB37*15% -> 33168.05 | AD37: ='Invoices (2)'!$AB37+'Invoices (2)'!$AC37 -> 254288.38 | DD37: =F37 -> 4421850 | DE37: =DD37*15% -> 663277.5 | DF37: =DD37+DE37 -> 5085127.5 | DG37: =SUMPRODUCT((MOD(COLUMN(G37:DB37)-COLUMN(G37),4)=1)*G37:DB37) -> 4421850 | DH37: =SUMPRODUCT((MOD(COLUMN(G37:DB37)-COLUMN(H37),4)=2)*G37:DB37) -> 5085127.5 | DI37: 1 | DJ37: =DI37*DD37 -> 4421850 | DK37: =DJ37-DG37 -> -0.0099999998
A38: EGEC - WAS | B38: WAS1-01-039 | C38: 2 | D38: Design commercial area with fuel station in Waad AlShamal | E38: WAS-01-034 | F38: 650000 | K38: 45395 | L38: ='EGEC - WAS'!O36 -> 195000 | M38: =L38*15% -> 29250 | N38: =L38+M38 -> 224250 | O38: 45777 | P38: ='EGEC - WAS'!Q36 -> 227500 | Q38: =P38*15% -> 34125 | R38: =P38+Q38 -> 261625 | S38: 45807 | T38: ='EGEC - WAS'!S36 -> 227500 | U38: =T38*15% -> 34125 | V38: =T38+U38 -> 261625 | DD38: =F38 -> 650000 | DE38: =DD38*15% -> 97500 | DF38: =DD38+DE38 -> 747500 | DG38: =SUMPRODUCT((MOD(COLUMN(G38:DB38)-COLUMN(G38),4)=1)*G38:DB38) -> 650000 | DH38: =SUMPRODUCT((MOD(COLUMN(G38:DB38)-COLUMN(H38),4)=2)*G38:DB38) -> 747500 | DI38: 1 | DJ38: =DI38*DD38 -> 650000 | DK38: =DJ38-DG38 -> 0
A39: EGEC - WAS | B39: WAS1-01-039 | C39: 4 | D39: Development of labour camps in: DAM03, NJR, MKH2, JDH2, SUD, ASR1 | E39: MLTX-01-119 | F39: 1150000 | W39: 45865 | X39: 115000 | Y39: =X39*15% -> 17250 | Z39: =X39+Y39 -> 132250 | AE39: 45917 | AF39: 460000 | AG39: ='Invoices (2)'!$AF39*15% -> 69000 | AH39: ='Invoices (2)'!$AF39+'Invoices (2)'!$AG39 -> 529000 | AI39: 45956 | AJ39: 575000 | AK39: ='Invoices (2)'!$AJ39*15% -> 86250 | AL39: ='Invoices (2)'!$AJ39+'Invoices (2)'!$AK39 -> 661250 | DD39: =F39 -> 1150000 | DE39: =DD39*15% -> 172500 | DF39: =DD39+DE39 -> 1322500 | DG39: =SUMPRODUCT((MOD(COLUMN(G39:DB39)-COLUMN(G39),4)=1)*G39:DB39) -> 1150000 | DH39: =SUMPRODUCT((MOD(COLUMN(G39:DB39)-COLUMN(H39),4)=2)*G39:DB39) -> 1322500 | DI39: 1 | DJ39: =DI39*DD39 -> 1150000 | DK39: =DJ39-DG39 -> 0
A40: EGEC - WAS | B40: WAS1-01-039 | C40: 4 | D40: Project support services 4 | F40: 853820 | AM40: 45994 | AN40: ='EGEC - WAS'!M65 -> 284606.76 | AO40: ='Invoices (2)'!$AN40*15% -> 42691.014 | AP40: ='Invoices (2)'!$AN40+'Invoices (2)'!$AO40 -> 327297.77 | AQ40: 46056 | AR40: ='EGEC - WAS'!O65 -> 355759.13 | AS40: =Currentinvoices[[#This Row],[Invoice '# 10 amount]]*15% -> 53363.87 | AT40: =Currentinvoices[[#This Row],[Invoice '# 10 amount]]+Currentinvoices[[#This Row],[Invoice '# 10 vat]] -> 409123 | AU40: 46205 | AV40: 213455 | AW40: =Currentinvoices[[#This Row],[Invoice '# 11 amount]]*15% -> 32018.25 | AX40: =Currentinvoices[[#This Row],[Invoice '# 11 vat]]+Currentinvoices[[#This Row],[Invoice '# 11 amount]] -> 245473.25 | DD40: =Currentinvoices[[#This Row],[Task Value]] -> 853820 | DE40: =DD40*15% -> 128073 | DF40: =DD40+DE40 -> 981893 | DG40: =SUMPRODUCT((MOD(COLUMN(G40:DB40)-COLUMN(G40),4)=1)*G40:DB40) -> 853820.89 | DH40: =SUMPRODUCT((MOD(COLUMN(G40:DB40)-COLUMN(H40),4)=2)*G40:DB40) -> 981894.02 | DI40: 1 | DJ40: =DI40*DD40 -> 853820 | DK40: =DJ40-DG40 -> -0.89
A41: ENGICON - RDH4 | B41: RDH4-01-002 | C41: 1 | D41: Design work for entrance and facilities for Riyadh 4 | F41: 7025000 | G41: 45684 | H41: ='ENGICON-RDH4'!F11 -> 1999999.9 | I41: =H41*15% -> 299999.98 | J41: =H41+I41 -> 2299999.8 | K41: 45839 | L41: ='ENGICON-RDH4'!H11 -> 2350000 | M41: =L41*15% -> 352500 | N41: =L41+M41 -> 2702500 | O41: 45848 | P41: ='ENGICON-RDH4'!J11 -> 2675000 | Q41: =P41*15% -> 401250 | R41: =P41+Q41 -> 3076250 | DD41: =F41 -> 7025000 | DE41: =DD41*15% -> 1053750 | DF41: =DD41+DE41 -> 8078750 | DG41: =SUMPRODUCT((MOD(COLUMN(G41:DB41)-COLUMN(G41),4)=1)*G41:DB41) -> 7024999.8 | DH41: =SUMPRODUCT((MOD(COLUMN(G41:DB41)-COLUMN(H41),4)=2)*G41:DB41) -> 8078749.8 | DI41: 1 | DJ41: =DI41*DD41 -> 7025000 | DK41: =DJ41-DG41 -> 0.15
A42: ENGICON - RDH4 | B42: RDH4-01-002 | DD42: =SUM(DD41:DD41) -> 7025000 | DE42: =SUM(DE41:DE41) -> 1053750 | DF42: =SUM(DF41:DF41) -> 8078750 | DG42: =SUMPRODUCT((MOD(COLUMN(G42:DB42)-COLUMN(G42),4)=1)*G42:DB42) -> 0 | DH42: =SUMPRODUCT((MOD(COLUMN(G42:DB42)-COLUMN(H42),4)=2)*G42:DB42) -> 0 | DJ42: =SUM(DJ41:DJ41) -> 7025000 | DK42: =SUM(DK41:DK41) -> 0.15
A43: Dar AlRiyadh 2 | B43: MLTX-01-100 | F43: 1 | G43: 45645 | H43: 40768 | I43: =H43*15% -> 6115.2 | J43: =H43+I43 -> 46883.2 | DG43: =SUMPRODUCT((MOD(COLUMN(G43:DB43)-COLUMN(G43),4)=1)*G43:DB43) -> 40768 | DH43: =SUMPRODUCT((MOD(COLUMN(G43:DB43)-COLUMN(H43),4)=2)*G43:DB43) -> 46883.2 | DI43: 1 | DJ43: =DI43*DD43 -> 0 | DK43: =DJ43-DG43 -> -40768
A44: Dar AlRiyadh 2 | B44: MLTX-01-100 | F44: 2 | G44: 45645 | H44: 866679.33 | I44: =H44*15% -> 130001.9 | J44: =H44+I44 -> 996681.23 | DG44: =SUMPRODUCT((MOD(COLUMN(G44:DB44)-COLUMN(G44),4)=1)*G44:DB44) -> 866679.33 | DH44: =SUMPRODUCT((MOD(COLUMN(G44:DB44)-COLUMN(H44),4)=2)*G44:DB44) -> 996681.23 | DI44: 1 | DJ44: =DI44*DD44 -> 0 | DK44: =DJ44-DG44 -> -866679.33
A45: Dar AlRiyadh 2 | B45: MLTX-01-100 | F45: 3 | G45: 45658 | H45: 1114782 | I45: =H45*15% -> 167217.3 | J45: =H45+I45 -> 1281999.3 | DG45: =SUMPRODUCT((MOD(COLUMN(G45:DB45)-COLUMN(G45),4)=1)*G45:DB45) -> 1114782 | DH45: =SUMPRODUCT((MOD(COLUMN(G45:DB45)-COLUMN(H45),4)=2)*G45:DB45) -> 1281999.3 | DI45: 1 | DJ45: =DI45*DD45 -> 0 | DK45: =DJ45-DG45 -> -1114782
A46: Dar AlRiyadh 2 | B46: MLTX-01-100 | F46: 4 | G46: 45692 | H46: 1206719.1 | I46: =H46*15% -> 181007.86 | J46: =H46+I46 -> 1387726.9 | DG46: =SUMPRODUCT((MOD(COLUMN(G46:DB46)-COLUMN(G46),4)=1)*G46:DB46) -> 1206719.1 | DH46: =SUMPRODUCT((MOD(COLUMN(G46:DB46)-COLUMN(H46),4)=2)*G46:DB46) -> 1387726.9 | DI46: 1 | DJ46: =DI46*DD46 -> 0 | DK46: =DJ46-DG46 -> -1206719.1
A47: Dar AlRiyadh 2 | B47: MLTX-01-100 | F47: 5 | G47: 45719 | H47: 1200633.9 | I47: =H47*15% -> 180095.09 | J47: =H47+I47 -> 1380729 | DG47: =SUMPRODUCT((MOD(COLUMN(G47:DB47)-COLUMN(G47),4)=1)*G47:DB47) -> 1200633.9 | DH47: =SUMPRODUCT((MOD(COLUMN(G47:DB47)-COLUMN(H47),4)=2)*G47:DB47) -> 1380729 | DI47: 1 | DJ47: =DI47*DD47 -> 0 | DK47: =DJ47-DG47 -> -1200633.9
A48: Dar AlRiyadh 2 | B48: MLTX-01-100 | F48: 6 | G48: 45755 | H48: 1118030.4 | I48: =H48*15% -> 167704.56 | J48: =H48+I48 -> 1285734.9 | DG48: =SUMPRODUCT((MOD(COLUMN(G48:DB48)-COLUMN(G48),4)=1)*G48:DB48) -> 1118030.4 | DH48: =SUMPRODUCT((MOD(COLUMN(G48:DB48)-COLUMN(H48),4)=2)*G48:DB48) -> 1285734.9 | DI48: 1 | DJ48: =DI48*DD48 -> 0 | DK48: =DJ48-DG48 -> -1118030.4
A49: Dar AlRiyadh 2 | B49: MLTX-01-100 | F49: 7 | G49: 45781 | H49: 1216426.3 | I49: =H49*15% -> 182463.95 | J49: =H49+I49 -> 1398890.2 | DG49: =SUMPRODUCT((MOD(COLUMN(G49:DB49)-COLUMN(G49),4)=1)*G49:DB49) -> 1216426.3 | DH49: =SUMPRODUCT((MOD(COLUMN(G49:DB49)-COLUMN(H49),4)=2)*G49:DB49) -> 1398890.2 | DI49: 1 | DJ49: =DI49*DD49 -> 0 | DK49: =DJ49-DG49 -> -1216426.3
A50: Dar AlRiyadh 2 | B50: MLTX-01-100 | F50: 8 | G50: 45809 | H50: 1310618.7 | I50: =H50*15% -> 196592.8 | J50: =H50+I50 -> 1507211.5 | DG50: =SUMPRODUCT((MOD(COLUMN(G50:DB50)-COLUMN(G50),4)=1)*G50:DB50) -> 1310618.7 | DH50: =SUMPRODUCT((MOD(COLUMN(G50:DB50)-COLUMN(H50),4)=2)*G50:DB50) -> 1507211.5 | DI50: 1 | DJ50: =DI50*DD50 -> 0 | DK50: =DJ50-DG50 -> -1310618.7
A51: Dar AlRiyadh 2 | B51: MLTX-01-100 | F51: 9 | G51: 45840 | H51: 1147200.4 | I51: =H51*15% -> 172080.06 | J51: =H51+I51 -> 1319280.5 | DG51: =SUMPRODUCT((MOD(COLUMN(G51:DB51)-COLUMN(G51),4)=1)*G51:DB51) -> 1147200.4 | DH51: =SUMPRODUCT((MOD(COLUMN(G51:DB51)-COLUMN(H51),4)=2)*G51:DB51) -> 1319280.5 | DI51: 1 | DJ51: =DI51*DD51 -> 0 | DK51: =DJ51-DG51 -> -1147200.4
A52: Dar AlRiyadh 2 | B52: MLTX-01-100 | F52: 10 | G52: 45873 | H52: 1122204.5 | I52: =H52*15% -> 168330.68 | J52: =H52+I52 -> 1290535.2 | DG52: =SUMPRODUCT((MOD(COLUMN(G52:DB52)-COLUMN(G52),4)=1)*G52:DB52) -> 1122204.5 | DH52: =SUMPRODUCT((MOD(COLUMN(G52:DB52)-COLUMN(H52),4)=2)*G52:DB52) -> 1290535.2 | DI52: 1 | DJ52: =DI52*DD52 -> 0 | DK52: =DJ52-DG52 -> -1122204.5
A53: Dar AlRiyadh 2 | B53: MLTX-01-100 | F53: 11 | G53: 45901 | H53: 1165613.3 | I53: =H53*15% -> 174841.99 | J53: =H53+I53 -> 1340455.3 | DG53: =SUMPRODUCT((MOD(COLUMN(G53:DB53)-COLUMN(G53),4)=1)*G53:DB53) -> 1165613.3 | DH53: =SUMPRODUCT((MOD(COLUMN(G53:DB53)-COLUMN(H53),4)=2)*G53:DB53) -> 1340455.3 | DI53: 1 | DJ53: =DI53*DD53 -> 0 | DK53: =DJ53-DG53 -> -1165613.3
A54: Dar AlRiyadh 2 | B54: MLTX-01-100 | F54: 12 | G54: 45931 | H54: 1069979.7 | I54: =H54*15% -> 160496.95 | J54: =H54+I54 -> 1230476.6 | DG54: =SUMPRODUCT((MOD(COLUMN(G54:DB54)-COLUMN(G54),4)=1)*G54:DB54) -> 1069979.7 | DH54: =SUMPRODUCT((MOD(COLUMN(G54:DB54)-COLUMN(H54),4)=2)*G54:DB54) -> 1230476.6 | DI54: 1 | DJ54: =DI54*DD54 -> 0 | DK54: =DJ54-DG54 -> -1069979.7
... A63: Dar AlRiyadh 2 | B63: MLTX-01-100 | F63: 21 | G63: 46204 | H63: 1098411.4 | I63: =H63*15% -> 164761.72 | J63: =H63+I63 -> 1263173.2 | DG63: =SUMPRODUCT((MOD(COLUMN(G63:DB63)-COLUMN(G63),4)=1)*G63:DB63) -> 1098411.4 | DH63: =SUMPRODUCT((MOD(COLUMN(G63:DB63)-COLUMN(H63),4)=2)*G63:DB63) -> 1263173.2 | DI63: 1 | DJ63: =DI63*DD63 -> 0 | DK63: =DJ63-DG63 -> -1098411.4
A64: Dar AlRiyadh 2 | B64: MLTX-01-100 | DG64: =SUMPRODUCT((MOD(COLUMN(G64:DB64)-COLUMN(G64),4)=1)*G64:DB64) -> 0 | DH64: =SUMPRODUCT((MOD(COLUMN(G64:DB64)-COLUMN(H64),4)=2)*G64:DB64) -> 0
A65: Dar AlRiyadh 2 | B65: MLTX-01-100 | DG65: =SUMPRODUCT((MOD(COLUMN(G65:DB65)-COLUMN(G65),4)=1)*G65:DB65) -> 0 | DH65: =SUMPRODUCT((MOD(COLUMN(G65:DB65)-COLUMN(H65),4)=2)*G65:DB65) -> 0
A66: ENGICON - Package1 | B66: MLTX-01-098 | C66: 1 | D66: NIS Design adaptation of RBF 450 , 900 m2 | F66: 7940002 | G66: 45685 | H66: ='Engicon - P1'!M31 -> 3062572.2 | I66: =H66*15% -> 459385.83 | J66: =H66+I66 -> 3521958 | K66: 45848 | L66: ='Engicon - P1'!O31 -> 1814857.6 | M66: =L66*15% -> 272228.64 | N66: =L66+M66 -> 2087086.2 | AA66: 45938 | AB66: ='Engicon - P1'!S31 -> 2296929.2 | AC66: =AB66*15% -> 344539.37 | AD66: =AB66+AC66 -> 2641468.5 | AI66: 45991 | AJ66: ='Engicon - P1'!U31 -> 765643.05 | AK66: =AJ66*15% -> 114846.46 | AL66: =AJ66+AK66 -> 880489.51 | DD66: =F66 -> 7940002 | DE66: =DD66*15% -> 1191000.3 | DF66: =DD66+DE66 -> 9131002.3 | DG66: =SUMPRODUCT((MOD(COLUMN(G66:DB66)-COLUMN(G66),4)=1)*G66:DB66) -> 7940002 | DH66: =SUMPRODUCT((MOD(COLUMN(G66:DB66)-COLUMN(H66),4)=2)*G66:DB66) -> 9131002.3 | DI66: 1 | DJ66: =DI66*DD66 -> 7940002 | DK66: =DJ66-DG66 -> -0.010000001
A67: ENGICON - Package1 | B67: MLTX-01-098 | C67: 2 | D67: Detailed design of lake park and supply connection for Sudair Industrial City | E67: SUD1-01-033 | F67: 1658659 | G67: 45685 | H67: ='Engicon - P1'!M15 -> 746396.55 | I67: =H67*15% -> 111959.48 | J67: =H67+I67 -> 858356.03 | K67: 45848 | L67: ='Engicon - P1'!O15 -> 912262.45 | M67: =L67*15% -> 136839.37 | N67: =L67+M67 -> 1049101.8 | DD67: =F67 -> 1658659 | DE67: =DD67*15% -> 248798.85 | DF67: =DD67+DE67 -> 1907457.9 | DG67: =SUMPRODUCT((MOD(COLUMN(G67:DB67)-COLUMN(G67),4)=1)*G67:DB67) -> 1658659 | DH67: =SUMPRODUCT((MOD(COLUMN(G67:DB67)-COLUMN(H67),4)=2)*G67:DB67) -> 1907457.9 | DI67: 1 | DJ67: =DI67*DD67 -> 1658659 | DK67: =DJ67-DG67 -> 0
A68: ENGICON - Package1 | B68: MLTX-01-098 | C68: 3 | D68: Technology Zone- Asfan | E68: ASFT-01-001 | F68: 1192999 | O68: 45859 | P68: ='Engicon - P1'!Q42 -> 119240 | Q68: =P68*15% -> 17886 | R68: =P68+Q68 -> 137126 | S68: 45893 | T68: ='Engicon - P1'!S42 -> 417907 | U68: =T68*15% -> 62686.05 | V68: =T68+U68 -> 480593.05 | W68: 45929 | X68: ='Engicon - P1'!W42 -> 268306 | Y68: =X68*15% -> 40245.9 | Z68: =X68+Y68 -> 308551.9 | AE68: 45959 | AF68: ='Engicon - P1'!Y42 -> 387546 | AG68: =AF68*15% -> 58131.9 | AH68: ='Invoices (2)'!$AF68+'Invoices (2)'!$AG68 -> 445677.9 | DD68: =F68 -> 1192999 | DE68: =DD68*15% -> 178949.85 | DF68: =DD68+DE68 -> 1371948.9 | DG68: =SUMPRODUCT((MOD(COLUMN(G68:DB68)-COLUMN(G68),4)=1)*G68:DB68) -> 1192999 | DH68: =SUMPRODUCT((MOD(COLUMN(G68:DB68)-COLUMN(H68),4)=2)*G68:DB68) -> 1371948.9 | DI68: 1 | DJ68: =DI68*DD68 -> 1192999 | DK68: =DJ68-DG68 -> 0
A69: ENGICON - Package1 | B69: MLTX-01-098 | C69: 4 | D69: Technology Zone- Khumra | E69: KUMT-01-001 | F69: 1318399 | O69: 45859 | P69: ='Engicon - P1'!Q55 -> 131844 | Q69: =P69*15% -> 19776.6 | R69: =P69+Q69 -> 151620.6 | S69: 45893 | T69: ='Engicon - P1'!S55 -> 461503 | U69: =T69*15% -> 69225.45 | V69: =T69+U69 -> 530728.45 | W69: 45929 | X69: ='Engicon - P1'!W55 -> 296604 | Y69: =X69*15% -> 44490.6 | Z69: =X69+Y69 -> 341094.6 | AE69: 45959 | AF69: ='Engicon - P1'!Y55 -> 428448 | AG69: =AF69*15% -> 64267.2 | AH69: ='Invoices (2)'!$AF69+'Invoices (2)'!$AG69 -> 492715.2 | DD69: =F69 -> 1318399 | DE69: =DD69*15% -> 197759.85 | DF69: =DD69+DE69 -> 1516158.9 | DG69: =SUMPRODUCT((MOD(COLUMN(G69:DB69)-COLUMN(G69),4)=1)*G69:DB69) -> 1318399 | DH69: =SUMPRODUCT((MOD(COLUMN(G69:DB69)-COLUMN(H69),4)=2)*G69:DB69) -> 1516158.8 | DI69: 1 | DJ69: =DI69*DD69 -> 1318399 | DK69: =DJ69-DG69 -> 0
A70: ENGICON - Package1 | B70: MLTX-01-098 | C70: 5 | D70: Riyadh 3 Business incubators | E70: RDH3-01-012 | F70: 1230000 | AE70: 45959 | AF70: ='Engicon - P1'!M66 -> 123052 | AG70: =AF70*15% -> 18457.8 | AH70: ='Invoices (2)'!$AF70+'Invoices (2)'!$AG70 -> 141509.8 | AI70: 45991 | AJ70: ='Engicon - P1'!O66 -> 122987 | AK70: =AJ70*15% -> 18448.05 | AL70: =AJ70+AK70 -> 141435.05 | AM70: 46005 | AN70: 122987 | AO70: =Currentinvoices[[#This Row],[Invoice '# 9 amount]]*15% -> 18448.05 | AP70: =Currentinvoices[[#This Row],[Invoice '# 9 vat]]+Currentinvoices[[#This Row],[Invoice '# 9 amount]] -> 141435.05 | AQ70: 46057 | AR70: ='Engicon - P1'!Q66 -> 676477 | AS70: =Currentinvoices[[#This Row],[Invoice '# 10 amount]]*15% -> 101471.55 | AT70: =Currentinvoices[[#This Row],[Invoice '# 10 amount]]+Currentinvoices[[#This Row],[Invoice '# 10 vat]] -> 777948.55 | AU70: 46125 | AV70: 184497 | AW70: =Currentinvoices[[#This Row],[Invoice '# 11 amount]]*15% -> 27674.55 | AX70: =Currentinvoices[[#This Row],[Invoice '# 11 amount]]+Currentinvoices[[#This Row],[Invoice '# 11 vat]] -> 212171.55 | DD70: =F70 -> 1230000 | DE70: =DD70*15% -> 184500 | DF70: =DD70+DE70 -> 1414500 | DG70: =SUMPRODUCT((MOD(COLUMN(G70:DB70)-COLUMN(G70),4)=1)*G70:DB70) -> 1230000 | DH70: =SUMPRODUCT((MOD(COLUMN(G70:DB70)-COLUMN(H70),4)=2)*G70:DB70) -> 1414500 | DI70: 1 | DJ70: =DI70*DD70 -> 1230000 | DK70: =DJ70-DG70 -> 0
A71: ENGICON - Package1 | B71: MLTX-01-098 | C71: 6 | D71: Bonded Zone in Jeddah 3rd Industrial City-MSC | F71: 2210695 | AU71: 46125 | AV71: 331568 | AW71: =Currentinvoices[[#This Row],[Invoice '# 11 amount]]*15% -> 49735.2 | AX71: =Currentinvoices[[#This Row],[Invoice '# 11 amount]]+Currentinvoices[[#This Row],[Invoice '# 11 vat]] -> 381303.2 | AY71: 46154 | AZ71: 773781 | BA71: =Currentinvoices[[#This Row],[Invoice '# 12 amount]]*15% -> 116067.15 | BB71: =Currentinvoices[[#This Row],[Invoice '# 12 vat]]+Currentinvoices[[#This Row],[Invoice '# 12 amount]] -> 889848.15 | BG71: 46218 | BH71: 442105 | BI71: =Currentinvoices[[#This Row],[Invoice '# 14 amount]]*15% -> 66315.75 | BJ71: =Currentinvoices[[#This Row],[Invoice '# 14 amount]]+Currentinvoices[[#This Row],[Invoice '# 14 vat]] -> 508420.75 | DD71: =Currentinvoices[[#This Row],[Task Value]] -> 2210695 | DE71: =DD71*15% -> 331604.25 | DF71: =DD71+DE71 -> 2542299.2 | DG71: =SUMPRODUCT((MOD(COLUMN(G71:DB71)-COLUMN(G71),4)=1)*G71:DB71) -> 1547454 | DH71: =SUMPRODUCT((MOD(COLUMN(G71:DB71)-COLUMN(H71),4)=2)*G71:DB71) -> 1779572.1 | DI71: 0.9 | DJ71: =DI71*DD71 -> 1989625.5 | DK71: =DJ71-DG71 -> 442171.5
A72: ENGICON - Package1 | B72: MLTX-01-098 | C72: 7 | D72: Adimn Building In Riyadh 4 | F72: 1000628 | BC72: 46196 | BD72: 75107.5 | BE72: =Currentinvoices[[#This Row],[Invoice '# 13 amount]]*15% -> 11266.125 | BF72: =Currentinvoices[[#This Row],[Invoice '# 13 vat]]+Currentinvoices[[#This Row],[Invoice '# 13 amount]] -> 86373.625 | DD72: =Currentinvoices[[#This Row],[Task Value]] -> 1000628 | DE72: =DD72*15% -> 150094.2 | DF72: =DD72+DE72 -> 1150722.2 | DG72: =SUMPRODUCT((MOD(COLUMN(G72:DB72)-COLUMN(G72),4)=1)*G72:DB72) -> 75107.5 | DH72: =SUMPRODUCT((MOD(COLUMN(G72:DB72)-COLUMN(H72),4)=2)*G72:DB72) -> 86373.625 | DI72: 0.22 | DJ72: =DI72*DD72 -> 220138.16 | DK72: =DJ72-DG72 -> 145030.66
A73: Meinhardt (KHJ- FOOD) | B73: KHJ1-01-020 | C73: 1 | D73: Development of Design guidelines, production strategy, and prototype packages for mid-sized RBFs | F73: 2997130 | G73: 45939 | H73: =MEINHARDT!R12 -> 299713 | I73: ='Invoices (2)'!$H73*15% -> 44956.95 | J73: ='Invoices (2)'!$H73+'Invoices (2)'!$I73 -> 344669.95 | K73: 45951 | L73: =MEINHARDT!T12 -> 299713 | M73: ='Invoices (2)'!$H73*15% -> 44956.95 | N73: ='Invoices (2)'!$H73+'Invoices (2)'!$I73 -> 344669.95 | O73: 45959 | P73: =MEINHARDT!V12 -> 599426.07 | Q73: ='Invoices (2)'!$P73*15% -> 89913.911 | R73: ='Invoices (2)'!$P73+'Invoices (2)'!$Q73 -> 689339.98 | S73: 45999 | T73: 157349.33 | U73: =Currentinvoices[[#This Row],[Invoice '# 4 amount]]*15% -> 23602.399 | V73: =Currentinvoices[[#This Row],[Invoice '# 4 vat]]+Currentinvoices[[#This Row],[Invoice '# 4 amount]] -> 180951.73 | W73: 45999 | X73: 157349.33 | Y73: =Currentinvoices[[#This Row],[Invoice '# 4 amount]]*15% -> 23602.399 | Z73: =Currentinvoices[[#This Row],[Invoice '# 4 vat]]+Currentinvoices[[#This Row],[Invoice '# 4 amount]] -> 180951.73 | AA73: 46028 | AB73: =MEINHARDT!AB12 -> 134870.85 | AC73: =Currentinvoices[[#This Row],[Invoice '# 6 amount]]*15% -> 20230.627 | AD73: =Currentinvoices[[#This Row],[Invoice '# 6 vat]]+Currentinvoices[[#This Row],[Invoice '# 6 amount]] -> 155101.48 | AE73: 46084 | AF73: 569454.69 | AG73: =Currentinvoices[[#This Row],[Invoice '# 7 amount]]*15% -> 85418.203 | AH73: =Currentinvoices[[#This Row],[Invoice '# 7 vat]]+Currentinvoices[[#This Row],[Invoice '# 7 amount]] -> 654872.89 | AI73: 46131 | AJ73: 779253.66 | AK73: =15%*Currentinvoices[[#This Row],[Invoice '# 8 amount]] -> 116888.05 | AL73: =Currentinvoices[[#This Row],[Invoice '# 8 vat]]+Currentinvoices[[#This Row],[Invoice '# 8 amount]] -> 896141.71 | DD73: =F73 -> 2997130 | DE73: =DD73*15% -> 449569.5 | DF73: =DD73+DE73 -> 3446699.5 | DG73: =SUMPRODUCT((MOD(COLUMN(G73:DB73)-COLUMN(G73),4)=1)*G73:DB73) -> 2997129.9 | DH73: =SUMPRODUCT((MOD(COLUMN(G73:DB73)-COLUMN(H73),4)=2)*G73:DB73) -> 3446699.4 | DI73: 1 | DJ73: =DI73*DD73 -> 2997130 | DK73: =DJ73-DG73 -> 0.069999999
A74: Meinhardt (KHJ- FOOD) | B74: KHJ1-01-020 | C74: 2 | D74: Development of full Design for Multi - Story Building for foure Sities | F74: 5188500 | AM74: 46191 | AN74: 255925 | AO74: =Currentinvoices[[#This Row],[Invoice '# 9 amount]]*15% -> 38388.75 | AP74: =Currentinvoices[[#This Row],[Invoice '# 9 vat]]+Currentinvoices[[#This Row],[Invoice '# 9 amount]] -> 294313.75 | AY74: 46253 | AZ74: 511850 | BA74: =Currentinvoices[[#This Row],[Invoice '# 12 amount]]*15% -> 76777.5 | BB74: =Currentinvoices[[#This Row],[Invoice '# 12 vat]]+Currentinvoices[[#This Row],[Invoice '# 12 amount]] -> 588627.5 | DD74: 5188500 | DE74: =DD74*15% -> 778275 | DF74: =DD74+DE74 -> 5966775 | DG74: =SUMPRODUCT((MOD(COLUMN(G74:DB74)-COLUMN(G74),4)=1)*G74:DB74) -> 767775 | DH74: =SUMPRODUCT((MOD(COLUMN(G74:DB74)-COLUMN(H74),4)=2)*G74:DB74) -> 882941.25 | DI74: 0.25 | DJ74: =DI74*DD74 -> 1297125 | DK74: =DJ74-DG74 -> 529350
A75: Meinhardt (KHJ- FOOD) | B75: KHJ1-01-020 | C75: 3 | D75: Development of full Design Of Mid RBFs for Food , Machinery & Equipment and Pharmceutical Cluster | F75: 3500000 | AM75: 46191 | AN75: 175000 | AO75: =Currentinvoices[[#This Row],[Invoice '# 9 amount]]*15% -> 26250 | AP75: =Currentinvoices[[#This Row],[Invoice '# 9 vat]]+Currentinvoices[[#This Row],[Invoice '# 9 amount]] -> 201250 | DD75: 3500000 | DE75: =DD75*15% -> 525000 | DF75: =DD75+DE75 -> 4025000 | DG75: =SUMPRODUCT((MOD(COLUMN(G75:DB75)-COLUMN(G75),4)=1)*G75:DB75) -> 175000 | DH75: =SUMPRODUCT((MOD(COLUMN(G75:DB75)-COLUMN(H75),4)=2)*G75:DB75) -> 201250 | DI75: 0.05 | DJ75: =DI75*DD75 -> 175000 | DK75: =DJ75-DG75 -> 0
A76: ENGICON - RDH4 PH2 | B76: RDH4-01-003 | C76: 1 | D76: 70 RBF's in Riyadh 04 | E76: RDH4-01-003 | F76: 2490457 | G76: 45966 | H76: ='ENGICON RIYADH 4 P2 '!M19 -> 747154 | I76: ='Invoices (2)'!$H76*15% -> 112073.1 | J76: ='Invoices (2)'!$H76+'Invoices (2)'!$I76 -> 859227.1 | L76: ='ENGICON RIYADH 4 P2 '!O19 -> 622572 | M76: ='Invoices (2)'!$L76*15% -> 93385.8 | N76: ='Invoices (2)'!$L76+'Invoices (2)'!$M76 -> 715957.8 | O76: 46013 | P76: 622572 | Q76: =Currentinvoices[[#This Row],[Invoice '# 3 amount]]*15% -> 93385.8 | R76: =Currentinvoices[[#This Row],[Invoice '# 3 vat]]+Currentinvoices[[#This Row],[Invoice '# 3 amount]] -> 715957.8 | W76: 46125 | X76: ='ENGICON RIYADH 4 P2 '!S19 -> 498159 | Y76: =15%*Currentinvoices[[#This Row],[Invoice '# 5 amount]] -> 74723.85 | Z76: =Currentinvoices[[#This Row],[Invoice '# 5 vat]]+Currentinvoices[[#This Row],[Invoice '# 5 amount]] -> 572882.85 | DD76: =F76 -> 2490457 | DE76: =DD76*15% -> 373568.55 | DF76: =DD76+DE76 -> 2864025.5 | DG76: =SUMPRODUCT((MOD(COLUMN(G76:DB76)-COLUMN(G76),4)=1)*G76:DB76) -> 2490457 | DH76: =SUMPRODUCT((MOD(COLUMN(G76:DB76)-COLUMN(H76),4)=2)*G76:DB76) -> 2864025.6 | DI76: 1 | DJ76: =DI76*DD76 -> 2490457 | DK76: =DJ76-DG76 -> 0
A77: ENGICON - RDH4 PH2 | B77: RDH4-01-003 | C77: 2 | D77: Development for the Masterplan and Concept Infrastructure for the expansion of Riyadh 4 industrial city | E77: RDH4-01-005 | F77: 24501677 | G77: 45966 | H77: ='ENGICON RIYADH 4 P2 '!M31 -> 7963335 | I77: ='Invoices (2)'!$H77*15% -> 1194500.2 | J77: ='Invoices (2)'!$H77+'Invoices (2)'!$I77 -> 9157835.2 | O77: 46013 | P77: 3062800.5 | Q77: =Currentinvoices[[#This Row],[Invoice '# 3 amount]]*15% -> 459420.08 | R77: =Currentinvoices[[#This Row],[Invoice '# 3 vat]]+Currentinvoices[[#This Row],[Invoice '# 3 amount]] -> 3522220.6 | S77: 46114 | T77: ='ENGICON RIYADH 4 P2 '!Q31 -> 2450222.5 | U77: =Currentinvoices[[#This Row],[Invoice '# 4 amount]]*15% -> 367533.38 | V77: =Currentinvoices[[#This Row],[Invoice '# 4 vat]]+Currentinvoices[[#This Row],[Invoice '# 4 amount]] -> 2817755.9 | AA77: 46127 | AB77: ='ENGICON RIYADH 4 P2 '!S31 -> 5512659.5 | AC77: =15%*Currentinvoices[[#This Row],[Invoice '# 6 amount]] -> 826898.92 | AD77: =Currentinvoices[[#This Row],[Invoice '# 6 vat]]+Currentinvoices[[#This Row],[Invoice '# 6 amount]] -> 6339558.4 | AI77: 46209 | AJ77: 5512659.5 | AK77: =Currentinvoices[[#This Row],[Invoice '# 8 amount]]*15% -> 826898.92 | AL77: =Currentinvoices[[#This Row],[Invoice '# 8 vat]]+Currentinvoices[[#This Row],[Invoice '# 8 amount]] -> 6339558.4 | DD77: =F77 -> 24501677 | DE77: =DD77*15% -> 3675251.5 | DF77: =DD77+DE77 -> 28176929 | DG77: =SUMPRODUCT((MOD(COLUMN(G77:DB77)-COLUMN(G77),4)=1)*G77:DB77) -> 24501677 | DH77: =SUMPRODUCT((MOD(COLUMN(G77:DB77)-COLUMN(H77),4)=2)*G77:DB77) -> 28176929 | DI77: 1 | DJ77: =DI77*DD77 -> 24501677 | DK77: =DJ77-DG77 -> 0
A78: ENGICON - RDH4 PH2 | B78: RDH4-01-003 | C78: 3 | D78: Design Bridge 3rd HIGHWAY RiyaDH 4 | F78: 1124289 | W78: 46125 | X78: ='ENGICON RIYADH 4 P2 '!M44 -> 168701 | Y78: =15%*Currentinvoices[[#This Row],[Invoice '# 5 amount]] -> 25305.15 | Z78: =Currentinvoices[[#This Row],[Invoice '# 5 vat]]+Currentinvoices[[#This Row],[Invoice '# 5 amount]] -> 194006.15 | DD78: =Currentinvoices[[#This Row],[Task Value]] -> 1124289 | DE78: =DD78*15% -> 168643.35 | DF78: =DD78+DE78 -> 1292932.4 | DG78: =SUMPRODUCT((MOD(COLUMN(G78:DB78)-COLUMN(G78),4)=1)*G78:DB78) -> 168701 | DH78: =SUMPRODUCT((MOD(COLUMN(G78:DB78)-COLUMN(H78),4)=2)*G78:DB78) -> 194006.15 | DI78: 0.25 | DJ78: =DI78*DD78 -> 281072.25 | DK78: =DJ78-DG78 -> 112371.25
A79: ENGICON - RDH4 PH2 | B79: RDH4-01-003 | C79: 4 | D79: Oasis Lab Riyadh 4 | F79: 2504618 | AE79: 46196 | AF79: 187841.5 | AG79: =Currentinvoices[[#This Row],[Invoice '# 7 amount]]*15% -> 28176.225 | AH79: =Currentinvoices[[#This Row],[Invoice '# 7 vat]]+Currentinvoices[[#This Row],[Invoice '# 7 amount]] -> 216017.73 | AM79: 46218 | AN79: 187841.5 | AO79: =Currentinvoices[[#This Row],[Invoice '# 9 amount]]*15% -> 28176.225 | AP79: =Currentinvoices[[#This Row],[Invoice '# 9 amount]]+Currentinvoices[[#This Row],[Invoice '# 9 vat]] -> 216017.73 | DD79: =Currentinvoices[[#This Row],[Task Value]] -> 2504618 | DE79: =DD79*15% -> 375692.7 | DF79: =DD79+DE79 -> 2880310.7 | DG79: =SUMPRODUCT((MOD(COLUMN(G79:DB79)-COLUMN(G79),4)=1)*G79:DB79) -> 375683 | DH79: =SUMPRODUCT((MOD(COLUMN(G79:DB79)-COLUMN(H79),4)=2)*G79:DB79) -> 432035.45 | DI79: 0.37 | DJ79: =DI79*DD79 -> 926708.66 | DK79: =DJ79-DG79 -> 551025.66
A80: ENGICON - RDH4 PH2 | B80: RDH4-01-003 | C80: 5 | D80: Riyadh4 Industrial City expansion 1&2 | F80: 8850569 | DG80: =SUMPRODUCT((MOD(COLUMN(G80:DB80)-COLUMN(G80),4)=1)*G80:DB80) -> 0 | DH80: =SUMPRODUCT((MOD(COLUMN(G80:DB80)-COLUMN(H80),4)=2)*G80:DB80) -> 0
A81: AlDar International (KHJ - FOOD2) | B81: KHJ-01-027 | C81: 1 | D81: AlKharj Food cluster | E81: KHJ1-01-030 | F81: 7146100 | G81: 45960 | H81: ='AlDar International '!M18 -> 659049.98 | I81: ='Invoices (2)'!$H81*15% -> 98857.497 | J81: ='Invoices (2)'!$H81+'Invoices (2)'!$I81 -> 757907.48 | K81: 45981 | L81: 776250 | M81: ='Invoices (2)'!$L81*15% -> 116437.5 | N81: ='Invoices (2)'!$M81+'Invoices (2)'!$L81 -> 892687.5 | O81: 46113 | P81: ='AlDar International '!Q18 -> 1090800 | Q81: =15%*Currentinvoices[[#This Row],[Invoice '# 3 amount]] -> 163620 | R81: =Currentinvoices[[#This Row],[Invoice '# 3 vat]]+Currentinvoices[[#This Row],[Invoice '# 3 vat]] -> 327240 | T81: ='AlDar International '!S18 -> 3517000.4 | U81: =Currentinvoices[[#This Row],[Invoice '# 4 amount]]*15% -> 527550.05 | V81: =Currentinvoices[[#This Row],[Invoice '# 4 vat]]+Currentinvoices[[#This Row],[Invoice '# 4 amount]] -> 4044550.4 | DD81: =F81 -> 7146100 | DE81: =DD81*15% -> 1071915 | DF81: =DD81+DE81 -> 8218015 | DG81: =SUMPRODUCT((MOD(COLUMN(G81:DB81)-COLUMN(G81),4)=1)*G81:DB81) -> 6043100.3 | DH81: =SUMPRODUCT((MOD(COLUMN(G81:DB81)-COLUMN(H81),4)=2)*G81:DB81) -> 6022385.4 | DI81: 1 | DJ81: =DI81*DD81 -> 7146100 | DK81: =DJ81-DG81 -> 1102999.7
A82: AlDar International (KHJ - FOOD2) | B82: KHJ-01-027 | DG82: =SUMPRODUCT((MOD(COLUMN(G82:DB82)-COLUMN(G82),4)=1)*G82:DB82) -> 0 | DH82: =SUMPRODUCT((MOD(COLUMN(G82:DB82)-COLUMN(H82),4)=2)*G82:DB82) -> 0
A83: AlDar International (KHJ - FOOD2) | B83: KHJ-01-027 | DG83: =SUMPRODUCT((MOD(COLUMN(G83:DB83)-COLUMN(G83),4)=1)*G83:DB83) -> 0 | DH83: =SUMPRODUCT((MOD(COLUMN(G83:DB83)-COLUMN(H83),4)=2)*G83:DB83) -> 0
A84: ENGICON - Logistics | B84: MLTX-01-117 | C84: 1 | D84: Logistic Zones (JDH3,DAM3,MAD,MKH2) | E84: MLTX-01-123 | F84: 19206662 | G84: 45929 | H84: =Logistic!M13 -> 960349 | I84: ='Invoices (2)'!$H84*15% -> 144052.35 | J84: ='Invoices (2)'!$H84+'Invoices (2)'!$I84 -> 1104401.4 | K84: 45938 | L84: =Logistic!O13 -> 960349 | M84: ='Invoices (2)'!$H84*15% -> 144052.35 | N84: ='Invoices (2)'!$H84+'Invoices (2)'!$I84 -> 1104401.4 | O84: 45959 | P84: =Logistic!Q13 -> 288080.85 | Q84: ='Invoices (2)'!$P84*15% -> 43212.127 | R84: ='Invoices (2)'!$P84+'Invoices (2)'!$Q84 -> 331292.98 | S84: 45992 | T84: =Logistic!S13 -> 2784853.1 | U84: ='Invoices (2)'!$T84*15% -> 417727.97 | V84: ='Invoices (2)'!$U84+'Invoices (2)'!$T84 -> 3202581.1 | W84: 46012 | X84: 2496772.2 | Y84: =Currentinvoices[[#This Row],[Invoice '# 5 amount]]*15% -> 374515.84 | Z84: =Currentinvoices[[#This Row],[Invoice '# 5 vat]]+Currentinvoices[[#This Row],[Invoice '# 5 amount]] -> 2871288.1 | AA84: 46057 | AB84: 4897779.9 | AC84: =15%*Currentinvoices[[#This Row],[Invoice '# 6 amount]] -> 734666.98 | AD84: =Currentinvoices[[#This Row],[Invoice '# 6 vat]]+Currentinvoices[[#This Row],[Invoice '# 6 amount]] -> 5632446.9 | AE84: 46125 | AF84: 5185884.6 | AG84: =15%*Currentinvoices[[#This Row],[Invoice '# 7 amount]] -> 777882.69 | AH84: =Currentinvoices[[#This Row],[Invoice '# 7 vat]]+Currentinvoices[[#This Row],[Invoice '# 7 amount]] -> 5963767.3 | DD84: =F84 -> 19206662 | DE84: =DD84*15% -> 2880999.3 | DF84: =DD84+DE84 -> 22087661 | DG84: =SUMPRODUCT((MOD(COLUMN(G84:DB84)-COLUMN(G84),4)=1)*G84:DB84) -> 17574069 | DH84: =SUMPRODUCT((MOD(COLUMN(G84:DB84)-COLUMN(H84),4)=2)*G84:DB84) -> 20210179 | DI84: 1 | DJ84: =DI84*DD84 -> 19206662 | DK84: =DJ84-DG84 -> 1632593.3
A85: ENGICON - Logistics | B85: MLTX-01-117 | C85: 2 | D85: SIDF-RBF SITE ADAPTATION 450 &900M2 IN 5 CITIES | F85: 4700512 | AI85: 46205 | AJ85: 940240 | AK85: =Currentinvoices[[#This Row],[Invoice '# 8 amount]]*15% -> 141036 | AL85: =Currentinvoices[[#This Row],[Invoice '# 8 vat]]+Currentinvoices[[#This Row],[Invoice '# 8 amount]] -> 1081276 | AM85: 46218 | AN85: 1410016 | AO85: =Currentinvoices[[#This Row],[Invoice '# 9 amount]]*15% -> 211502.4 | AP85: =Currentinvoices[[#This Row],[Invoice '# 9 vat]]+Currentinvoices[[#This Row],[Invoice '# 9 amount]] -> 1621518.4 | DD85: =F85 -> 4700512 | DE85: =DD85*15% -> 705076.8 | DF85: =DD85+DE85 -> 5405588.8 | DG85: =SUMPRODUCT((MOD(COLUMN(G85:DB85)-COLUMN(G85),4)=1)*G85:DB85) -> 2350256 | DH85: =SUMPRODUCT((MOD(COLUMN(G85:DB85)-COLUMN(H85),4)=2)*G85:DB85) -> 2702794.4 | DI85: 0.8 | DJ85: =DI85*DD85 -> 3760409.6 | DK85: =DJ85-DG85 -> 1410153.6
A86: ENGICON - Logistics | B86: MLTX-01-117 | C86: 3 | DG86: =SUMPRODUCT((MOD(COLUMN(G86:DB86)-COLUMN(G86),4)=1)*G86:DB86) -> 0 | DH86: =SUMPRODUCT((MOD(COLUMN(G86:DB86)-COLUMN(H86),4)=2)*G86:DB86) -> 0
A87: EGEC - NIS3 | DG87: =SUMPRODUCT((MOD(COLUMN(G87:DB87)-COLUMN(G87),4)=1)*G87:DB87) -> 0 | DH87: =SUMPRODUCT((MOD(COLUMN(G87:DB87)-COLUMN(H87),4)=2)*G87:DB87) -> 0
A88: EGEC - NIS3 | DG88: =SUMPRODUCT((MOD(COLUMN(G88:DB88)-COLUMN(G88),4)=1)*G88:DB88) -> 0 | DH88: =SUMPRODUCT((MOD(COLUMN(G88:DB88)-COLUMN(H88),4)=2)*G88:DB88) -> 0
A89: EGEC - NIS3 | DG89: =SUMPRODUCT((MOD(COLUMN(G89:DB89)-COLUMN(G89),4)=1)*G89:DB89) -> 0 | DH89: =SUMPRODUCT((MOD(COLUMN(G89:DB89)-COLUMN(H89),4)=2)*G89:DB89) -> 0
A90: TYPSA- (KHJ2-01-001) | B90: KHJ2-01-001 | C90: 1 | D90: Design and Engineering Support Works for the Master Plan and Infrastructure Project for the Military Industries City in Al Kharj | E90: KHJ2-01-002 | F90: 42715824 | G90: 45991 | H90: ='TYPSA-KHJ2MIC'!G49 -> 857830 | I90: ='Invoices (2)'!$H90*15% -> 128674.5 | J90: ='Invoices (2)'!$H90+'Invoices (2)'!$I90 -> 986504.5 | K90: 46014 | L90: ='TYPSA-KHJ2MIC'!I49 -> 1510048.5 | M90: =Currentinvoices[[#This Row],[Invoice '# 2 amount]]*15% -> 226507.27 | N90: =Currentinvoices[[#This Row],[Invoice '# 2 vat]]+Currentinvoices[[#This Row],[Invoice '# 2 amount]] -> 1736555.8 | O90: 46055 | P90: ='TYPSA-KHJ2MIC'!K49 -> 1681963.1 | Q90: ='Invoices (2)'!$P90*15% -> 252294.46 | R90: ='Invoices (2)'!$P90+'Invoices (2)'!$Q90 -> 1934257.6 | S90: 46117 | T90: ='TYPSA-KHJ2MIC'!M49 -> 290932.38 | U90: =Currentinvoices[[#This Row],[Invoice '# 4 amount]]*15% -> 43639.857 | V90: =Currentinvoices[[#This Row],[Invoice '# 4 vat]]+Currentinvoices[[#This Row],[Invoice '# 4 amount]] -> 334572.24 | W90: 46134 | X90: ='TYPSA-KHJ2MIC'!O49 -> 514671 | Y90: ='TYPSA-KHJ2MIC'!O50 -> 77200.65 | Z90: ='TYPSA-KHJ2MIC'!O51 -> 591871.65 | AA90: 46181 | AB90: 1362021.7 | AC90: =Currentinvoices[[#This Row],[Invoice '# 6 amount]]*15% -> 204303.26 | AD90: =Currentinvoices[[#This Row],[Invoice '# 6 vat]]+Currentinvoices[[#This Row],[Invoice '# 6 amount]] -> 1566325 | AE90: 46209 | AF90: 1362021.7 | AG90: =Currentinvoices[[#This Row],[Invoice '# 7 amount]]*15% -> 204303.26 | AH90: =Currentinvoices[[#This Row],[Invoice '# 7 vat]]+Currentinvoices[[#This Row],[Invoice '# 7 amount]] -> 1566325 | DD90: ='Invoices (2)'!$F90 -> 42715824 | DE90: =Currentinvoices[[#This Row],[Task Value2]]*15% -> 6407373.5 | DF90: =Currentinvoices[[#This Row],[VAT]]+Currentinvoices[[#This Row],[Task Value2]] -> 49123197 | DG90: =SUMPRODUCT((MOD(COLUMN(G90:DB90)-COLUMN(G90),4)=1)*G90:DB90) -> 7579488.4 | DH90: =SUMPRODUCT((MOD(COLUMN(G90:DB90)-COLUMN(H90),4)=2)*G90:DB90) -> 8716411.7 | DI90: 0.1322 | DJ90: =DI90*DD90 -> 5647031.9 | DK90: =DJ90-DG90 -> -1932456.5
A91: TYPSA- (KHJ2-01-001) | B91: KHJ2-01-001 | C91: 2 | D91: Strategic Advisory and Military Industrial Planning Support Services | E91: KHJ2-01-007 | F91: 2142000 | DG91: =SUMPRODUCT((MOD(COLUMN(G91:DB91)-COLUMN(G91),4)=1)*G91:DB91) -> 0 | DH91: =SUMPRODUCT((MOD(COLUMN(G91:DB91)-COLUMN(H91),4)=2)*G91:DB91) -> 0
A92: TYPSA- (KHJ2-01-001) | B92: KHJ2-01-000 | C92: 3 | D92: Comprehensive Facility Survey & Update of As-Builts, Al Kharj MIC | E92: KHJ2-01-006 | F92: 6684584.9 | DG92: =SUMPRODUCT((MOD(COLUMN(G92:DB92)-COLUMN(G92),4)=1)*G92:DB92) -> 0 | DH92: =SUMPRODUCT((MOD(COLUMN(G92:DB92)-COLUMN(H92),4)=2)*G92:DB92) -> 0
A93: Meinhardt (RDH1-01-006) | B93: RDH1-01-006 | C93: 1 | D93: Riyadh 1 Industrial City Masterplan | E93: RDH1-01-007 | F93: 16898852 | G93: 46138 | H93: 844942.61 | I93: =Currentinvoices[[#This Row],[Invoice '# 1 amount]]*15% -> 126741.39 | J93: =Currentinvoices[[#This Row],[Invoice '# 1 vat]]+Currentinvoices[[#This Row],[Invoice '# 1 amount]] -> 971684 | K93: 46155 | L93: 422471 | M93: =Currentinvoices[[#This Row],[Invoice '# 2 amount]]*15% -> 63370.65 | N93: =Currentinvoices[[#This Row],[Invoice '# 2 vat]]+Currentinvoices[[#This Row],[Invoice '# 2 amount]] -> 485841.65 | O93: 46184 | P93: 422471.3 | Q93: =Currentinvoices[[#This Row],[Invoice '# 3 amount]]*15% -> 63370.695 | R93: =Currentinvoices[[#This Row],[Invoice '# 3 vat]]+Currentinvoices[[#This Row],[Invoice '# 3 amount]] -> 485841.99 | S93: 46209 | T93: 844942.61 | U93: =Currentinvoices[[#This Row],[Invoice '# 4 amount]]*15% -> 126741.39 | V93: =Currentinvoices[[#This Row],[Invoice '# 4 vat]]+Currentinvoices[[#This Row],[Invoice '# 4 amount]] -> 971684 | W93: 46230 | X93: 422471.3 | Y93: =Currentinvoices[[#This Row],[Invoice '# 5 amount]]*15% -> 63370.695 | Z93: =Currentinvoices[[#This Row],[Invoice '# 5 vat]]+Currentinvoices[[#This Row],[Invoice '# 5 amount]] -> 485841.99 | AE93: 46250 | AF93: 422471.3 | AG93: =Currentinvoices[[#This Row],[Invoice '# 7 amount]]*15% -> 63370.695 | AH93: =Currentinvoices[[#This Row],[Invoice '# 7 vat]]+Currentinvoices[[#This Row],[Invoice '# 7 amount]] -> 485841.99 | DD93: =Currentinvoices[[#This Row],[Task Value]] -> 16898852 | DE93: =DD93*15% -> 2534827.8 | DF93: =DD93+DE93 -> 19433680 | DG93: =SUMPRODUCT((MOD(COLUMN(G93:DB93)-COLUMN(G93),4)=1)*G93:DB93) -> 3379770.1 | DH93: =SUMPRODUCT((MOD(COLUMN(G93:DB93)-COLUMN(H93),4)=2)*G93:DB93) -> 3886735.6 | DI93: 0.36 | DJ93: =DI93*DD93 -> 6083586.7 | DK93: =DJ93-DG93 -> 2703816.6
A94: Meinhardt (RDH1-01-006) | B94: RDH1-01-006 | C94: 2 | D94: Riyadh 1-Codes and Guidelines | E94: RDH1-01-008 | F94: 6200000 | G94: 46138 | H94: 310000 | I94: =Currentinvoices[[#This Row],[Invoice '# 1 amount]]*15% -> 46500 | J94: =Currentinvoices[[#This Row],[Invoice '# 1 vat]]+Currentinvoices[[#This Row],[Invoice '# 1 amount]] -> 356500 | K94: 46155 | L94: 1240000 | M94: =Currentinvoices[[#This Row],[Invoice '# 2 amount]]*15% -> 186000 | N94: =Currentinvoices[[#This Row],[Invoice '# 2 vat]]+Currentinvoices[[#This Row],[Invoice '# 2 amount]] -> 1426000 | O94: 46184 | P94: 620000 | Q94: =Currentinvoices[[#This Row],[Invoice '# 3 amount]]*15% -> 93000 | R94: =Currentinvoices[[#This Row],[Invoice '# 3 vat]]+Currentinvoices[[#This Row],[Invoice '# 3 amount]] -> 713000 | W94: 46230 | X94: 434000 | Y94: =Currentinvoices[[#This Row],[Invoice '# 5 amount]]*15% -> 65100 | Z94: =Currentinvoices[[#This Row],[Invoice '# 5 vat]]+Currentinvoices[[#This Row],[Invoice '# 5 amount]] -> 499100 | AE94: 46250 | AF94: 186000 | AG94: =Currentinvoices[[#This Row],[Invoice '# 7 amount]]*15% -> 27900 | AH94: =Currentinvoices[[#This Row],[Invoice '# 7 vat]]+Currentinvoices[[#This Row],[Invoice '# 7 amount]] -> 213900 | DD94: =Currentinvoices[[#This Row],[Task Value]] -> 6200000 | DE94: =DD94*15% -> 930000 | DF94: =DD94+DE94 -> 7130000 | DG94: =SUMPRODUCT((MOD(COLUMN(G94:DB94)-COLUMN(G94),4)=1)*G94:DB94) -> 2790000 | DH94: =SUMPRODUCT((MOD(COLUMN(G94:DB94)-COLUMN(H94),4)=2)*G94:DB94) -> 3208500 | DI94: 0.63 | DJ94: =DI94*DD94 -> 3906000 | DK94: =DJ94-DG94 -> 1116000
A95: Meinhardt (RDH1-01-006) | B95: RDH1-01-006 | C95: 3 | D95: Riyadh 1-RBF-Value Engineering | E95: RDH1-01-009 | F95: 1200000 | G95: 46138 | H95: 60000 | I95: =Currentinvoices[[#This Row],[Invoice '# 1 amount]]*15% -> 9000 | J95: =Currentinvoices[[#This Row],[Invoice '# 1 vat]]+Currentinvoices[[#This Row],[Invoice '# 1 amount]] -> 69000 | K95: 46155 | L95: 240000 | M95: =Currentinvoices[[#This Row],[Invoice '# 2 amount]]*15% -> 36000 | N95: =Currentinvoices[[#This Row],[Invoice '# 2 vat]]+Currentinvoices[[#This Row],[Invoice '# 2 amount]] -> 276000 | DD95: =Currentinvoices[[#This Row],[Task Value]] -> 1200000 | DE95: =DD95*15% -> 180000 | DF95: =DD95+DE95 -> 1380000 | DG95: =SUMPRODUCT((MOD(COLUMN(G95:DB95)-COLUMN(G95),4)=1)*G95:DB95) -> 300000 | DH95: =SUMPRODUCT((MOD(COLUMN(G95:DB95)-COLUMN(H95),4)=2)*G95:DB95) -> 345000 | DI95: 0.85 | DJ95: =DI95*DD95 -> 1020000 | DK95: =DJ95-DG95 -> 720000
A96: Meinhardt (RDH1-01-006) | B96: RDH1-01-006 | C96: 4 | D96: Multi-Story Building | E96: RDH1-01-000 | F96: 1000000 | G96: 46138 | H96: 50000 | I96: =Currentinvoices[[#This Row],[Invoice '# 1 amount]]*15% -> 7500 | J96: =Currentinvoices[[#This Row],[Invoice '# 1 vat]]+Currentinvoices[[#This Row],[Invoice '# 1 amount]] -> 57500 | K96: 46155 | L96: 400000 | M96: =Currentinvoices[[#This Row],[Invoice '# 2 amount]]*15% -> 60000 | N96: =Currentinvoices[[#This Row],[Invoice '# 2 vat]]+Currentinvoices[[#This Row],[Invoice '# 2 amount]] -> 460000 | O96: 46184 | P96: 200000 | Q96: =Currentinvoices[[#This Row],[Invoice '# 3 amount]]*15% -> 30000 | R96: =Currentinvoices[[#This Row],[Invoice '# 3 vat]]+Currentinvoices[[#This Row],[Invoice '# 3 amount]] -> 230000 | S96: 46209 | T96: 150000 | U96: =Currentinvoices[[#This Row],[Invoice '# 4 amount]]*15% -> 22500 | V96: =Currentinvoices[[#This Row],[Invoice '# 4 vat]]+Currentinvoices[[#This Row],[Invoice '# 4 amount]] -> 172500 | W96: 46230 | X96: 100000 | Y96: =Currentinvoices[[#This Row],[Invoice '# 5 amount]]*15% -> 15000 | Z96: =Currentinvoices[[#This Row],[Invoice '# 5 vat]]+Currentinvoices[[#This Row],[Invoice '# 5 amount]] -> 115000 | AE96: 46250 | AF96: 100000 | AG96: =Currentinvoices[[#This Row],[Invoice '# 7 amount]]*15% -> 15000 | AH96: =Currentinvoices[[#This Row],[Invoice '# 7 vat]]+Currentinvoices[[#This Row],[Invoice '# 7 amount]] -> 115000 | DD96: =Currentinvoices[[#This Row],[Task Value]] -> 1000000 | DE96: =DD96*15% -> 150000 | DF96: =DD96+DE96 -> 1150000 | DG96: =SUMPRODUCT((MOD(COLUMN(G96:DB96)-COLUMN(G96),4)=1)*G96:DB96) -> 1000000 | DH96: =SUMPRODUCT((MOD(COLUMN(G96:DB96)-COLUMN(H96),4)=2)*G96:DB96) -> 1150000 | DI96: 1 | DJ96: =DI96*DD96 -> 1000000 | DK96: =DJ96-DG96 -> 0
DG97: =SUMPRODUCT((MOD(COLUMN(G97:DB97)-COLUMN(G97),4)=1)*G97:DB97) -> 0
DG98: =SUMPRODUCT((MOD(COLUMN(G98:DB98)-COLUMN(G98),4)=1)*G98:DB98) -> 0

Sheet Sheet4
A1: Framework name | B1: Framework ID | C1: Framework Total amount | D1: Framework Status | E1: Project Name | F1: Project status | G1: Project ID | H1: Project Total amount
A2: Dorsch food | B2: MLTX-01-085 | C2: 19993600 | D2: Closed | E2: Jeddah 2 - Food Cluster - RBF 450 & 900 m2 | F2: Closed | G2: JDH2-01-016 | H2: 877779
A3: Dorsch food | B3: MLTX-01-085 | C3: 19993600 | D3: Closed | E3: Jeddah Food Cluster - Masterplan Update & Lands Selection at Jeddah 2nd & 3rd Ind. Cities | F3: Closed | G3: MLTX-01-093 | H3: 1403611
A4: Dorsch food | B4: MLTX-01-085 | C4: 19993600 | D4: Closed | E4: Jeddah 3 - Design of Shared Dry & Cold Storage Warehouses in Jeddah 3 Ind. City | F4: Closed | G4: JDH3-01-021 | H4: 2999654
A5: Dorsch food | B5: MLTX-01-085 | C5: 19993600 | D5: Closed | E5: Master planning a logistic area in Dammam 2 | F5: Closed | G5: DAM2-01-026 | H5: 4125000
A6: Dorsch food | B6: MLTX-01-085 | C6: 19993600 | D6: Closed | E6: Hydrology Study for preventing Jeddah 4th Industrial City from floods and stormwater | F6: Closed | G6: JDH4-01-040 | H6: 404258
A7: Dorsch food | B7: MLTX-01-085 | C7: 19993600 | D7: Closed | E7: Completing the infrastructure networks and residential neighborhood in the 2nd industrial city in Dammam | F7: Closed | G7: DAM2-02-027 | H7: 6968306
A8: Dorsch food | B8: MLTX-01-085 | C8: 19993600 | D8: Closed | E8: Reviewing the masterplan for alkhrj nd. City | F8: Closed | H8: 174000
A9: Dorsch food | B9: MLTX-01-085 | C9: 19993600 | D9: Closed | E9: Detail MPL and infra Design for the multi-use area in Dammam2 | F9: Closed | G9: DAM2-01-029 | H9: 836000
A10: Dorsch food | B10: MLTX-01-085 | C10: 19993600 | D10: Closed | E10: Design shared services center - Food cluster | F10: Closed | G10: JDH2-01-023 | H10: 1505768
A11: Dorsch food | B11: MLTX-01-085 | C11: 19993600 | D11: Closed | E11: الدراسه القيميه لمشاريع المصانع الجاهزة | F11: Closed | H11: 264505
A12: SYSTRA | B12: MLTX-01-102 | C12: 15054089 | D12: ongoing | E12: Masterplan & Infrstructure Detailed Design For Technology Zones (Jenadryah) | F12: Closed | G12: JNDT-01-001 | H12: 6726972
A13: SYSTRA | B13: MLTX-01-102 | C13: 15054089 | D13: ongoing | E13: Masterplan & Infrstructure Detailed Design For Technology Zones (Dammam) | F13: ongoing | G13: DAMT-01-001 | H13: 3300435
A14: SYSTRA | B14: MLTX-01-102 | C14: 15054089 | D14: ongoing | E14: Masterplan & Infrstructure Detailed Design For Technology Zones (Dhahran) | F14: ongoing | G14: DHRT-01-001 | H14: 3300435
A15: SYSTRA | B15: MLTX-01-102 | C15: 15054089 | D15: ongoing | E15: Technical review and transport planning expertise support for Riyadh Industrial cities 1 & 4 | F15: Closed | G15: MLTX-01-111 | H15: 1726247
A16: EGEC - NIS2 | B16: MLTX-01-099 | C16: 19979840 | D16: ongoing | E16: Updated concept masterplan & Infrastructure designs for Tabouk ind. City | F16: Closed | G16: TAB-01-009 | H16: 4360270
A17: EGEC - NIS2 | B17: MLTX-01-099 | C17: 19979840 | D17: ongoing | E17: Project support services (6 months) (Masterplan) | F17: Closed | H17: 744150
A18: EGEC - NIS2 | B18: MLTX-01-099 | C18: 19979840 | D18: ongoing | E18: Project support services (6 months) (VRO) | F18: Closed | H18: 744150
A19: EGEC - NIS2 | B19: MLTX-01-099 | C19: 19979840 | D19: ongoing | E19: Testing and evaluating concrete structure | F19: Closed | H19: 153002
A20: EGEC - NIS2 | B20: MLTX-01-099 | C20: 19979840 | D20: ongoing | E20: Preliminary designs for the expansion of the industrial city in riyadh | H20: 156177
A21: EGEC - NIS2 | B21: MLTX-01-099 | C21: 19979840 | D21: ongoing | E21: Incubators in Al-Qassim Oasis | F21: Closed | G21: QSM3-01-014 | H21: 1656100
A22: EGEC - NIS2 | B22: MLTX-01-099 | C22: 19979840 | D22: ongoing | E22: Site development and infrastructure design works for expansion in Jeddah 1 | F22: Closed | G22: JDH1-01-021 | H22: 2560090
A23: EGEC - NIS2 | B23: MLTX-01-099 | C23: 19979840 | D23: ongoing | E23: Detailed design of connection road (Fly Over) in Dammam 2 | F23: ongoing | G23: DAM2-01-033 | H23: 2310000
A24: EGEC - NIS2 | B24: MLTX-01-099 | C24: 19979840 | D24: ongoing | E24: Labour camp masterplan and infrastructure development in AlKharj | F24: Closed | G24: KHJ-01-025 | H24: 350000
A25: EGEC - NIS2 | B25: MLTX-01-099 | C25: 19979840 | D25: ongoing | E25: Potable water pipeline supply and connection to alkharj 1st ind. City | F25: ongoing | G25: KHJ-01-026 | H25: 534490
A26: EGEC - NIS2 | B26: MLTX-01-099 | C26: 19979840 | D26: ongoing | E26: Study design RBFs 900 & 450m2 SFDA requirements | H26: 170000
A27: EGEC - NIS2 | B27: MLTX-01-099 | C27: 19979840 | D27: ongoing | E27: Improving the entrances and exit points for Jeddah 1 | F27: ongoing | G27: JDH1-01-028 | H27: 1590000
A28: EGEC - NIS2 | B28: MLTX-01-099 | C28: 19979840 | D28: ongoing | E28: Hydrology study for Jeddah 2 | F28: ongoing | H28: 110500
A29: EGEC - NIS2 | B29: MLTX-01-099 | C29: 19979840 | D29: ongoing | E29: Jenadriyadh Business Incubators | F29: ongoing | G29: JNDT-01-002 | H29: 500000
A30: EGEC - NIS2 | B30: MLTX-01-099 | C30: 19979840 | D30: ongoing | E30: Project support services 3 | H30: 1798340
A31: EGEC - NIS2 | B31: MLTX-01-099 | C31: 19979840 | D31: ongoing | E31: Adaptation and Design of an Administrative Building Humanization in Riyadh 2 | F31: ongoing | H31: 590000
A32: ENGICON | B32: RDH4-00-001 | C32: 27837620 | D32: Closed | E32: Riyadh 4 Masterplan and Infrastructure concept design | F32: Closed | G32: RDH4-00-001 | H32: 27837620
A33: EGEC - WAS | B33: WAS1-01-039 | C33: 9799000 | D33: ongoing | E33: Site development and buildings design for labour community area in WAS industrial city | F33: ongoing | G33: WAS-01-035 | H33: 4421850
A34: EGEC - WAS | B34: WAS1-01-039 | C34: 9799000 | D34: ongoing | E34: Design commercial area with fuel station in Waad AlShamal | F34: ongoing | G34: WAS-01-034 | H34: 650000
A35: EGEC - WAS | B35: WAS1-01-039 | C35: 9799000 | D35: ongoing | E35: Development of labour camps in: DAM03, NJR, MKH2, JDH2, SUD, ASR1 | F35: ongoing | G35: MLTX-01-119 | H35: 1150000
A36: EGEC - WAS | B36: WAS1-01-039 | C36: 9799000 | D36: ongoing | E36: Project support services 4 | F36: ongoing | H36: 853820
A37: ENGICON - RDH4 | B37: RDH4-01-002 | C37: 7025000 | D37: Closed | E37: Design work for entrance and facilities for Riyadh 4 | F37: Closed | G37: RDH4-01-002 | H37: 7025000
A38: Dar AlRiyadh 2 | B38: MLTX-01-100 | C38: 59999686 | D38: ongoing | F38: ongoing | G38: MLTX-01-100
A39: ENGICON - Package1 | B39: MLTX-01-098 | C39: 19856000 | D39: ongoing | E39: NIS Design adaptation of RBF 450 , 900 m2 | F39: Closed | H39: 7940002
A40: ENGICON - Package1 | B40: MLTX-01-098 | C40: 19856000 | D40: ongoing | E40: Detailed design of lake park and supply connection for Sudair Industrial City | F40: Closed | G40: SUD1-01-033 | H40: 1658659
A41: ENGICON - Package1 | B41: MLTX-01-098 | C41: 19856000 | D41: ongoing | E41: Technology Zone- Asfan | F41: ongoing | G41: ASFT-01-001 | H41: 1192999
A42: ENGICON - Package1 | B42: MLTX-01-098 | C42: 19856000 | D42: ongoing | E42: Technology Zone- Khumra | F42: ongoing | G42: KUMT-01-001 | H42: 1318399
A43: ENGICON - Package1 | B43: MLTX-01-098 | C43: 19856000 | D43: ongoing | E43: Riyadh 3 Business incubators | F43: ongoing | G43: RDH3-01-012 | H43: 1230000
A44: ENGICON - Package1 | B44: MLTX-01-098 | C44: 19856000 | D44: ongoing | E44: Bonded Zone in Jeddah 3rd Industrial City-MSC | F44: ongoing | H44: 2210695
A45: ENGICON - Package1 | B45: MLTX-01-098 | C45: 19856000 | D45: ongoing | E45: Adimn Building In Riyadh 4 | F45: ongoing | H45: 1000628
A46: Meinhardt (KHJ- FOOD) | B46: KHJ1-01-020 | C46: 14990000 | D46: ongoing | E46: Development of Design guidelines, production strategy, and prototype packages for mid-sized RBFs | F46: ongoing | H46: 2997130
A47: Meinhardt (KHJ- FOOD) | B47: KHJ1-01-020 | C47: 14990001 | D47: ongoing | E47: Development of full Design for Multi - Story Building for foure Sities | F47: ongoing | H47: 5188500
A48: Meinhardt (KHJ- FOOD) | B48: KHJ1-01-020 | C48: 14990002 | D48: ongoing | E48: Development of full Design Of Mid RBFs for Food , Machinery & Equipment and Pharmceutical Cluster | F48: ongoing | H48: 3500000
A49: ENGICON - RDH4 PH2 | B49: RDH4-01-003 | C49: 59500000 | D49: ongoing | E49: 70 RBF's in Riyadh 04 | F49: ongoing | H49: 2490457
A50: ENGICON - RDH4 PH2 | B50: RDH4-01-003 | C50: 59500000 | D50: ongoing | E50: Development for the Masterplan and Concept Infrastructure for the expansion of Riyadh 4 industrial city | F50: ongoing | G50: RDH4-01-005 | H50: 24501677
A51: ENGICON - RDH4 PH2 | B51: RDH4-01-003 | C51: 59500000 | D51: ongoing | E51: Design Bridge 3rd HIGHWAY RiyaDH 4 | F51: ongoing | H51: 1124289
A52: ENGICON - RDH4 PH2 | B52: RDH4-01-003 | C52: 59500000 | D52: ongoing | E52: Oasis Lab Riyadh 4 | F52: ongoing | H52: 2504618
A53: ENGICON - RDH4 PH2 | B53: RDH4-01-003 | C53: 59500000 | D53: ongoing | E53: Riyadh4 Industrial City expansion 1&2 | F53: ongoing | H53: 8850569
A54: AlDar International (KHJ - FOOD2) | B54: KHJ-01-027 | C54: 11637180 | D54: ongoing | E54: AlKharj Food cluster | F54: ongoing | G54: KHJ1-01-030 | H54: 7146100
A55: ENGICON - Logistics | B55: MLTX-01-117 | C55: 27800000 | D55: ongoing | E55: Logistic Zones (JDH3,DAM3,MAD,MKH2) | F55: ongoing | G55: MLTX-01-123 | H55: 19206662
A56: ENGICON - Logistics | B56: MLTX-01-117 | C56: 27800000 | D56: ongoing | E56: SIDF-RBF SITE ADAPTATION 450 &900M2 IN 5 CITIES | F56: ongoing | H56: 4700512
A57: TYPSA- (KHJ-AMIC) | B57: KHJ2-01-001 | C57: 57332139 | D57: ongoing | E57: Design and Engineering Support Works for the Master Plan and Infrastructure Project for the Military Industries City in Al Kharj | F57: ongoing | G57: KHJ2-01-002 | H57: 42715824
A58: TYPSA- (KHJ-AMIC) | B58: KHJ2-01-001 | C58: 57332139 | D58: ongoing | E58: Strategic Advisory and Military Industrial Planning Support Services | G58: KHJ2-01-007 | H58: 2142000
A59: TYPSA- (KHJ-AMIC) | B59: KHJ2-01-001 | C59: 57332139 | D59: ongoing | E59: Comprehensive Facility Survey & Update of As-Builts, Al Kharj MIC | G59: KHJ2-01-006 | H59: 6684584.9
A60: EGEC - NIS2 | B60: MLTX-01-099 | C60: 19979840 | D60: ongoing | E60: Ddevelopment The walkway In residential area Jeddah1 | F60: ongoing | H60: 170000
A61: Meinhardt (RDH1-01-006) | B61: RDH1-01-006 | C61: 25298852 | D61: ongoing | E61: Riyadh 1 Industrial City Masterplan | F61: ongoing | G61: RDH1-01-007 | H61: 16898852
A62: Meinhardt (RDH1-01-006) | B62: RDH1-01-006 | C62: 25298852 | D62: ongoing | E62: Riyadh 1-Codes and Guidelines | F62: ongoing | G62: RDH1-01-008 | H62: 6200000
A63: Meinhardt (RDH1-01-006) | B63: RDH1-01-006 | C63: 25298852 | D63: ongoing | E63: Riyadh 1-RBF-Value Engineering | F63: ongoing | G63: RDH1-01-009 | H63: 1200000
A64: Meinhardt (RDH1-01-006) | B64: RDH1-01-006 | C64: 25298852 | D64: ongoing | E64: Multi-Story Building | F64: ongoing | G64: RDH1-01-000 | H64: 1000000

Sheet EGEC - NIS2
G5: Tabouk | L5: Invoice 1 | N5: Invoice 2 | P5: Invoice 5 | R5: Invoice 6
A6: Description | C6: Total quantity | D6: Remaining quantity | G6: Description | H6: Category | I6: Total Quantity | J6: Remaining quantity | K6: Rate | L6: Quantity | M6: Amount | N6: Quantity2 | O6: Amount3 | P6: Quantity3 | Q6: Amount4 | R6: Quantity25 | S6: Amount36
A7: Lead Engineer/ Discipline Engineer | B7: A1 | C7: 670 | G7: Lead Engineer/ Discipline Engineer | H7: A1 | J7: =Table5[[#This Row],[Total Quantity]]-Table5[[#This Row],[Quantity]]-Table5[[#This Row],[Quantity2]] -> 0 | K7: 465 | M7: =Table5[[#This Row],[Quantity2]]*Table5[[#This Row],[Rate]] -> 0 | O7: =Table5[[#This Row],[Quantity2]]*Table5[[#This Row],[Rate]] -> 0 | Q7: =Table5[[#This Row],[Quantity2]]*Table5[[#This Row],[Rate]] -> 0 | S7: =Table5[[#This Row],[Quantity2]]*Table5[[#This Row],[Rate]] -> 0
A8: Sr. Engineer/ Senior discipline specialist | B8: B1 | C8: 1050 | G8: Sr. Engineer/ Senior discipline specialist | H8: B1 | J8: =Table5[[#This Row],[Total Quantity]]-Table5[[#This Row],[Quantity]]-Table5[[#This Row],[Quantity2]] -> 0 | K8: 390 | M8: =Table5[[#This Row],[Quantity2]]*Table5[[#This Row],[Rate]] -> 0 | O8: =Table5[[#This Row],[Quantity2]]*Table5[[#This Row],[Rate]] -> 0 | Q8: =Table5[[#This Row],[Quantity2]]*Table5[[#This Row],[Rate]] -> 0 | S8: =Table5[[#This Row],[Quantity2]]*Table5[[#This Row],[Rate]] -> 0
A9: Engineer/ Discipline Specialist | B9: C1 | C9: 1810 | G9: Engineer/ Discipline Specialist | H9: C1 | J9: =Table5[[#This Row],[Total Quantity]]-Table5[[#This Row],[Quantity]]-Table5[[#This Row],[Quantity2]] -> 0 | K9: 200 | M9: =Table5[[#This Row],[Quantity2]]*Table5[[#This Row],[Rate]] -> 0 | O9: =Table5[[#This Row],[Quantity2]]*Table5[[#This Row],[Rate]] -> 0 | Q9: =Table5[[#This Row],[Quantity2]]*Table5[[#This Row],[Rate]] -> 0 | S9: =Table5[[#This Row],[Quantity2]]*Table5[[#This Row],[Rate]] -> 0
A10: Draftsman | B10: D1 | C10: 2380 | G10: Draftsman | H10: D1 | J10: =Table5[[#This Row],[Total Quantity]]-Table5[[#This Row],[Quantity]]-Table5[[#This Row],[Quantity2]] -> 0 | K10: 90 | M10: =Table5[[#This Row],[Quantity2]]*Table5[[#This Row],[Rate]] -> 0 | O10: =Table5[[#This Row],[Quantity2]]*Table5[[#This Row],[Rate]] -> 0 | Q10: =Table5[[#This Row],[Quantity2]]*Table5[[#This Row],[Rate]] -> 0 | S10: =Table5[[#This Row],[Quantity2]]*Table5[[#This Row],[Rate]] -> 0
A11: Lead engineer/ discipline expert | B11: A2 | C11: 9040 | D11: =C11-Table5[[#This Row],[Total Quantity]]-I26-I41-I58-I76-I95-I118-I140-I159-I177 -> -1690.27 | G11: Lead engineer/ discipline expert | H11: A2 | I11: 1800 | J11: =Table5[[#This Row],[Total Quantity]]-Table5[[#This Row],[Quantity]]-Table5[[#This Row],[Quantity2]] -> 561.51822 | K11: 275 | L11: 253.5 | M11: =Table5[[#This Row],[Rate]]*Table5[[#This Row],[Quantity]] -> 69712.5 | N11: 984.98178 | O11: =Table5[[#This Row],[Quantity2]]*Table5[[#This Row],[Rate]] -> 270869.99 | P11: 471.51822 | Q11: =Table5[[#This Row],[Rate]]*Table5[[#This Row],[Quantity3]] -> 129667.51 | R11: 90 | S11: =Table5[[#This Row],[Quantity25]]*Table5[[#This Row],[Rate]] -> 24750
A12: Sr. Engineer/ Senior discipline specialist | B12: B2 | C12: 19600 | D12: =C12-Table5[[#This Row],[Total Quantity]]-I27-I42-I59-I77-I96-I119-I141-I160-I178-I272 -> 10753.11 | G12: Sr. Engineer/ Senior discipline specialist | H12: B2 | I12: 3200 | J12: =Table5[[#This Row],[Total Quantity]]-Table5[[#This Row],[Quantity]]-Table5[[#This Row],[Quantity2]] -> 952.45 | K12: 180 | L12: 775.55 | M12: =Table5[[#This Row],[Rate]]*Table5[[#This Row],[Quantity]] -> 139599 | N12: 1472 | O12: =Table5[[#This Row],[Quantity2]]*Table5[[#This Row],[Rate]] -> 264960 | P12: 792.45 | Q12: =Table5[[#This Row],[Rate]]*Table5[[#This Row],[Quantity3]] -> 142641 | R12: 160 | S12: =Table5[[#This Row],[Quantity25]]*Table5[[#This Row],[Rate]] -> 28800
A13: Engineer/ Discipline Specialist | B13: C2 | C13: 33970 | D13: =C13-Table5[[#This Row],[Total Quantity]]-I28-I43-I60-I78-I97-I120-I142-I161-I273 -> -3702.03 | G13: Engineer/ Discipline Specialist | H13: C2 | I13: 15200 | J13: =Table5[[#This Row],[Total Quantity]]-Table5[[#This Row],[Quantity]]-Table5[[#This Row],[Quantity2]] -> 4511 | K13: 145 | L13: 3849 | M13: =Table5[[#This Row],[Rate]]*Table5[[#This Row],[Quantity]] -> 558105 | N13: 6840 | O13: =Table5[[#This Row],[Quantity2]]*Table5[[#This Row],[Rate]] -> 991800 | P13: 3751 | Q13: =Table5[[#This Row],[Rate]]*Table5[[#This Row],[Quantity3]] -> 543895 | R13: 760 | S13: =Table5[[#This Row],[Quantity25]]*Table5[[#This Row],[Rate]] -> 110200
A14: Draftsman | B14: D2 | C14: 36820 | D14: =C14-Table5[[#This Row],[Total Quantity]]-I29-I44-I61-I79-I98-I121-I143-I162 -> -10720.06 | G14: Draftsman | H14: D2 | I14: 13235 | J14: =Table5[[#This Row],[Total Quantity]]-Table5[[#This Row],[Quantity]]-Table5[[#This Row],[Quantity2]] -> 1342.8 | K14: 82 | L14: 7657 | M14: =Table5[[#This Row],[Rate]]*Table5[[#This Row],[Quantity]] -> 627874 | N14: 4235.2 | O14: =Table5[[#This Row],[Quantity2]]*Table5[[#This Row],[Rate]] -> 347286.4 | P14: 681.05 | Q14: =Table5[[#This Row],[Rate]]*Table5[[#This Row],[Quantity3]] -> 55846.1 | R14: 661.75 | S14: =Table5[[#This Row],[Quantity25]]*Table5[[#This Row],[Rate]] -> 54263.5
A15: E2/ Project Manager | B15: E2 | C15: 7140 | D15: =C15-Table5[[#This Row],[Total Quantity]]-I30-I45-I275 -> 7140 | G15: E2/ Project Manager | H15: E2 | J15: =Table5[[#This Row],[Total Quantity]]-Table5[[#This Row],[Quantity]]-Table5[[#This Row],[Quantity2]] -> 0 | K15: 275 | M15: =Table5[[#This Row],[Quantity2]]*Table5[[#This Row],[Rate]] -> 0 | O15: =Table5[[#This Row],[Quantity2]]*Table5[[#This Row],[Rate]] -> 0 | Q15: =Table5[[#This Row],[Quantity2]]*Table5[[#This Row],[Rate]] -> 0 | S15: =Table5[[#This Row],[Quantity2]]*Table5[[#This Row],[Rate]] -> 0
A16: F2/ Project Manager | B16: F2 | C16: 7140 | D16: =C16-Table5[[#This Row],[Total Quantity]]-I31-I46-I276 -> 7140 | G16: F2/ Project Manager | H16: F2 | J16: =Table5[[#This Row],[Total Quantity]]-Table5[[#This Row],[Quantity]]-Table5[[#This Row],[Quantity2]] -> 0 | K16: 180 | M16: =Table5[[#This Row],[Quantity2]]*Table5[[#This Row],[Rate]] -> 0 | O16: =Table5[[#This Row],[Quantity2]]*Table5[[#This Row],[Rate]] -> 0 | Q16: =Table5[[#This Row],[Quantity2]]*Table5[[#This Row],[Rate]] -> 0 | S16: =Table5[[#This Row],[Quantity2]]*Table5[[#This Row],[Rate]] -> 0
K17: Total | L17: =SUM(L7:L16) -> 12535.05 | M17: =SUM(M7:M16) -> 1395290.5 | N17: =SUM(N7:N16) -> 13532.182 | O17: =SUM(O7:O16) -> 1874916.4 | P17: =SUM(P7:P16) -> 5696.0182 | Q17: =SUM(Q7:Q16) -> 872049.61 | R17: =SUM(R7:R16) -> 1671.75 | S17: =SUM(S7:S16) -> 218013.5
U19: VO
G20: Project support services | L20: Invoice 1 | N20: Invoice 2 | P20: Invoice 4 | T20: Invoice 7 | V20: Invoice 11
G21: Description | H21: Category | I21: Total Quantity | J21: Remaining quantity | K21: Rate | L21: Quantity | M21: Amount | N21: Quantity2 | O21: Amount3 | P21: Quantity22 | Q21: Amount33 | R21: Column1 | S21: Column2 | T21: Quantity2222 | U21: Amount3333 | V21: Quantity22222 | W21: Amount33333
D22: =K12/5421 -> 0.033204206 | G22: Lead Engineer/ Discipline Engineer | H22: A1 | J22: =Table57[[#This Row],[Total Quantity]]-Table57[[#This Row],[Quantity2222]] -> 0 | K22: 465 | M22: =Table57[[#This Row],[Quantity2222]]*Table57[[#This Row],[Rate]] -> 0 | O22: =Table57[[#This Row],[Quantity2222]]*Table57[[#This Row],[Rate]] -> 0 | Q22: =Table57[[#This Row],[Quantity2222]]*Table57[[#This Row],[Rate]] -> 0 | U22: =Table57[[#This Row],[Quantity2222]]*Table57[[#This Row],[Rate]] -> 0 | W22: =Table57[[#This Row],[Quantity2222]]*Table57[[#This Row],[Rate]] -> 0
G23: Sr. Engineer/ Senior discipline specialist | H23: B1 | J23: =Table57[[#This Row],[Total Quantity]]-Table57[[#This Row],[Quantity2222]] -> 0 | K23: 390 | M23: =Table57[[#This Row],[Quantity2222]]*Table57[[#This Row],[Rate]] -> 0 | O23: =Table57[[#This Row],[Quantity2222]]*Table57[[#This Row],[Rate]] -> 0 | Q23: =Table57[[#This Row],[Quantity2222]]*Table57[[#This Row],[Rate]] -> 0 | U23: =Table57[[#This Row],[Quantity2222]]*Table57[[#This Row],[Rate]] -> 0 | W23: =Table57[[#This Row],[Quantity2222]]*Table57[[#This Row],[Rate]] -> 0
C24: 1488300 | D24: =C24/K12 -> 8268.3333 | G24: Engineer/ Discipline Specialist | H24: C1 | J24: =Table57[[#This Row],[Total Quantity]]-Table57[[#This Row],[Quantity2222]] -> 0 | K24: 200 | M24: =Table57[[#This Row],[Quantity2222]]*Table57[[#This Row],[Rate]] -> 0 | O24: =Table57[[#This Row],[Quantity2222]]*Table57[[#This Row],[Rate]] -> 0 | Q24: =Table57[[#This Row],[Quantity2222]]*Table57[[#This Row],[Rate]] -> 0 | U24: =Table57[[#This Row],[Quantity2222]]*Table57[[#This Row],[Rate]] -> 0 | W24: =Table57[[#This Row],[Quantity2222]]*Table57[[#This Row],[Rate]] -> 0
G25: Draftsman | H25: D1 | J25: =Table57[[#This Row],[Total Quantity]]-Table57[[#This Row],[Quantity2222]] -> 0 | K25: 90 | M25: =Table57[[#This Row],[Quantity2222]]*Table57[[#This Row],[Rate]] -> 0 | O25: =Table57[[#This Row],[Quantity2222]]*Table57[[#This Row],[Rate]] -> 0 | Q25: =Table57[[#This Row],[Quantity2222]]*Table57[[#This Row],[Rate]] -> 0 | U25: =Table57[[#This Row],[Quantity2222]]*Table57[[#This Row],[Rate]] -> 0 | W25: =Table57[[#This Row],[Quantity2222]]*Table57[[#This Row],[Rate]] -> 0
G26: Lead engineer/ discipline expert | H26: A2 | I26: 5412 | J26: =Table57[[#This Row],[Total Quantity]]-Table57[[#This Row],[Quantity2222]]-Table57[[#This Row],[Quantity2]]-Table57[[#This Row],[Quantity22]]-Table57[[#This Row],[Column1]]-Table57[[#This Row],[Quantity22222]] -> 0 | K26: 275 | N26: 1353 | O26: =Table57[[#This Row],[Quantity2]]*Table57[[#This Row],[Rate]] -> 372075 | P26: 1353 | Q26: =Table57[[#This Row],[Quantity2222]]*Table57[[#This Row],[Rate]] -> 372075 | T26: 1353 | U26: =Table57[[#This Row],[Quantity2222]]*Table57[[#This Row],[Rate]] -> 372075 | V26: 1353 | W26: =Table57[[#This Row],[Quantity22222]]*Table57[[#This Row],[Rate]] -> 372075
G27: Sr. Engineer/ Senior discipline specialist | H27: B2 | J27: =Table57[[#This Row],[Total Quantity]]-Table57[[#This Row],[Quantity2222]] -> 0 | K27: 180
G28: Engineer/ Discipline Specialist | H28: C2 | J28: =Table57[[#This Row],[Total Quantity]]-Table57[[#This Row],[Quantity2222]] -> 0 | K28: 145
G29: Draftsman | H29: D2 | K29: 82
G30: E2/ Project Manager | H30: E2 | K30: 275 | M30: =Table57[[#This Row],[Quantity2222]]*Table57[[#This Row],[Rate]] -> 0 | O30: =Table57[[#This Row],[Quantity2222]]*Table57[[#This Row],[Rate]] -> 0 | Q30: =Table57[[#This Row],[Quantity2222]]*Table57[[#This Row],[Rate]] -> 0 | U30: =Table57[[#This Row],[Quantity2222]]*Table57[[#This Row],[Rate]] -> 0 | W30: =Table57[[#This Row],[Quantity2222]]*Table57[[#This Row],[Rate]] -> 0
G31: F2/ Project Manager | H31: F2 | K31: 180 | M31: =Table57[[#This Row],[Quantity2222]]*Table57[[#This Row],[Rate]] -> 0 | O31: =Table57[[#This Row],[Quantity2222]]*Table57[[#This Row],[Rate]] -> 0 | Q31: =Table57[[#This Row],[Quantity2222]]*Table57[[#This Row],[Rate]] -> 0 | U31: =Table57[[#This Row],[Quantity2222]]*Table57[[#This Row],[Rate]] -> 0 | W31: =Table57[[#This Row],[Quantity2222]]*Table57[[#This Row],[Rate]] -> 0
K32: Total | L32: =SUM(L22:L31) -> 0 | M32: =SUM(M22:M31) -> 0 | N32: =SUM(N22:N31) -> 1353 | O32: =SUM(O22:O31) -> 372075 | P32: =SUM(P22:P31) -> 1353 | Q32: =SUM(Q22:Q31) -> 372075 | T32: =SUM(T22:T31) -> 1353 | U32: =SUM(U22:U31) -> 372075 | V32: =SUM(V22:V31) -> 1353 | W32: =SUM(W22:W31) -> 372075
G35: Testing and evaluating concrete structure | L35: Invoice 1 | N35: Invoice 2 | P35: Invoice 3
G36: Description | H36: Category | I36: Total Quantity | J36: Remaining quantity | K36: Rate | L36: Quantity | M36: Amount | N36: Quantity2 | O36: Amount3 | P36: Quantity22 | Q36: Amount33
G37: Lead Engineer/ Discipline Engineer | H37: A1 | K37: 465 | M37: =Table578[[#This Row],[Quantity2]]*Table578[[#This Row],[Rate]] -> 0 | O37: =Table578[[#This Row],[Quantity2]]*Table578[[#This Row],[Rate]] -> 0
G38: Sr. Engineer/ Senior discipline specialist | H38: B1 | K38: 390 | M38: =Table578[[#This Row],[Quantity2]]*Table578[[#This Row],[Rate]] -> 0 | O38: =Table578[[#This Row],[Quantity2]]*Table578[[#This Row],[Rate]] -> 0 | S38: =U32+W32 -> 744150
G39: Engineer/ Discipline Specialist | H39: C1 | K39: 200 | M39: =Table578[[#This Row],[Quantity2]]*Table578[[#This Row],[Rate]] -> 0 | O39: =Table578[[#This Row],[Quantity2]]*Table578[[#This Row],[Rate]] -> 0 | S39: =O32+Q32+S32 -> 744150
G40: Draftsman | H40: D1 | K40: 90 | M40: =Table578[[#This Row],[Quantity2]]*Table578[[#This Row],[Rate]] -> 0 | O40: =Table578[[#This Row],[Quantity2]]*Table578[[#This Row],[Rate]] -> 0
G41: Lead engineer/ discipline expert | H41: A2 | I41: 28 | J41: =Table578[[#This Row],[Total Quantity]]-Table578[[#This Row],[Quantity2]] -> 8.4 | K41: 275 | N41: 19.6 | O41: =Table578[[#This Row],[Rate]]*Table578[[#This Row],[Quantity2]] -> 5390 | P41: 8.4 | Q41: =Table578[[#This Row],[Rate]]*Table578[[#This Row],[Quantity22]] -> 2310
G42: Sr. Engineer/ Senior discipline specialist | H42: B2 | I42: 84 | J42: =Table578[[#This Row],[Total Quantity]]-Table578[[#This Row],[Quantity2]] -> 25.2 | K42: 180 | N42: 58.8 | O42: =Table578[[#This Row],[Rate]]*Table578[[#This Row],[Quantity2]] -> 10584 | P42: 25.2 | Q42: =Table578[[#This Row],[Rate]]*Table578[[#This Row],[Quantity22]] -> 4536
G43: Engineer/ Discipline Specialist | H43: C2 | I43: 423 | J43: =Table578[[#This Row],[Total Quantity]]-Table578[[#This Row],[Quantity2]] -> 126.9 | K43: 145 | N43: 296.1 | O43: =Table578[[#This Row],[Rate]]*Table578[[#This Row],[Quantity2]] -> 42934.5 | P43: 126.9 | Q43: =Table578[[#This Row],[Rate]]*Table578[[#This Row],[Quantity22]] -> 18400.5
G44: Draftsman | H44: D2 | I44: 839.6 | J44: =Table578[[#This Row],[Total Quantity]]-Table578[[#This Row],[Quantity2]] -> 251.88 | K44: 82 | N44: 587.72 | O44: =Table578[[#This Row],[Rate]]*Table578[[#This Row],[Quantity2]] -> 48193.04 | P44: 251.88 | Q44: =Table578[[#This Row],[Rate]]*Table578[[#This Row],[Quantity22]] -> 20654.16
G45: E2/ Project Manager | H45: E2 | K45: 275 | M45: =Table578[[#This Row],[Quantity2]]*Table578[[#This Row],[Rate]] -> 0 | O45: =Table578[[#This Row],[Quantity2]]*Table578[[#This Row],[Rate]] -> 0
G46: F2/ Project Manager | H46: F2 | K46: 180 | M46: =Table578[[#This Row],[Quantity2]]*Table578[[#This Row],[Rate]] -> 0 | O46: =Table578[[#This Row],[Quantity2]]*Table578[[#This Row],[Rate]] -> 0
K47: Total | L47: =SUM(L37:L46) -> 0 | M47: =SUM(M37:M46) -> 0 | N47: =SUM(N37:N46) -> 962.22 | O47: =SUM(O37:O46) -> 107101.54 | P47: =SUM(P37:P46) -> 412.38 | Q47: =SUM(Q37:Q46) -> 45900.66
G52: Preliminary designs for the expansion of the industrial city in riyadh | L52: Invoice 1 | N52: Invoice 2 | P52: Invoice 3
G53: Description | H53: Category | I53: Total Quantity | J53: Remaining quantity | K53: Rate | L53: Quantity | M53: Amount | N53: Quantity2 | O53: Amount3 | P53: Quantity22 | Q53: Amount33
G54: Lead Engineer/ Discipline Engineer | H54: A1 | K54: 465 | M54: =Table57811[[#This Row],[Quantity2]]*Table57811[[#This Row],[Rate]] -> 0 | O54: =Table57811[[#This Row],[Quantity2]]*Table57811[[#This Row],[Rate]] -> 0
G55: Sr. Engineer/ Senior discipline specialist | H55: B1 | K55: 390 | M55: =Table57811[[#This Row],[Quantity2]]*Table57811[[#This Row],[Rate]] -> 0 | O55: =Table57811[[#This Row],[Quantity2]]*Table57811[[#This Row],[Rate]] -> 0
G56: Engineer/ Discipline Specialist | H56: C1 | K56: 200 | M56: =Table57811[[#This Row],[Quantity2]]*Table57811[[#This Row],[Rate]] -> 0 | O56: =Table57811[[#This Row],[Quantity2]]*Table57811[[#This Row],[Rate]] -> 0
G57: Draftsman | H57: D1 | K57: 90 | M57: =Table57811[[#This Row],[Quantity2]]*Table57811[[#This Row],[Rate]] -> 0
G58: Lead engineer/ discipline expert | H58: A2 | I58: 29 | J58: =Table57811[[#This Row],[Total Quantity]]-Table57811[[#This Row],[Quantity2]] -> 29 | K58: 275 | P58: 20.3 | Q58: =Table57811[[#This Row],[Rate]]*Table57811[[#This Row],[Quantity22]] -> 5582.5
G59: Sr. Engineer/ Senior discipline specialist | H59: B2 | I59: 87 | J59: =Table57811[[#This Row],[Total Quantity]]-Table57811[[#This Row],[Quantity2]] -> 87 | K59: 180 | P59: 60.9 | Q59: =Table57811[[#This Row],[Rate]]*Table57811[[#This Row],[Quantity22]] -> 10962
G60: Engineer/ Discipline Specialist | H60: C2 | I60: 430 | J60: =Table57811[[#This Row],[Total Quantity]]-Table57811[[#This Row],[Quantity2]] -> 430 | K60: 145 | P60: 301 | Q60: =Table57811[[#This Row],[Rate]]*Table57811[[#This Row],[Quantity22]] -> 43645
G61: Draftsman | H61: D2 | I61: 856 | J61: =Table57811[[#This Row],[Total Quantity]]-Table57811[[#This Row],[Quantity2]] -> 856 | K61: 82 | P61: 599.2 | Q61: =Table57811[[#This Row],[Rate]]*Table57811[[#This Row],[Quantity22]] -> 49134.4
G62: E2/ Project Manager | H62: E2 | K62: 275 | M62: =Table57811[[#This Row],[Quantity2]]*Table57811[[#This Row],[Rate]] -> 0 | O62: =Table57811[[#This Row],[Quantity2]]*Table57811[[#This Row],[Rate]] -> 0
G63: F2/ Project Manager | H63: F2 | K63: 180 | M63: =Table57811[[#This Row],[Quantity2]]*Table57811[[#This Row],[Rate]] -> 0 | O63: =Table57811[[#This Row],[Quantity2]]*Table57811[[#This Row],[Rate]] -> 0
K64: Total | L64: =SUM(L54:L63) -> 0 | M64: =SUM(M54:M63) -> 0 | N64: =SUM(N54:N63) -> 0 | O64: =SUM(O54:O63) -> 0 | P64: =SUM(P54:P63) -> 981.4 | Q64: =SUM(Q54:Q63) -> 109323.9
G70: Incubators in AlQassim oasis | L70: Invoice 6 | N70: Invoice 7 | P70: Invoice 8
G71: Description | H71: Category | I71: Total Quantity | J71: Remaining quantity | K71: Rate | L71: Quantity | M71: Amount | N71: Quantity2 | O71: Amount3 | P71: Quantity22 | Q71: Amount33
G72: Lead Engineer/ Discipline Engineer | H72: A1 | J72: =Table5716[[#This Row],[Total Quantity]]-Table5716[[#This Row],[Quantity22]] -> 0 | K72: 465 | M72: =Table5716[[#This Row],[Quantity]]*Table5716[[#This Row],[Rate]] -> 0 | O72: =Table5716[[#This Row],[Quantity2]]*Table5716[[#This Row],[Rate]] -> 0
G73: Sr. Engineer/ Senior discipline specialist | H73: B1 | J73: =Table5716[[#This Row],[Total Quantity]]-Table5716[[#This Row],[Quantity22]] -> 0 | K73: 390 | M73: =Table5716[[#This Row],[Quantity]]*Table5716[[#This Row],[Rate]] -> 0 | O73: =Table5716[[#This Row],[Quantity2]]*Table5716[[#This Row],[Rate]] -> 0
G74: Engineer/ Discipline Specialist | H74: C1 | J74: =Table5716[[#This Row],[Total Quantity]]-Table5716[[#This Row],[Quantity22]] -> 0 | K74: 200 | M74: =Table5716[[#This Row],[Quantity]]*Table5716[[#This Row],[Rate]] -> 0 | O74: =Table5716[[#This Row],[Quantity2]]*Table5716[[#This Row],[Rate]] -> 0
G75: Draftsman | H75: D1 | J75: =Table5716[[#This Row],[Total Quantity]]-Table5716[[#This Row],[Quantity22]] -> 0 | K75: 90 | M75: =Table5716[[#This Row],[Quantity]]*Table5716[[#This Row],[Rate]] -> 0 | O75: =Table5716[[#This Row],[Quantity2]]*Table5716[[#This Row],[Rate]] -> 0
G76: Lead engineer/ discipline expert | H76: A2 | I76: 700 | J76: =Table5716[[#This Row],[Total Quantity]]-Table5716[[#This Row],[Quantity]]-Table5716[[#This Row],[Quantity2]] -> 105 | K76: 275 | L76: 350 | M76: =Table5716[[#This Row],[Quantity]]*Table5716[[#This Row],[Rate]] -> 96250 | N76: 245 | O76: =Table5716[[#This Row],[Quantity2]]*Table5716[[#This Row],[Rate]] -> 67375
G77: Sr. Engineer/ Senior discipline specialist | H77: B2 | I77: 1300 | J77: =Table5716[[#This Row],[Total Quantity]]-Table5716[[#This Row],[Quantity]]-Table5716[[#This Row],[Quantity2]] -> 195 | K77: 180 | L77: 650 | M77: =Table5716[[#This Row],[Quantity]]*Table5716[[#This Row],[Rate]] -> 117000 | N77: 455 | O77: =Table5716[[#This Row],[Quantity2]]*Table5716[[#This Row],[Rate]] -> 81900
G78: Engineer/ Discipline Specialist | H78: C2 | I78: 5200 | J78: =Table5716[[#This Row],[Total Quantity]]-Table5716[[#This Row],[Quantity]]-Table5716[[#This Row],[Quantity2]] -> 780 | K78: 145 | L78: 2600 | M78: =Table5716[[#This Row],[Quantity]]*Table5716[[#This Row],[Rate]] -> 377000 | N78: 1820 | O78: =Table5716[[#This Row],[Quantity2]]*Table5716[[#This Row],[Rate]] -> 263900
G79: Draftsman | H79: D2 | I79: 5800 | J79: =Table5716[[#This Row],[Total Quantity]]-Table5716[[#This Row],[Quantity]]-Table5716[[#This Row],[Quantity2]] -> 870 | K79: 82 | L79: 2900 | M79: =Table5716[[#This Row],[Quantity]]*Table5716[[#This Row],[Rate]] -> 237800 | N79: 2030 | O79: =Table5716[[#This Row],[Quantity2]]*Table5716[[#This Row],[Rate]] -> 166460
G80: E2/ Project Manager | H80: E2 | K80: 275 | M80: =Table5716[[#This Row],[Quantity]]*Table5716[[#This Row],[Rate]] -> 0 | O80: =Table5716[[#This Row],[Quantity2]]*Table5716[[#This Row],[Rate]] -> 0
G81: F2/ Project Manager | H81: F2 | K81: 180 | M81: =Table5716[[#This Row],[Quantity]]*Table5716[[#This Row],[Rate]] -> 0 | O81: =Table5716[[#This Row],[Quantity2]]*Table5716[[#This Row],[Rate]] -> 0
K82: Total | M82: =SUM(M73:M80) -> 828050 | O82: =SUM(O73:O80) -> 579635
G89: Jeddah 1 Expansion | L89: Invoice 6 | N89: Invoice 7 | P89: Invoice 8 | R89: Invoice 9 | T89: Invoice 10 | V89: Invoice 11 | X89: Invoice 12
G90: Description | H90: Category | I90: Total Quantity | J90: Remaining quantity | K90: Rate | L90: Quantity | M90: Amount | N90: Quantity2 | O90: Amount3 | P90: Quantity22 | Q90: Amount33 | R90: Quantity222 | S90: Amount333 | T90: Quantity222 | U90: Amount333 | V90: Quantity222 | W90: Amount333 | X90: Quantity222 | Y90: Amount333
G91: Lead Engineer/ Discipline Engineer | H91: A1 | J91: =Table571617[[#This Row],[Total Quantity]]-Table571617[[#This Row],[Quantity22]] -> 0 | K91: 465 | M91: =Table571617[[#This Row],[Quantity]]*Table571617[[#This Row],[Rate]] -> 0 | O91: =Table571617[[#This Row],[Quantity2]]*Table571617[[#This Row],[Rate]] -> 0 | S91: =Table571617[[#This Row],[Quantity222]]*Table571617[[#This Row],[Rate]] -> 0 | U91: =Table571617[[#This Row],[Quantity222]]*Table571617[[#This Row],[Rate]] -> 0 | W91: =Table571617[[#This Row],[Quantity222]]*Table571617[[#This Row],[Rate]] -> 0 | Y91: =Table571617[[#This Row],[Quantity222]]*Table571617[[#This Row],[Rate]] -> 0
G92: Sr. Engineer/ Senior discipline specialist | H92: B1 | J92: =Table571617[[#This Row],[Total Quantity]]-Table571617[[#This Row],[Quantity22]] -> 0 | K92: 390 | M92: =Table571617[[#This Row],[Quantity]]*Table571617[[#This Row],[Rate]] -> 0 | O92: =Table571617[[#This Row],[Quantity2]]*Table571617[[#This Row],[Rate]] -> 0 | S92: =Table571617[[#This Row],[Quantity222]]*Table571617[[#This Row],[Rate]] -> 0 | U92: =Table571617[[#This Row],[Quantity222]]*Table571617[[#This Row],[Rate]] -> 0 | W92: =Table571617[[#This Row],[Quantity222]]*Table571617[[#This Row],[Rate]] -> 0 | Y92: =Table571617[[#This Row],[Quantity222]]*Table571617[[#This Row],[Rate]] -> 0
G93: Engineer/ Discipline Specialist | H93: C1 | J93: =Table571617[[#This Row],[Total Quantity]]-Table571617[[#This Row],[Quantity22]] -> 0 | K93: 200 | M93: =Table571617[[#This Row],[Quantity]]*Table571617[[#This Row],[Rate]] -> 0 | O93: =Table571617[[#This Row],[Quantity2]]*Table571617[[#This Row],[Rate]] -> 0 | S93: =Table571617[[#This Row],[Quantity222]]*Table571617[[#This Row],[Rate]] -> 0 | U93: =Table571617[[#This Row],[Quantity222]]*Table571617[[#This Row],[Rate]] -> 0 | W93: =Table571617[[#This Row],[Quantity222]]*Table571617[[#This Row],[Rate]] -> 0
G94: Draftsman | H94: D1 | J94: =Table571617[[#This Row],[Total Quantity]]-Table571617[[#This Row],[Quantity22]] -> 0 | K94: 90 | M94: =Table571617[[#This Row],[Quantity]]*Table571617[[#This Row],[Rate]] -> 0 | O94: =Table571617[[#This Row],[Quantity2]]*Table571617[[#This Row],[Rate]] -> 0 | S94: =Table571617[[#This Row],[Quantity222]]*Table571617[[#This Row],[Rate]] -> 0
G95: Lead engineer/ discipline expert | H95: A2 | I95: 1800 | J95: =Table571617[[#This Row],[Total Quantity]]-Table571617[[#This Row],[Quantity]]-Table571617[[#This Row],[Quantity2]]-Table571617[[#This Row],[Quantity222]] -> 1260 | K95: 275 | N95: 270 | O95: =Table571617[[#This Row],[Quantity2]]*Table571617[[#This Row],[Rate]] -> 74250 | R95: 270 | S95: =Table571617[[#This Row],[Quantity222]]*Table571617[[#This Row],[Rate]] -> 74250 | T95: 450 | U95: =T95*Table571617[[#This Row],[Rate]] -> 123750 | V95: 630.00036 | W95: =V95*Table571617[[#This Row],[Rate]] -> 173250.1 | X95: 179.99964 | Y95: =X95*Table571617[[#This Row],[Rate]] -> 49499.9 | Z95: 173250.1 | AA95: =Z95/Table571617[[#This Row],[Rate]] -> 630.00036
G96: Sr. Engineer/ Senior discipline specialist | H96: B2 | I96: 1900 | J96: =Table571617[[#This Row],[Total Quantity]]-Table571617[[#This Row],[Quantity]]-Table571617[[#This Row],[Quantity2]]-Table571617[[#This Row],[Quantity222]] -> 1330 | K96: 180 | N96: 285 | O96: =Table571617[[#This Row],[Quantity2]]*Table571617[[#This Row],[Rate]] -> 51300 | R96: 285 | S96: =Table571617[[#This Row],[Quantity222]]*Table571617[[#This Row],[Rate]] -> 51300 | T96: 475 | U96: =T96*Table571617[[#This Row],[Rate]] -> 85500 | V96: 665.00039 | W96: =V96*Table571617[[#This Row],[Rate]] -> 119700.07 | X96: 189.99961 | Y96: =X96*Table571617[[#This Row],[Rate]] -> 34199.93 | Z96: 119700.07 | AA96: =Z96/Table571617[[#This Row],[Rate]] -> 665.00039
G97: Engineer/ Discipline Specialist | H97: C2 | I97: 7150 | J97: =Table571617[[#This Row],[Total Quantity]]-Table571617[[#This Row],[Quantity]]-Table571617[[#This Row],[Quantity2]]-Table571617[[#This Row],[Quantity222]] -> 5005 | K97: 145 | N97: 1072.5 | O97: =Table571617[[#This Row],[Quantity2]]*Table571617[[#This Row],[Rate]] -> 155512.5 | R97: 1072.5 | S97: =Table571617[[#This Row],[Quantity222]]*Table571617[[#This Row],[Rate]] -> 155512.5 | T97: 1787.5 | U97: =T97*Table571617[[#This Row],[Rate]] -> 259187.5 | V97: 2502.5014 | W97: =V97*Table571617[[#This Row],[Rate]] -> 362862.7 | X97: 714.99862 | Y97: =X97*Table571617[[#This Row],[Rate]] -> 103674.8 | Z97: 362862.7 | AA97: =Z97/Table571617[[#This Row],[Rate]] -> 2502.5014
G98: Draftsman | H98: D2 | I98: 8370 | J98: =Table571617[[#This Row],[Total Quantity]]-Table571617[[#This Row],[Quantity]]-Table571617[[#This Row],[Quantity2]]-Table571617[[#This Row],[Quantity222]] -> 5859 | K98: 82 | N98: 1255.5 | O98: =Table571617[[#This Row],[Quantity2]]*Table571617[[#This Row],[Rate]] -> 102951 | R98: 1255.5 | S98: =Table571617[[#This Row],[Quantity222]]*Table571617[[#This Row],[Rate]] -> 102951 | T98: 2092.5 | U98: =T98*Table571617[[#This Row],[Rate]] -> 171585 | V98: 2929.5016 | W98: =V98*Table571617[[#This Row],[Rate]] -> 240219.13 | X98: 836.99841 | Y98: =X98*Table571617[[#This Row],[Rate]] -> 68633.87 | Z98: 240219.13 | AA98: =Z98/Table571617[[#This Row],[Rate]] -> 2929.5016
G99: E2/ Project Manager | H99: E2 | K99: 275 | O99: =Table571617[[#This Row],[Quantity2]]*Table571617[[#This Row],[Rate]] -> 0 | S99: =Table571617[[#This Row],[Quantity222]]*Table571617[[#This Row],[Rate]] -> 0
G100: F2/ Project Manager | H100: F2 | K100: 180 | O100: =Table571617[[#This Row],[Quantity2]]*Table571617[[#This Row],[Rate]] -> 0 | S100: =Table571617[[#This Row],[Quantity222]]*Table571617[[#This Row],[Rate]] -> 0
K101: Total | O101: =SUM(O92:O99) -> 384013.5 | S101: =SUM(S92:S99) -> 384013.5 | T101: =SUM(T92:T99) -> 4805 | U101: =SUM(U92:U99) -> 640022.5 | V101: =SUM(V92:V99) -> 6727.0037 | W101: =SUM(W92:W99) -> 896032 | X101: =SUM(X92:X99) -> 1921.9963 | Y101: =SUM(Y92:Y99) -> 256008.5
G112: Labour camp in AlKharj | L112: Invoice 6 | N112: Invoice 7 | P112: Invoice 8 | R112: Invoice 9
G113: Description | H113: Category | I113: Total Quantity | J113: Remaining quantity | K113: Rate | L113: Quantity | M113: Amount | N113: Quantity2 | O113: Amount3 | P113: Quantity22 | Q113: Amount33 | R113: Quantity222 | S113: Amount333 | T113: Column1 | U113: Column2
G114: Lead Engineer/ Discipline Engineer | H114: A1 | J114: =Table57161718[[#This Row],[Total Quantity]]-Table57161718[[#This Row],[Quantity22]] -> 0 | K114: 465 | M114: =Table57161718[[#This Row],[Quantity]]*Table57161718[[#This Row],[Rate]] -> 0 | O114: =Table57161718[[#This Row],[Quantity2]]*Table57161718[[#This Row],[Rate]] -> 0 | S114: =Table57161718[[#This Row],[Quantity222]]*Table57161718[[#This Row],[Rate]] -> 0
G115: Sr. Engineer/ Senior discipline specialist | H115: B1 | J115: =Table57161718[[#This Row],[Total Quantity]]-Table57161718[[#This Row],[Quantity22]] -> 0 | K115: 390 | M115: =Table57161718[[#This Row],[Quantity]]*Table57161718[[#This Row],[Rate]] -> 0 | O115: =Table57161718[[#This Row],[Quantity2]]*Table57161718[[#This Row],[Rate]] -> 0 | S115: =Table57161718[[#This Row],[Quantity222]]*Table57161718[[#This Row],[Rate]] -> 0
G116: Engineer/ Discipline Specialist | H116: C1 | J116: =Table57161718[[#This Row],[Total Quantity]]-Table57161718[[#This Row],[Quantity22]] -> 0 | K116: 200 | M116: =Table57161718[[#This Row],[Quantity]]*Table57161718[[#This Row],[Rate]] -> 0 | O116: =Table57161718[[#This Row],[Quantity2]]*Table57161718[[#This Row],[Rate]] -> 0 | S116: =Table57161718[[#This Row],[Quantity222]]*Table57161718[[#This Row],[Rate]] -> 0
G117: Draftsman | H117: D1 | J117: =Table57161718[[#This Row],[Total Quantity]]-Table57161718[[#This Row],[Quantity22]] -> 0 | K117: 90 | M117: =Table57161718[[#This Row],[Quantity]]*Table57161718[[#This Row],[Rate]] -> 0 | Q117: =Table57161718[[#This Row],[Quantity2]]*Table57161718[[#This Row],[Rate]] -> 0 | S117: =Table57161718[[#This Row],[Quantity222]]*Table57161718[[#This Row],[Rate]] -> 0
G118: Lead engineer/ discipline expert | H118: A2 | I118: 64 | J118: =Table57161718[[#This Row],[Total Quantity]]-Table57161718[[#This Row],[Quantity]]-Table57161718[[#This Row],[Quantity22]]-Table57161718[[#This Row],[Quantity222]] -> 0.36363636 | K118: 275 | P118: 31.818182 | Q118: =Table57161718[[#This Row],[Quantity22]]*Table57161718[[#This Row],[Rate]] -> 8750 | R118: 31.818182 | S118: =Table57161718[[#This Row],[Quantity222]]*Table57161718[[#This Row],[Rate]] -> 8750
G119: Sr. Engineer/ Senior discipline specialist | H119: B2 | I119: 194 | J119: =Table57161718[[#This Row],[Total Quantity]]-Table57161718[[#This Row],[Quantity]]-Table57161718[[#This Row],[Quantity22]]-Table57161718[[#This Row],[Quantity222]] -> -0.44444444 | K119: 180 | P119: 97.222222 | Q119: =Table57161718[[#This Row],[Quantity22]]*Table57161718[[#This Row],[Rate]] -> 17500 | R119: 97.222222 | S119: =Table57161718[[#This Row],[Quantity222]]*Table57161718[[#This Row],[Rate]] -> 17500
G120: Engineer/ Discipline Specialist | H120: C2 | I120: 966 | J120: =Table57161718[[#This Row],[Total Quantity]]-Table57161718[[#This Row],[Quantity]]-Table57161718[[#This Row],[Quantity22]]-Table57161718[[#This Row],[Quantity222]] -> 0.48275862 | K120: 145 | P120: 482.75862 | Q120: =Table57161718[[#This Row],[Quantity22]]*Table57161718[[#This Row],[Rate]] -> 70000 | R120: 482.75862 | S120: =Table57161718[[#This Row],[Quantity222]]*Table57161718[[#This Row],[Rate]] -> 70000
G121: Draftsman | H121: D2 | I121: 1921 | J121: =Table57161718[[#This Row],[Total Quantity]]-Table57161718[[#This Row],[Quantity]]-Table57161718[[#This Row],[Quantity22]]-Table57161718[[#This Row],[Quantity222]] -> 0.26829268 | K121: 82 | P121: 960.36585 | Q121: =Table57161718[[#This Row],[Quantity22]]*Table57161718[[#This Row],[Rate]] -> 78750 | R121: 960.36585 | S121: =Table57161718[[#This Row],[Quantity222]]*Table57161718[[#This Row],[Rate]] -> 78750
G122: E2/ Project Manager | H122: E2 | K122: 275 | Q122: =Table57161718[[#This Row],[Quantity22]]*Table57161718[[#This Row],[Rate]] -> 0 | S122: =Table57161718[[#This Row],[Quantity222]]*Table57161718[[#This Row],[Rate]] -> 0
G123: F2/ Project Manager | H123: F2 | K123: 180 | Q123: =Table57161718[[#This Row],[Quantity2]]*Table57161718[[#This Row],[Rate]] -> 0 | S123: =Table57161718[[#This Row],[Quantity222]]*Table57161718[[#This Row],[Rate]] -> 0 | W123: 210000
K124: Total | Q124: =SUM(Q117:Q121) -> 175000 | S124: =SUM(S117:S121) -> 175000 | W124: 693000
W125: 85000
W126: 384013.5
W127: 175000
G134: Potable water pipeline supply and connection to kharj 1 | L134: Invoice 6 | N134: Invoice 7 | P134: Invoice 8 | R134: Invoice 9 | T134: Invoice13 | V134: Invoice16
G135: Description | H135: Category | I135: Total Quantity | J135: Remaining quantity | K135: Rate | L135: Quantity | M135: Amount | N135: Quantity2 | O135: Amount3 | P135: Column1 | Q135: Column2 | R135: Quantity222 | S135: Amount333 | T135: Column3 | U135: Column4 | V135: Column5 | W135: Column6
G136: Lead Engineer/ Discipline Engineer | H136: A1 | J136: =Table5716171819[[#This Row],[Total Quantity]]-Table5716171819[[#This Row],[Column1]] -> 0 | K136: 465 | M136: =Table5716171819[[#This Row],[Quantity]]*Table5716171819[[#This Row],[Rate]] -> 0 | O136: =Table5716171819[[#This Row],[Quantity2]]*Table5716171819[[#This Row],[Rate]] -> 0 | U136: =Table5716171819[[#This Row],[Column3]]*Table5716171819[[#This Row],[Rate]] -> 0 | W136: =Table5716171819[[#This Row],[Column5]]*Table5716171819[[#This Row],[Rate]] -> 0
G137: Sr. Engineer/ Senior discipline specialist | H137: B1 | J137: =Table5716171819[[#This Row],[Total Quantity]]-Table5716171819[[#This Row],[Column1]] -> 0 | K137: 390 | M137: =Table5716171819[[#This Row],[Quantity]]*Table5716171819[[#This Row],[Rate]] -> 0 | O137: =Table5716171819[[#This Row],[Quantity2]]*Table5716171819[[#This Row],[Rate]] -> 0 | U137: =Table5716171819[[#This Row],[Column3]]*Table5716171819[[#This Row],[Rate]] -> 0 | W137: =Table5716171819[[#This Row],[Column5]]*Table5716171819[[#This Row],[Rate]] -> 0
G138: Engineer/ Discipline Specialist | H138: C1 | J138: =Table5716171819[[#This Row],[Total Quantity]]-Table5716171819[[#This Row],[Column1]] -> 0 | K138: 200 | M138: =Table5716171819[[#This Row],[Quantity]]*Table5716171819[[#This Row],[Rate]] -> 0 | O138: =Table5716171819[[#This Row],[Quantity2]]*Table5716171819[[#This Row],[Rate]] -> 0 | U138: =Table5716171819[[#This Row],[Column3]]*Table5716171819[[#This Row],[Rate]] -> 0 | W138: =Table5716171819[[#This Row],[Column5]]*Table5716171819[[#This Row],[Rate]] -> 0
...

Sheet Meinhardt (RDH1-01-006)
A20: Description | B20: Category | C20: Quanty | D20: Rate | E20: total
A21: Lead Engineer/ Discipline Engineer | B21: A1 | C21: 13900.94 | D21: 504.35 | E21: =D21*C21 -> 7010939.1
A22: Sr. Engineer/ Senior discipline specialist | B22: B1 | C22: 13100.146 | D22: 391.3 | E22: =D22*C22 -> 5126087
A23: Engineer/ Discipline Specialist | B23: C1 | C23: 16309.802 | D23: 286.96 | E23: =D23*C23 -> 4680260.9 | I23: Riyadh 1 Industrial City Masterplan
A24: Draftsman | B24: D1 | C24: 17999.315 | D24: 173.91 | E24: =D24*C24 -> 3130260.9 | I24: Description | J24: Category | K24: Rate | L24: Quanty | M24: Total
A25: Project Manager | B25: E1 | C25: 5000.0368 | D25: 591.3 | E25: =D25*C25 -> 2956521.7 | I25: Lead Engineer/ Discipline Engineer | J25: A1 | K25: 504.35 | L25: =M25/K25 -> 9285.399 | M25: 4683091
A26: Project Manager | B26: F1 | C26: 7650.085 | D26: 313.04 | E26: =D26*C26 -> 2394782.6 | I26: Sr. Engineer/ Senior discipline specialist | J26: B1 | K26: 391.3 | L26: =M26/K26 -> 8750.4932 | M26: 3424068
E27: =SUM(E21:E26) -> 25298852 | I27: Engineer/ Discipline Specialist | J27: C1 | K27: 286.96 | L27: =M27/K27 -> 10894.445 | M27: 3126270
I28: Draftsman | J28: D1 | K28: 173.91 | L28: =M28/K28 -> 12022.989 | M28: 2090918
I29: Project Manager | J29: E1 | K29: 591.3 | L29: =M29/K29 -> 3339.8698 | M29: 1974865
I30: Project Manager | J30: F1 | K30: 313.04 | L30: =M30/K30 -> 5110.0211 | M30: 1599641
I31: TOTAL | M31: =SUM(M25:M30) -> 16898853
I33: Riyadh 1-Codes and Guidelines
I34: Description | J34: Category | K34: Rate | L34: Quanty | M34: Total
I35: Lead Engineer/ Discipline Engineer | J35: A1 | K35: 504.35 | L35: =M35/K35 -> 3406.7096 | M35: 1718174
I36: Sr. Engineer/ Senior discipline specialist | J36: B1 | K36: 391.3 | L36: =M36/K36 -> 3210.4574 | M36: 1256252
I37: Engineer/ Discipline Specialist | J37: C1 | K37: 286.96 | L37: =M37/K37 -> 3997.0484 | M37: 1146993
I38: Draftsman | J38: D1 | K38: 173.91 | L38: =M38/K38 -> 4411.0977 | M38: 767134
I39: Project Manager | J39: E1 | K39: 591.3 | L39: =M39/K39 -> 1225.3611 | M39: 724556
I40: Project Manager | J40: F1 | K40: 313.04 | L40: =M40/K40 -> 1874.8083 | M40: 586890
I41: TOTAL | M41: =SUM(M35:M40) -> 6199999
I43: Riyadh 1-RBF-Value Engineering
I44: Description | J44: Category | K44: Rate | L44: Quanty | M44: Total
I45: Lead Engineer/ Discipline Engineer | J45: A1 | K45: 504.35 | L45: =M45/K45 -> 659.36354 | M45: 332550
I46: Sr. Engineer/ Senior discipline specialist | J46: B1 | K46: 391.3 | L46: =M46/K46 -> 621.38002 | M46: 243146
I47: Engineer/ Discipline Specialist | J47: C1 | K47: 286.96 | L47: =M47/K47 -> 773.6235 | M47: 221999
I48: Draftsman | J48: D1 | K48: 173.91 | L48: =M48/K48 -> 853.76344 | M48: 148478
I49: Project Manager | J49: E1 | K49: 591.3 | L49: =M49/K49 -> 237.16726 | M49: 140237
I50: Project Manager | J50: F1 | K50: 313.04 | L50: =M50/K50 -> 362.86737 | M50: 113592
I51: TOTAL | M51: =SUM(M45:M50) -> 1200002
I54: Multi-Story Building
I55: Description | J55: Category | K55: Rate | L55: Quanty | M55: Total
I56: Lead Engineer/ Discipline Engineer | J56: A1 | K56: 504.35 | L56: =M56/K56 -> 549.46961 | M56: 277125
I57: Sr. Engineer/ Senior discipline specialist | J57: B1 | K57: 391.3 | L57: =M57/K57 -> 517.81498 | M57: 202621
I58: Engineer/ Discipline Specialist | J58: C1 | K58: 286.96 | L58: =M58/K58 -> 644.68567 | M58: 184999
I59: Draftsman | J59: D1 | K59: 173.91 | L59: =M59/K59 -> 711.4657 | M59: 123731
I60: Project Manager | J60: E1 | K60: 591.3 | L60: =M60/K60 -> 197.6391 | M60: 116864
I61: Project Manager | J61: F1 | K61: 313.04 | L61: =M61/K61 -> 302.38947 | M61: 94660
I62: TOTAL | M62: =SUM(M56:M61) -> 1000000

Sheet Logistic
G5: Logistics | J5: Logistic Zones (JDH3,DAM3,MAD,MKH2) | L5: Invoice 1 | N5: Invoice 2 | P5: Invoice 3 | R5: Invoice 4 | T5: Invoice 5 | V5: Invoice 6 | X5: Invoice 7
A6: Description | C6: Total quantity | D6: Remaining quantity | G6: Description | H6: Category | I6: Total Quantity | J6: Remaining quantity | K6: Rate | L6: Amount | M6: Quantity2 | N6: Amount3 | O6: Amount36 | P6: Quantity25 | Q6: Amount363 | R6: Quantity26 | S6: Amount364 | T6: Quantity27 | U6: Amount365 | V6: Quantity28 | W6: Amount366 | X6: Quantity29 | Y6: Amount367
A7: Lead Engineer/ Discipline Engineer | B7: A1 | C7: 6000 | G7: Lead Engineer/ Discipline Engineer | H7: A1 | J7: =Table52529[[#This Row],[Total Quantity]]-#REF!-Table52529[[#This Row],[Quantity2]] -> #REF! | K7: 478 | L7: 110 | M7: =Table52529[[#This Row],[Amount]]*Table52529[[#This Row],[Rate]] -> 52580 | N7: 110 | O7: =Table52529[[#This Row],[Amount3]]*Table52529[[#This Row],[Rate]] -> 52580 | P7: 97.5 | Q7: =Table52529[[#This Row],[Quantity25]]*Table52529[[#This Row],[Rate]] -> 46605 | R7: 747.88 | S7: =Table52529[[#This Row],[Quantity26]]*Table52529[[#This Row],[Rate]] -> 357486.64 | T7: 650.38 | U7: =T7*Table52529[[#This Row],[Rate]] -> 310881.64 | V7: 554.63 | W7: =V7*Table52529[[#This Row],[Rate]] -> 265113.14 | X7: 587.63 | Y7: =X7*Table52529[[#This Row],[Rate]] -> 280887.14
A8: Sr. Engineer/ Senior discipline specialist | B8: B1 | C8: 378 | G8: Sr. Engineer/ Senior discipline specialist | H8: B1 | J8: =Table52529[[#This Row],[Total Quantity]]-#REF!-Table52529[[#This Row],[Quantity2]] -> #REF! | K8: 378 | L8: 600 | M8: =Table52529[[#This Row],[Amount]]*Table52529[[#This Row],[Rate]] -> 226800 | N8: 600 | O8: =Table52529[[#This Row],[Amount3]]*Table52529[[#This Row],[Rate]] -> 226800 | P8: 172.5 | Q8: =Table52529[[#This Row],[Quantity25]]*Table52529[[#This Row],[Rate]] -> 65205 | R8: 1690 | S8: =Table52529[[#This Row],[Quantity26]]*Table52529[[#This Row],[Rate]] -> 638820 | T8: 1517.5 | U8: =T8*Table52529[[#This Row],[Rate]] -> 573615 | V8: 3060 | W8: =V8*Table52529[[#This Row],[Rate]] -> 1156680 | X8: 3240 | Y8: =X8*Table52529[[#This Row],[Rate]] -> 1224720
A9: Engineer/ Discipline Specialist | B9: C1 | C9: 302 | G9: Engineer/ Discipline Specialist | H9: C1 | J9: =Table52529[[#This Row],[Total Quantity]]-#REF!-Table52529[[#This Row],[Quantity2]] -> #REF! | K9: 302 | L9: 850 | M9: =Table52529[[#This Row],[Amount]]*Table52529[[#This Row],[Rate]] -> 256700 | N9: 850 | O9: =Table52529[[#This Row],[Amount3]]*Table52529[[#This Row],[Rate]] -> 256700 | P9: 210 | Q9: =Table52529[[#This Row],[Quantity25]]*Table52529[[#This Row],[Rate]] -> 63420 | R9: 2165 | S9: =Table52529[[#This Row],[Quantity26]]*Table52529[[#This Row],[Rate]] -> 653830 | T9: 1955 | U9: =T9*Table52529[[#This Row],[Rate]] -> 590410 | V9: 4335 | W9: =V9*Table52529[[#This Row],[Rate]] -> 1309170 | X9: 4591.5 | Y9: =X9*Table52529[[#This Row],[Rate]] -> 1386633
A10: Draftsman | B10: D1 | C10: 220 | G10: Draftsman | H10: D1 | J10: =Table52529[[#This Row],[Total Quantity]]-#REF!-Table52529[[#This Row],[Quantity2]] -> #REF! | K10: 220 | L10: 700 | M10: =Table52529[[#This Row],[Amount]]*Table52529[[#This Row],[Rate]] -> 154000 | N10: 700 | O10: =Table52529[[#This Row],[Amount3]]*Table52529[[#This Row],[Rate]] -> 154000 | P10: 210 | Q10: =Table52529[[#This Row],[Quantity25]]*Table52529[[#This Row],[Rate]] -> 46200 | R10: 2030 | S10: =Table52529[[#This Row],[Quantity26]]*Table52529[[#This Row],[Rate]] -> 446600 | T10: 1820 | U10: =T10*Table52529[[#This Row],[Rate]] -> 400400 | V10: 3570 | W10: =V10*Table52529[[#This Row],[Rate]] -> 785400 | X10: 3795 | Y10: =X10*Table52529[[#This Row],[Rate]] -> 834900
A11: Project Manager | B11: E1 | C11: 478 | D11: =C11-Table52529[[#This Row],[Total Quantity]]-I22-I37-I54-I72-I91-I114-I136-I155-I173 -> 478 | G11: Project Manager | H11: E1 | I11: 0 | J11: =Table52529[[#This Row],[Total Quantity]]-#REF!-Table52529[[#This Row],[Quantity2]] -> #REF! | K11: 478 | L11: 500 | M11: =Table52529[[#This Row],[Amount]]*Table52529[[#This Row],[Rate]] -> 239000 | N11: 500 | O11: =Table52529[[#This Row],[Amount3]]*Table52529[[#This Row],[Rate]] -> 239000 | P11: 112.5 | Q11: =Table52529[[#This Row],[Quantity25]]*Table52529[[#This Row],[Rate]] -> 53775 | R11: 1200 | S11: =Table52529[[#This Row],[Quantity26]]*Table52529[[#This Row],[Rate]] -> 573600 | T11: 1087.5 | U11: =T11*Table52529[[#This Row],[Rate]] -> 519825 | V11: 2550 | W11: =V11*Table52529[[#This Row],[Rate]] -> 1218900 | X11: 2700 | Y11: =X11*Table52529[[#This Row],[Rate]] -> 1290600
A12: Project Manager | B12: F1 | C12: 172 | D12: =C12-Table52529[[#This Row],[Total Quantity]]-I23-I38-I55-I73-I92-I115-I137-I156-I174 -> 172 | G12: Project Manager | H12: F1 | I12: 0 | J12: =Table52529[[#This Row],[Total Quantity]]-#REF!-Table52529[[#This Row],[Quantity2]] -> #REF! | K12: 172 | L12: 181.79651 | M12: =Table52529[[#This Row],[Amount]]*Table52529[[#This Row],[Rate]] -> 31269 | N12: 181.79651 | O12: =Table52529[[#This Row],[Amount3]]*Table52529[[#This Row],[Rate]] -> 31269 | P12: 74.86 | Q12: =Table52529[[#This Row],[Quantity25]]*Table52529[[#This Row],[Rate]] -> 12875.92 | R12: 665.81 | S12: =Table52529[[#This Row],[Quantity26]]*Table52529[[#This Row],[Rate]] -> 114519.32 | T12: 590.95 | U12: =T12*Table52529[[#This Row],[Rate]] -> 101643.4 | V12: 944.88 | W12: =V12*Table52529[[#This Row],[Rate]] -> 162519.36 | X12: 977.6 | Y12: =X12*Table52529[[#This Row],[Rate]] -> 168147.2
G13: TOTAL | J13: =Table52529[[#This Row],[Total Quantity]]-#REF!-Table52529[[#This Row],[Quantity2]] -> #REF! | M13: =SUM(M7:M12) -> 960349 | O13: =SUM(O7:O12) -> 960349 | Q13: 288080.85 | S13: 2784853.1 | U13: =SUM(U7:U12) -> 2496775 | W13: =SUM(W7:W12) -> 4897782.5 | Y13: =SUM(Y7:Y12) -> 5185887.3
Q22: =M13+O13+Q13 -> 2208778.9

Sheet ENGICON RIYADH 4 P2 
B1: Total quantity | C1: Remaining quantity
A2: A1 | B2: 30000
A3: B1 | B3: 45000
A4: C1 | B4: 40000
A5: D1 | B5: 440000
A6: E1 | B6: 16000
A7: F1 | B7: 14000
G11: 70 RBF's in Riyadh 04 | L11: Invoice1 | N11: Invoice2 | P11: Invoice3 | R11: Invoice5
G12: Description | H12: Category | I12: Total Quantity | J12: Remaining quantity | K12: Rate | L12: Quantity | M12: Amount | N12: Quantity | O12: Amount | P12: Quantity | Q12: Amount | R12: Quantity | S12: Amount
G13: Lead Engineer/ Discipline Engineer | H13: A1 | I13: 2000 | K13: 463 | L13: 600 | M13: =L13*K13 -> 277800 | N13: 500 | O13: =N13*K13 -> 231500 | P13: 500 | Q13: =P13*K13 -> 231500 | R13: 400 | S13: =K13*R13 -> 185200
G14: Sr. Engineer/ Senior discipline specialist | H14: B1 | I14: 2000 | K14: 349 | L14: 600 | M14: =L14*K14 -> 209400 | N14: 500 | O14: =N14*K14 -> 174500 | P14: 500 | Q14: =P14*K14 -> 174500 | R14: 400 | S14: =K14*R14 -> 139600
G15: Engineer/ Discipline Specialist | H15: C1 | I15: 2000 | K15: 302 | L15: 600 | M15: =L15*K15 -> 181200 | N15: 500 | O15: =N15*K15 -> 151000 | P15: 500 | Q15: =P15*K15 -> 151000 | R15: 400 | S15: =K15*R15 -> 120800
G16: Draftsman | H16: D1 | I16: 1553 | K16: 169 | L16: 466 | M16: =L16*K16 -> 78754 | N16: 388 | O16: =N16*K16 -> 65572 | P16: 388 | Q16: =P16*K16 -> 65572 | R16: 311 | S16: =K16*R16 -> 52559
G17: Project Manager | H17: E1 | I17: 0 | M17: =L17*K17 -> 0
G18: Project Manager | H18: F1 | I18: 0
G19: TOTAL | M19: =SUM(M13:M16) -> 747154 | O19: =SUM(O13:O16) -> 622572 | Q19: =SUM(Q13:Q18) -> 622572 | S19: =SUM(S13:S18) -> 498159
G23: Development for the Masterplan and Concept Infrastructure for the expansion of Riyadh 4 industrial city | L23: Invoice1 | N23: Invoice3 | P23: Invoice4 | R23: Invoice6
G24: Description | H24: Category | I24: Total Quantity | J24: Remaining quantity | K24: Rate | L24: Quantity | M24: Amount | N24: Quantity | O24: Amount | P24: Quantity | Q24: Amount | R24: Quantity | S24: Amount
G25: Lead Engineer/ Discipline Engineer | H25: A1 | I25: 8000 | K25: 463 | L25: 2600 | M25: =L25*K25 -> 1203800 | N25: 1000 | O25: =N25*K25 -> 463000 | P25: 800 | Q25: =P25*K25 -> 370400 | R25: 1800 | S25: =R25*K25 -> 833400
G26: Sr. Engineer/ Senior discipline specialist | H26: B1 | I26: 20000 | K26: 349 | L26: 6500 | M26: =L26*K26 -> 2268500 | N26: 2500 | O26: =N26*K26 -> 872500 | P26: 2000 | Q26: =P26*K26 -> 698000 | R26: 4500 | S26: =R26*K26 -> 1570500
G27: Engineer/ Discipline Specialist | H27: C1 | I27: 17557 | K27: 302 | L27: 5707 | M27: =L27*K27 -> 1723514 | N27: 2195 | O27: =N27*K27 -> 662890 | P27: 1756 | Q27: =P27*K27 -> 530312 | R27: 3949.5 | S27: =R27*K27 -> 1192749
G28: Draftsman | H28: D1 | I28: 20000 | K28: 169 | L28: 6500 | M28: =L28*K28 -> 1098500 | N28: 2500 | O28: =N28*K28 -> 422500 | P28: 2000 | Q28: =P28*K28 -> 338000 | R28: 4500 | S28: =R28*K28 -> 760500
G29: Project Manager | H29: E1 | I29: 8000 | K29: 463 | L29: 2600 | M29: =L29*K29 -> 1203800 | N29: 1000 | O29: =N29*K29 -> 463000 | P29: 800 | Q29: =P29*K29 -> 370400 | R29: 1800 | S29: =R29*K29 -> 833400
G30: Project Manager | H30: F1 | I30: 7997 | K30: 179 | L30: 2599 | M30: =L30*K30 -> 465221 | N30: 999.5 | O30: =N30*K30 -> 178910.5 | P30: 799.5 | Q30: =P30*K30 -> 143110.5 | R30: 1799.5 | S30: =R30*K30 -> 322110.5
G31: TOTAL | M31: =SUM(M25:M30) -> 7963335 | O31: =SUM(O25:O30) -> 3062800.5 | Q31: =SUM(Q25:Q30) -> 2450222.5 | S31: =SUM(S25:S30) -> 5512659.5
G36: Design Bridge 3rd HIGHWAY RiyaDH 4 | L36: Invoice5
G37: Description | H37: Category | I37: Total Quantity | J37: Remaining quantity | K37: Rate | L37: Quantity | M37: Amount
G38: Lead Engineer/ Discipline Engineer | H38: A1 | I38: 923 | K38: 463 | L38: 126.5 | M38: =L38*K38 -> 58569.5
G39: Sr. Engineer/ Senior discipline specialist | H39: B1 | I39: 832 | K39: 349 | L39: 135.5 | M39: =L39*K39 -> 47289.5
G40: Engineer/ Discipline Specialist | H40: C1 | I40: 530 | K40: 302 | L40: 75 | M40: =L40*K40 -> 22650
G41: Draftsman | H41: D1 | I41: 375 | K41: 169 | L41: 50 | M41: =L41*K41 -> 8450
G42: Project Manager | H42: E1 | I42: 290 | K42: 463 | L42: 50 | M42: =L42*K42 -> 23150
G43: Project Manager | H43: F1 | I43: 273 | K43: 179 | L43: 48 | M43: =L43*K43 -> 8592
M44: =SUM(M38:M43) -> 168701

Sheet Engicon - P1
G7: Sudair lake | L7: Invoice 1 | N7: Invoice 2 | P7: Invoice 3 | R7: Invoice 4
A8: Description | C8: Total quantity | D8: Remaining quantity | G8: Description | H8: Category | I8: Total Quantity | J8: Remaining quantity | K8: Rate | L8: Quantity | M8: Amount | N8: Quantity2 | O8: Amount3 | P8: Quantity3 | Q8: Amount4 | R8: Quantity25 | S8: Amount36
A9: Lead Engineer/ Discipline Engineer | B9: A1 | G9: Lead Engineer/ Discipline Engineer | H9: A1 | I9: 810 | J9: =Table525[[#This Row],[Total Quantity]]-Table525[[#This Row],[Quantity]]-Table525[[#This Row],[Quantity2]] -> 0 | K9: 405 | L9: 364.5 | M9: =Table525[[#This Row],[Rate]]*Table525[[#This Row],[Quantity]] -> 147622.5 | N9: 445.5 | O9: =Table525[[#This Row],[Quantity2]]*Table525[[#This Row],[Rate]] -> 180427.5
A10: Sr. Engineer/ Senior discipline specialist | B10: B1 | G10: Sr. Engineer/ Senior discipline specialist | H10: B1 | I10: 1905 | J10: =Table525[[#This Row],[Total Quantity]]-Table525[[#This Row],[Quantity]]-Table525[[#This Row],[Quantity2]] -> 0 | K10: 302 | L10: 857.25 | M10: =Table525[[#This Row],[Rate]]*Table525[[#This Row],[Quantity]] -> 258889.5 | N10: 1047.75 | O10: =Table525[[#This Row],[Quantity2]]*Table525[[#This Row],[Rate]] -> 316420.5
A11: Engineer/ Discipline Specialist | B11: C1 | G11: Engineer/ Discipline Specialist | H11: C1 | I11: 2233 | J11: =Table525[[#This Row],[Total Quantity]]-Table525[[#This Row],[Quantity]]-Table525[[#This Row],[Quantity2]] -> 0 | K11: 259 | L11: 1004.85 | M11: =Table525[[#This Row],[Rate]]*Table525[[#This Row],[Quantity]] -> 260256.15 | N11: 1228.15 | O11: =Table525[[#This Row],[Quantity2]]*Table525[[#This Row],[Rate]] -> 318090.85
A12: Draftsman | B12: D1 | G12: Draftsman | H12: D1 | I12: 1212 | J12: =Table525[[#This Row],[Total Quantity]]-Table525[[#This Row],[Quantity]]-Table525[[#This Row],[Quantity2]] -> 0 | K12: 146 | L12: 545.4 | M12: =Table525[[#This Row],[Rate]]*Table525[[#This Row],[Quantity]] -> 79628.4 | N12: 666.6 | O12: =Table525[[#This Row],[Quantity2]]*Table525[[#This Row],[Rate]] -> 97323.6
A13: Project Manager | B13: E1 | D13: =C13-Table525[[#This Row],[Total Quantity]]-I23-I38-I56-#REF!-I85-I108-I130-I149-I167 -> #REF! | G13: Project Manager | H13: E1 | I13: 0 | J13: =Table525[[#This Row],[Total Quantity]]-Table525[[#This Row],[Quantity]]-Table525[[#This Row],[Quantity2]] -> 0 | K13: 405 | M13: =Table525[[#This Row],[Rate]]*Table525[[#This Row],[Quantity]] -> 0
A14: Project Manager | B14: F1 | D14: =C14-Table525[[#This Row],[Total Quantity]]-I24-I39-I57-I67-I86-I109-I131-I150-I168 -> #VALUE! | G14: Project Manager | H14: F1 | I14: 0 | J14: =Table525[[#This Row],[Total Quantity]]-Table525[[#This Row],[Quantity]]-Table525[[#This Row],[Quantity2]] -> 0 | K14: 162 | M14: =Table525[[#This Row],[Rate]]*Table525[[#This Row],[Quantity]] -> 0
G15: TOTAL | J15: =Table525[[#This Row],[Total Quantity]]-Table525[[#This Row],[Quantity]]-Table525[[#This Row],[Quantity2]] -> 0 | M15: =SUM(M9:M14) -> 746396.55 | O15: =SUM(O9:O14) -> 912262.45
G23: NIS RBF | L23: Invoice 1 | N23: Invoice 2 | P23: Invoice 3 | R23: Invoice 6 | T23: Invoice 8
G24: Description | H24: Category | I24: Total Quantity | J24: Remaining quantity | K24: Rate | L24: Quantity | M24: Amount | N24: Quantity2 | O24: Amount3 | P24: Quantity3 | Q24: Amount4 | R24: Quantity25 | S24: Amount36 | T24: Quantity26 | U24: Amount38
G25: Lead Engineer/ Discipline Engineer | H25: A1 | I25: 5359 | J25: =Table52526[[#This Row],[Total Quantity]]-Table52526[[#This Row],[Quantity]]-Table52526[[#This Row],[Quantity2]]-Table52526[[#This Row],[Quantity25]]-Table52526[[#This Row],[Quantity26]] -> 0.00069135802 | K25: 405 | L25: 2067.0429 | M25: =Table52526[[#This Row],[Rate]]*Table52526[[#This Row],[Quantity]] -> 837152.36 | N25: 1224.9143 | O25: =Table52526[[#This Row],[Quantity2]]*Table52526[[#This Row],[Rate]] -> 496090.29 | R25: 1550.2821 | S25: =Table52526[[#This Row],[Quantity25]]*Table52526[[#This Row],[Rate]] -> 627864.27 | T25: 516.76 | U25: =Table52526[[#This Row],[Quantity26]]*Table52526[[#This Row],[Rate]] -> 209287.8
G26: Sr. Engineer/ Senior discipline specialist | H26: B1 | I26: 8558 | J26: =Table52526[[#This Row],[Total Quantity]]-Table52526[[#This Row],[Quantity]]-Table52526[[#This Row],[Quantity2]]-Table52526[[#This Row],[Quantity25]]-Table52526[[#This Row],[Quantity26]] -> -0.0042715232 | K26: 302 | L26: 3300.9428 | M26: =Table52526[[#This Row],[Rate]]*Table52526[[#This Row],[Quantity]] -> 996884.74 | N26: 1956.1143 | O26: =Table52526[[#This Row],[Quantity2]]*Table52526[[#This Row],[Rate]] -> 590746.51 | R26: 2475.7072 | S26: =Table52526[[#This Row],[Quantity25]]*Table52526[[#This Row],[Rate]] -> 747663.56 | T26: 825.24 | U26: =Table52526[[#This Row],[Quantity26]]*Table52526[[#This Row],[Rate]] -> 249222.48
G27: Engineer/ Discipline Specialist | H27: C1 | I27: 8695 | J27: =Table52526[[#This Row],[Total Quantity]]-Table52526[[#This Row],[Quantity]]-Table52526[[#This Row],[Quantity2]]-Table52526[[#This Row],[Quantity25]]-Table52526[[#This Row],[Quantity26]] -> -0.0035907336 | K27: 259 | L27: 3353.7857 | M27: =Table52526[[#This Row],[Rate]]*Table52526[[#This Row],[Quantity]] -> 868630.5 | N27: 1987.4286 | O27: =Table52526[[#This Row],[Quantity2]]*Table52526[[#This Row],[Rate]] -> 514744 | R27: 2515.3393 | S27: =Table52526[[#This Row],[Quantity25]]*Table52526[[#This Row],[Rate]] -> 651472.88 | T27: 838.45 | U27: =Table52526[[#This Row],[Quantity26]]*Table52526[[#This Row],[Rate]] -> 217158.55
G28: Draftsman | H28: D1 | I28: 6391 | J28: =Table52526[[#This Row],[Total Quantity]]-Table52526[[#This Row],[Quantity]]-Table52526[[#This Row],[Quantity2]]-Table52526[[#This Row],[Quantity25]]-Table52526[[#This Row],[Quantity26]] -> -0.005 | K28: 146 | L28: 2465.1 | M28: =Table52526[[#This Row],[Rate]]*Table52526[[#This Row],[Quantity]] -> 359904.6 | N28: 1460.8 | O28: =Table52526[[#This Row],[Quantity2]]*Table52526[[#This Row],[Rate]] -> 213276.8 | R28: 1848.825 | S28: =Table52526[[#This Row],[Quantity25]]*Table52526[[#This Row],[Rate]] -> 269928.45 | T28: 616.28 | U28: =Table52526[[#This Row],[Quantity26]]*Table52526[[#This Row],[Rate]] -> 89976.88
G29: Project Manager | H29: E1 | I29: 0 | J29: =Table52526[[#This Row],[Total Quantity]]-Table52526[[#This Row],[Quantity]]-Table52526[[#This Row],[Quantity2]]-Table52526[[#This Row],[Quantity25]]-Table52526[[#This Row],[Quantity26]] -> 0 | K29: 405 | M29: =Table52526[[#This Row],[Rate]]*Table52526[[#This Row],[Quantity]] -> 0 | O29: =Table52526[[#This Row],[Quantity2]]*Table52526[[#This Row],[Rate]] -> 0 | S29: =Table52526[[#This Row],[Amount4]]*Table52526[[#This Row],[Rate]] -> 0 | U29: =Table52526[[#This Row],[Quantity26]]*Table52526[[#This Row],[Rate]] -> 0
G30: Project Manager | H30: F1 | I30: 0 | J30: =Table52526[[#This Row],[Total Quantity]]-Table52526[[#This Row],[Quantity]]-Table52526[[#This Row],[Quantity2]]-Table52526[[#This Row],[Quantity25]]-Table52526[[#This Row],[Quantity26]] -> 0 | K30: 162 | M30: =Table52526[[#This Row],[Rate]]*Table52526[[#This Row],[Quantity]] -> 0 | O30: =Table52526[[#This Row],[Quantity2]]*Table52526[[#This Row],[Rate]] -> 0 | S30: =Table52526[[#This Row],[Amount4]]*Table52526[[#This Row],[Rate]] -> 0 | U30: =Table52526[[#This Row],[Quantity26]]*Table52526[[#This Row],[Rate]] -> 0
G31: TOTAL | J31: =Table52526[[#This Row],[Total Quantity]]-Table52526[[#This Row],[Quantity]]-Table52526[[#This Row],[Quantity2]]-Table52526[[#This Row],[Quantity25]]-Table52526[[#This Row],[Quantity26]] -> 0 | M31: =SUM(M25:M30) -> 3062572.2 | O31: =SUM(O25:O30) -> 1814857.6 | S31: =SUM(S25:S28) -> 2296929.2 | U31: 765643.05
M32: =M31+O31 -> 4877429.8
G34: Technology zones - Asfan | L34: Invoice 1 | N34: Invoice 2 | P34: Invoice 3 | R34: Invoice 4 | V34: Invoice 5 | X34: Invoice 7
G35: Description | H35: Category | I35: Total Quantity | J35: Remaining quantity | K35: Rate | L35: Quantity | M35: Amount | N35: Quantity2 | O35: Amount3 | P35: Quantity3 | Q35: Amount4 | R35: Quantity25 | S35: Amount36 | T35: Amount37 | U35: Amount38 | V35: Amount39 | W35: Amount40 | X35: Amount41 | Y35: Amount42
G36: Lead Engineer/ Discipline Engineer | H36: A1 | I36: 1008 | K36: 405 | O36: =Table5252624[[#This Row],[Quantity2]]*Table5252624[[#This Row],[Rate]] -> 0 | P36: 110 | Q36: =Table5252624[[#This Row],[Quantity3]]*Table5252624[[#This Row],[Rate]] -> 44550 | R36: 388 | S36: =Table5252624[[#This Row],[Quantity25]]*Table5252624[[#This Row],[Rate]] -> 157140 | T36: 200 | U36: =Table5252624[[#This Row],[Amount37]]*Table5252624[[#This Row],[Rate]] -> 81000 | V36: 200 | W36: =Table5252624[[#This Row],[Amount39]]*Table5252624[[#This Row],[Rate]] -> 81000 | X36: 310 | Y36: =Table5252624[[#This Row],[Amount41]]*Table5252624[[#This Row],[Rate]] -> 125550
G37: Sr. Engineer/ Senior discipline specialist | H37: B1 | I37: 1008 | K37: 302 | O37: =Table5252624[[#This Row],[Quantity2]]*Table5252624[[#This Row],[Rate]] -> 0 | P37: 110 | Q37: =Table5252624[[#This Row],[Quantity3]]*Table5252624[[#This Row],[Rate]] -> 33220 | R37: 388 | S37: =Table5252624[[#This Row],[Quantity25]]*Table5252624[[#This Row],[Rate]] -> 117176 | T37: 200 | U37: =Table5252624[[#This Row],[Amount37]]*Table5252624[[#This Row],[Rate]] -> 60400 | V37: 200 | W37: =Table5252624[[#This Row],[Amount39]]*Table5252624[[#This Row],[Rate]] -> 60400 | X37: 310 | Y37: =Table5252624[[#This Row],[Amount41]]*Table5252624[[#This Row],[Rate]] -> 93620
G38: Engineer/ Discipline Specialist | H38: C1 | I38: 617 | K38: 259 | O38: =Table5252624[[#This Row],[Quantity2]]*Table5252624[[#This Row],[Rate]] -> 0 | P38: 50 | Q38: =Table5252624[[#This Row],[Quantity3]]*Table5252624[[#This Row],[Rate]] -> 12950 | R38: 169 | S38: =Table5252624[[#This Row],[Quantity25]]*Table5252624[[#This Row],[Rate]] -> 43771 | T38: 174 | U38: =Table5252624[[#This Row],[Amount37]]*Table5252624[[#This Row],[Rate]] -> 45066 | V38: 174 | W38: =Table5252624[[#This Row],[Amount39]]*Table5252624[[#This Row],[Rate]] -> 45066 | X38: 224 | Y38: =Table5252624[[#This Row],[Amount41]]*Table5252624[[#This Row],[Rate]] -> 58016
G39: Draftsman | H39: D1 | I39: 520 | K39: 146 | P39: 40 | Q39: =Table5252624[[#This Row],[Quantity3]]*Table5252624[[#This Row],[Rate]] -> 5840 | R39: 140 | S39: =Table5252624[[#This Row],[Quantity25]]*Table5252624[[#This Row],[Rate]] -> 20440 | T39: 150 | U39: =Table5252624[[#This Row],[Amount37]]*Table5252624[[#This Row],[Rate]] -> 21900 | V39: 150 | W39: =Table5252624[[#This Row],[Amount39]]*Table5252624[[#This Row],[Rate]] -> 21900 | X39: 190 | Y39: =Table5252624[[#This Row],[Amount41]]*Table5252624[[#This Row],[Rate]] -> 27740
G40: Project Manager | H40: E1 | I40: 440 | K40: 405 | P40: 40 | Q40: =Table5252624[[#This Row],[Quantity3]]*Table5252624[[#This Row],[Rate]] -> 16200 | R40: 140 | S40: =Table5252624[[#This Row],[Quantity25]]*Table5252624[[#This Row],[Rate]] -> 56700 | T40: 110 | U40: =Table5252624[[#This Row],[Amount37]]*Table5252624[[#This Row],[Rate]] -> 44550 | V40: 110 | W40: =Table5252624[[#This Row],[Amount39]]*Table5252624[[#This Row],[Rate]] -> 44550 | X40: 150 | Y40: =Table5252624[[#This Row],[Amount41]]*Table5252624[[#This Row],[Rate]] -> 60750
G41: Project Manager | H41: F1 | I41: 410 | K41: 162 | P41: 40 | Q41: =Table5252624[[#This Row],[Quantity3]]*Table5252624[[#This Row],[Rate]] -> 6480 | R41: 140 | S41: =Table5252624[[#This Row],[Quantity25]]*Table5252624[[#This Row],[Rate]] -> 22680 | T41: 95 | U41: =Table5252624[[#This Row],[Amount37]]*Table5252624[[#This Row],[Rate]] -> 15390 | V41: 95 | W41: =Table5252624[[#This Row],[Amount39]]*Table5252624[[#This Row],[Rate]] -> 15390 | X41: 135 | Y41: =Table5252624[[#This Row],[Amount41]]*Table5252624[[#This Row],[Rate]] -> 21870
G42: TOTAL | Q42: =SUM(Q36:Q41) -> 119240 | S42: =SUM(S36:S41) -> 417907 | U42: =SUM(U36:U41) -> 268306 | W42: =SUM(W36:W41) -> 268306 | Y42: =SUM(Y36:Y41) -> 387546
G47: Technology zones - Khumra | L47: Invoice 1 | N47: Invoice 2 | P47: Invoice 3 | R47: Invoice 4 | V47: Invoice5 | X47: Invoice7
G48: Description | H48: Category | I48: Total Quantity | J48: Remaining quantity | K48: Rate | L48: Quantity | M48: Amount | N48: Quantity2 | O48: Amount3 | P48: Quantity3 | Q48: Amount4 | R48: Quantity25 | S48: Amount36 | T48: Amount37 | U48: Amount38 | V48: Amount39 | W48: Amount40 | X48: Amount41 | Y48: Amount42
G49: Lead Engineer/ Discipline Engineer | H49: A1 | I49: 1023 | K49: 405 | O49: =Table525262427[[#This Row],[Quantity2]]*Table525262427[[#This Row],[Rate]] -> 0 | P49: 121 | Q49: =Table525262427[[#This Row],[Quantity3]]*Table525262427[[#This Row],[Rate]] -> 49005 | R49: 341 | S49: =Table525262427[[#This Row],[Quantity25]]*Table525262427[[#This Row],[Rate]] -> 138105 | T49: 220 | U49: =Table525262427[[#This Row],[Amount37]]*Table525262427[[#This Row],[Rate]] -> 89100 | V49: 220 | W49: =Table525262427[[#This Row],[Amount39]]*Table525262427[[#This Row],[Rate]] -> 89100 | X49: 341 | Y49: =Table525262427[[#This Row],[Amount41]]*Table525262427[[#This Row],[Rate]] -> 138105
G50: Sr. Engineer/ Senior discipline specialist | H50: B1 | I50: 1023 | K50: 302 | O50: =Table525262427[[#This Row],[Quantity2]]*Table525262427[[#This Row],[Rate]] -> 0 | P50: 121 | Q50: =Table525262427[[#This Row],[Quantity3]]*Table525262427[[#This Row],[Rate]] -> 36542 | R50: 341 | S50: =Table525262427[[#This Row],[Quantity25]]*Table525262427[[#This Row],[Rate]] -> 102982 | T50: 220 | U50: =Table525262427[[#This Row],[Amount37]]*Table525262427[[#This Row],[Rate]] -> 66440 | V50: 220 | W50: =Table525262427[[#This Row],[Amount39]]*Table525262427[[#This Row],[Rate]] -> 66440 | X50: 341 | Y50: =Table525262427[[#This Row],[Amount41]]*Table525262427[[#This Row],[Rate]] -> 102982
G51: Engineer/ Discipline Specialist | H51: C1 | I51: 765 | K51: 259 | O51: =Table525262427[[#This Row],[Quantity2]]*Table525262427[[#This Row],[Rate]] -> 0 | P51: 57 | Q51: =Table525262427[[#This Row],[Quantity3]]*Table525262427[[#This Row],[Rate]] -> 14763 | R51: 265 | S51: =Table525262427[[#This Row],[Quantity25]]*Table525262427[[#This Row],[Rate]] -> 68635 | T51: 193 | U51: =Table525262427[[#This Row],[Amount37]]*Table525262427[[#This Row],[Rate]] -> 49987 | V51: 193 | W51: =Table525262427[[#This Row],[Amount39]]*Table525262427[[#This Row],[Rate]] -> 49987 | X51: 250 | Y51: =Table525262427[[#This Row],[Amount41]]*Table525262427[[#This Row],[Rate]] -> 64750
G52: Draftsman | H52: D1 | I52: 677 | K52: 146 | P52: 44 | Q52: =Table525262427[[#This Row],[Quantity3]]*Table525262427[[#This Row],[Rate]] -> 6424 | R52: 259 | S52: =Table525262427[[#This Row],[Quantity25]]*Table525262427[[#This Row],[Rate]] -> 37814 | T52: 165 | U52: =Table525262427[[#This Row],[Amount37]]*Table525262427[[#This Row],[Rate]] -> 24090 | V52: 165 | W52: =Table525262427[[#This Row],[Amount39]]*Table525262427[[#This Row],[Rate]] -> 24090 | X52: 209 | Y52: =Table525262427[[#This Row],[Amount41]]*Table525262427[[#This Row],[Rate]] -> 30514
G53: Project Manager | H53: E1 | I53: 569 | K53: 405 | P53: 44 | Q53: =Table525262427[[#This Row],[Quantity3]]*Table525262427[[#This Row],[Rate]] -> 17820 | R53: 239 | S53: =Table525262427[[#This Row],[Quantity25]]*Table525262427[[#This Row],[Rate]] -> 96795 | T53: 121 | U53: =Table525262427[[#This Row],[Amount37]]*Table525262427[[#This Row],[Rate]] -> 49005 | V53: 121 | W53: =Table525262427[[#This Row],[Amount39]]*Table525262427[[#This Row],[Rate]] -> 49005 | X53: 165 | Y53: =Table525262427[[#This Row],[Amount41]]*Table525262427[[#This Row],[Rate]] -> 66825
G54: Project Manager | H54: F1 | I54: 418 | K54: 162 | P54: 45 | Q54: =Table525262427[[#This Row],[Quantity3]]*Table525262427[[#This Row],[Rate]] -> 7290 | R54: 106 | S54: =Table525262427[[#This Row],[Quantity25]]*Table525262427[[#This Row],[Rate]] -> 17172 | T54: 111 | U54: =Table525262427[[#This Row],[Amount37]]*Table525262427[[#This Row],[Rate]] -> 17982 | V54: 111 | W54: =Table525262427[[#This Row],[Amount39]]*Table525262427[[#This Row],[Rate]] -> 17982 | X54: 156 | Y54: =Table525262427[[#This Row],[Amount41]]*Table525262427[[#This Row],[Rate]] -> 25272
G55: TOTAL | Q55: =SUM(Q49:Q54) -> 131844 | S55: =SUM(S49:S54) -> 461503 | U55: =SUM(U49:U54) -> 296604 | W55: =SUM(W49:W54) -> 296604 | Y55: =SUM(Y49:Y54) -> 428448
G58: Industrial incubators 3rd ind. City | L58: Invoice 7 | N58: Invoice 8 | P58: Invoice 10
G59: Description | H59: Category | I59: Total Quantity | J59: Remaining quantity | K59: Rate | L59: Quantity | M59: Amount | N59: Quantity | O59: Amount | P59: Quantity | Q59: Amount
G60: Lead Engineer/ Discipline Engineer | H60: A1 | I60: 1000 | J60: =I60-L60-N60 -> 800 | K60: 405 | L60: 100 | M60: =L60*K60 -> 40500 | N60: 100 | O60: =N60*K60 -> 40500 | P60: 550 | Q60: =P60*K60 -> 222750
G61: Sr. Engineer/ Senior discipline specialist | H61: B1 | I61: 1000 | J61: =I61-L61-N61 -> 800 | K61: 302 | L61: 100 | M61: =L61*K61 -> 30200 | N61: 100 | O61: =N61*K61 -> 30200 | P61: 550 | Q61: =P61*K61 -> 166100
G62: Engineer/ Discipline Specialist | H62: C1 | I62: 800 | J62: =I62-L62-N62 -> 640 | K62: 259 | L62: 80 | M62: =L62*K62 -> 20720 | N62: 80 | O62: =N62*K62 -> 20720 | P62: 440 | Q62: =P62*K62 -> 113960
G63: Draftsman | H63: D1 | I63: 472 | J63: =I63-L63-N63 -> 377 | K63: 146 | L63: 48 | M63: =L63*K63 -> 7008 | N63: 47 | O63: =N63*K63 -> 6862 | P63: 258 | Q63: =P63*K63 -> 37668
G64: Project Manager | H64: E1 | I64: 438 | J64: =I64-L64-N64 -> 350 | K64: 405 | L64: 44 | M64: =L64*K64 -> 17820 | N64: 44 | O64: =N64*K64 -> 17820 | P64: 241 | Q64: =P64*K64 -> 97605
G65: Project Manager | H65: F1 | I65: 429 | J65: =I65-L65-N65 -> 344.5 | K65: 162 | L65: 42 | M65: =L65*K65 -> 6804 | N65: 42.5 | O65: =N65*K65 -> 6885 | P65: 237 | Q65: =P65*K65 -> 38394
G66: TOTAL | M66: =SUM(M60:M65) -> 123052 | O66: =SUM(O60:O65) -> 122987 | Q66: =SUM(Q60:Q65) -> 676477

Sheet Invoices
C1: Invoices Process Report - Design Projects
C4: Consultant | D4: Column1 | E4: Frame Work Contract | F4: Value | G4: Duration | H4: Start Date | I4: Finsih Date2 | J4: Committed | K4: remaining from framework | L4: Invoices w/out VAT | M4: Earned value
A5: NA | C5: Dorsch | E5: 2178 | F5: 29966000 | G5: 48M | I5: 45244 | J5: =SUM(#REF!) -> #REF! | K5: =F5-J5 -> #REF! | L5: =#REF! -> #REF! | M5: =#REF! -> #REF!
A6: W/OUT VAT | B6: =100*(Wrapup[[#This Row],[Invoices w/out VAT]]/Wrapup[[#This Row],[Value]]) -> 94.486564 | C6: Dorsch food | E6: 2547 | F6: =22992640/1.15 -> 19993600 | G6: 24M | H6: 45085 | I6: 45816 | J6: =SUM(H30:H41) -> 19558881 | K6: =F6-J6 -> 434719 | L6: =DI42 -> 18891266 | M6: =DL42 -> 19558881
A7: W/OUT VAT | B7: =100*(Wrapup[[#This Row],[Invoices w/out VAT]]/Wrapup[[#This Row],[Value]]) -> #REF! | C7: EGEC old | E7: 2454 | F7: 3400000 | G7: 9M | I7: 45151 | J7: =F7 -> 3400000 | K7: =F7-J7 -> 0 | L7: =#REF! -> #REF! | M7: =#REF! -> #REF!
A8: W/OUT VAT | B8: =100*(Wrapup[[#This Row],[Invoices w/out VAT]]/Wrapup[[#This Row],[Value]]) -> 82.460925 | C8: SYSTRA | E8: 2672 | F8: 15054089 | G8: 24M | H8: =EDATE(Wrapup[[#This Row],[Finsih Date2]], - 24) -> 45342 | I8: 46073 | J8: =SUM(H44:H48) -> 15054089 | K8: =F8-J8 -> 0 | L8: =SUM(DI44:DI48) -> 12413741 | M8: =DL49 -> 15054089
A9: W/OUT VAT | B9: =100*(Wrapup[[#This Row],[Invoices w/out VAT]]/Wrapup[[#This Row],[Value]]) -> 72.479596 | C9: EGEC - NIS2 | E9: 2709 | F9: 19979840 | G9: 48M | H9: 45421 | I9: 46882 | J9: =SUM(H51:H66) -> 18492779 | K9: =F9-J9 -> 1487061 | L9: =DI68 -> 14481307 | M9: =DL68 -> 15572069
A10: W/OUT VAT | B10: =100*(Wrapup[[#This Row],[Invoices w/out VAT]]/Wrapup[[#This Row],[Value]]) -> 90 | C10: ENGICON | E10: 2666 | F10: 27837620 | G10: 10M | H10: =EDATE(Wrapup[[#This Row],[Finsih Date2]], - 10) -> 45444 | I10: 45748 | J10: =H70 -> 27837620 | K10: =F10-J10 -> 0 | L10: =DI72 -> 25053858 | M10: =DL72 -> 27837620
A11: W/OUT VAT | B11: =100*(Wrapup[[#This Row],[Invoices w/out VAT]]/Wrapup[[#This Row],[Value]]) -> 66.399191 | C11: EGEC - WAS | E11: TBA | F11: 9799000 | G11: 24M | H11: 45608 | I11: 46338 | J11: =SUM(H74:H78) -> 7075670 | K11: =F11-J11 -> 2723330 | L11: =DI78 -> 6506456.8 | M11: =DL78 -> 6221850
B12: =100*(Wrapup[[#This Row],[Invoices w/out VAT]]/Wrapup[[#This Row],[Value]]) -> 62.228536 | C12: ENGICON - Package1 | E12: 2891 | F12: 19856000 | G12: 60M | H12: 45700 | I12: 47526 | J12: =SUM(H99:H104) -> 13340059 | K12: =F12-J12 -> 6515941 | L12: =DI105 -> 12356098 | M12: =DL105 -> 12479059 | BQ12: a | BR12: b | BS12: c
A13: W/OUT VAT | B13: =100*(Wrapup[[#This Row],[Invoices w/out VAT]]/Wrapup[[#This Row],[Value]]) -> 99.999998 | C13: ENGICON - RDH4 | E13: TBA | F13: 7025000 | G13: 24M | H13: =EDATE(Wrapup[[#This Row],[Finsih Date2]], - 24) -> 45617 | I13: 46347 | J13: =H80 -> 7025000 | K13: =F13-J13 -> 0 | L13: =DI81 -> 7024999.8 | M13: =DL81 -> 7025000 | BP13: a | BQ13: 15 | BR13: 13 | BS13: 15
A14: W/OUT VAT | B14: =100*(Wrapup[[#This Row],[Invoices w/out VAT]]/Wrapup[[#This Row],[Value]]) -> 24.764554 | C14: Dar AlRiyadh 2 | E14: 2814 | F14: 59999686 | G14: 60M | H14: 45567 | I14: 47393 | J14: =Wrapup[[#This Row],[Value]] -> 59999686 | K14: =F14-J14 -> 0 | L14: =J97 -> 14858655 | M14: =Wrapup[[#This Row],[Invoices w/out VAT]] -> 14858655
A15: W/OUT VAT | C15: Meinhardt (KHJ - FOOD) | E15: 2966 | F15: 14990000 | G15: 24M | H15: 45832 | I15: 46562 | J15: =SUM(H107:H110) -> 2997130 | K15: =F15-J15 -> 11992870 | L15: =DI111 -> 1198852.1 | M15: =DM111 -> -0.07
A16: W/OUT VAT | C16: ENGICON - RDH4 PH2 | E16: 3026 | F16: 59500000 | G16: 36M | H16: 45858 | I16: 46954 | J16: =SUM(H113:H116) -> 26992134 | K16: =F16-J16 -> 32507866 | L16: =DI117 -> 9333061 | M16: =DM117 -> 1347327.6 | BQ16: =MOD(SUM(BQ13:BS13),2) -> 1
A17: W/OUT VAT | C17: AlDar International (KHJ - FOOD2) | E17: 3041 | F17: 11637180 | G17: 24M | H17: =EDATE(Wrapup[[#This Row],[Finsih Date2]], - 24) -> 45879 | I17: 46609 | J17: =SUM(H119:H122) -> 7146100 | K17: =F17-J17 -> 4491080 | L17: =DI123 -> 1385226.5 | M17: =DM123 -> 845071.31
A18: W/OUT VAT | C18: ENGICON - Logistics | E18: 3042 | F18: 27800000 | G18: 24M | H18: =EDATE(Wrapup[[#This Row],[Finsih Date2]], - 24) -> 45868 | I18: 46598 | J18: =SUM(H125:H128) -> 19206662 | K18: =F18-J18 -> 8593338 | L18: =DI129 -> 4993632 | M18: =DM129 -> 614713.35
A19: W/OUT VAT | C19: EGEC - NIS3 | E19: 3020 | F19: 19955000 | G19: 48M | H19: =EDATE(Wrapup[[#This Row],[Finsih Date2]], - 48) -> 45848 | I19: 47309 | K19: =F19-J19 -> 19955000 | L19: =DI143 -> 0 | M19: =DM143 -> 0
A21: CASH FLOW OVERVIEW OF RUNNING PROJECTS
A23: INVOICES STATUS
A26: Consultant | B26: NO. | C26: Projects | D26: Column1 | E26: Column2 | F26: Column3 | G26: Column4 | H26: Column8 | I26: Column9 | J26: Column10 | K26: Column11 | L26: Column12 | M26: Column13 | N26: Column14 | O26: Column15 | P26: Column16 | Q26: Column17 | R26: Column18 | S26: Column19 | T26: Column20 | U26: Column21 | V26: Column22 | W26: Column23 | X26: Column24 | Y26: Column25 | Z26: Column26 | AA26: Column27 | AB26: Column28 | AC26: Column29 | AD26: Column30 | AE26: Column31 | AF26: Column32 | AG26: Column33 | AH26: Column34 | AI26: Column35 | AJ26: Column36 | AK26: Column37 | AL26: Column38 | AM26: Column39 | AN26: Column40 | AO26: Column41 | AP26: Column42 | AQ26: Column43 | AR26: Column44 | AS26: Column45 | AT26: Column46 | AU26: Column47 | AV26: Column48 | AW26: Column49 | AX26: Column50 | AY26: Column51 | AZ26: Column52 | BA26: Column53 | BB26: Column54 | BC26: Column55 | BD26: Column56 | BE26: Column57 | BF26: Column58 | BG26: Column59 | BH26: Column60 | BI26: Column61 | BJ26: Column62 | BK26: Column63 | BL26: Column64 | BM26: Column73 | BN26: Column72 | BO26: Column74 | BP26: Column71 | BQ26: Column77 | BR26: Column78 | BS26: Column76 | BT26: Column75 | BU26: Column79 | BV26: Column82 | BW26: Column81 | BX26: Column80 | BY26: Column86 | BZ26: Column85 | CA26: Column84 | CB26: Column83 | CC26: Column90 | CD26: Column89 | CE26: Column88 | CF26: Column87 | CG26: Column94 | CH26: Column93 | CI26: Column92 | CJ26: Column91 | CK26: Column98 | CL26: Column97 | CM26: Column96 | CN26: Column95 | CO26: Column102 | CP26: Column101 | CQ26: Column100 | CR26: Column99 | CS26: Column103 | CT26: Column104 | CU26: Column105 | CV26: Column106 | CW26: Column107 | CX26: Column108 | CY26: Column109 | CZ26: Column110 | DA26: Column114 | DB26: Column113 | DC26: Column112 | DD26: Column111 | DE26: Column5 | DF26: Column6 | DG26: Column7 | DH26: Column65 | DI26: Column66 | DJ26: Column67 | DK26: Column68 | DL26: Column69 | DM26: Column70
A27: Consultant | B27: S/No. | C27: Projects | G27: Project ID | H27: Task Value | I27: Invoice # 1 date | J27: Invoice # 1 amount | K27: Invoice # 1 vat | L27: Invoice # 1 total | M27: Invoice # 2 date | N27: Invoice # 2 amount | O27: Invoice # 2 vat | P27: Invoice # 2 total | Q27: Invoice # 3 date | R27: Invoice # 3 amount | S27: Invoice # 3 vat | T27: Invoice # 3 total | U27: Invoice # 4 date | V27: Invoice # 4 amount | W27: Invoice # 4 vat | X27: Invoice # 4 total | Y27: Invoice # 5 date | Z27: Invoice # 5 amount | AA27: Invoice # 5 vat | AB27: Invoice # 5 total | AC27: Invoice # 6 date | AD27: Invoice # 6 amount | AE27: Invoice # 6 vat | AF27: Invoice # 6 total | AG27: Invoice # 7 date | AH27: Invoice # 7 amount | AI27: Invoice # 7 vat | AJ27: Invoice # 7 total | AK27: Invoice # 8 date | AL27: Invoice # 8 amount | AM27: Invoice # 8 vat | AN27: Invoice # 8 total | AO27: Invoice # 9 date | AP27: Invoice # 9 amount | AQ27: Invoice # 9 vat | AR27: Invoice # 9 total | AS27: Invoice # 10 date | AT27: Invoice # 10 amount | AU27: Invoice # 10 vat | AV27: Invoice # 10 total | AW27: Invoice # 11 date | AX27: Invoice # 11 amount | AY27: Invoice # 11 vat | AZ27: Invoice # 11 total | BA27: Invoice # 12 date | BB27: Invoice # 12 amount | BC27: Invoice # 12 vat | BD27: Invoice # 12 total | BE27: Invoice # 13 date | BF27: Invoice # 13 amount | BG27: Invoice # 13 vat | BH27: Invoice # 13 total | BI27: Invoice # 14 date | BJ27: Invoice # 14 amount | BK27: Invoice # 14 vat | BL27: Invoice # 14 total | BM27: Invoice # 15 date | BN27: Invoice # 15 amount | BO27: Invoice # 15 vat | BP27: Invoice # 15 total | BQ27: Invoice # 16 date | BR27: Invoice # 16 amount | BS27: Invoice # 16 vat | BT27: Invoice # 16 total | BU27: Invoice # 17 date | BV27: Invoice # 17 amount | BW27: Invoice # 17 vat | BX27: Invoice # 17 total | BY27: Invoice # 18 date | BZ27: Invoice # 18 amount | CA27: Invoice # 18 vat | CB27: Invoice # 18 total | CC27: Invoice # 19 date | CD27: Invoice # 19 amount | CE27: Invoice # 19 vat | CF27: Invoice # 19 total | CG27: Invoice # 20 date | CH27: Invoice # 20 amount | CI27: Invoice # 20 vat | CJ27: Invoice # 20 total | CK27: Invoice # 21 date | CL27: Invoice # 21 amount | CM27: Invoice # 21 vat | CN27: Invoice # 21 total | CO27: Invoice # 22 date | CP27: Invoice # 22 amount | CQ27: Invoice # 22 vat | CR27: Invoice # 22 total | CS27: Invoice # 23 date | CT27: Invoice # 23 amount | CU27: Invoice # 23 vat | CV27: Invoice # 23 total | CW27: Invoice # 24 date | CX27: Invoice # 24 amount | CY27: Invoice # 24 vat | CZ27: Invoice # 24 total | DA27: Invoice # 25 date | DB27: Invoice # 25 amount | DC27: Invoice # 25 vat | DD27: Invoice # 25 total | DE27: Remarks | DF27: Task Value | DG27: VAT | DH27: Total | DI27: Invoices Submitted Without VAT | DJ27: Invoices Submitted With VAT | DK27: % Completion | DL27: Earned Value | DM27: Remaining Value
A29: Dorsch food | G29: MLTX-01-085 | H29: =F6 -> 19993600 | DN29: =SUMPRODUCT(COLUMN(I:DD)-COLUMN(i),2) -> #NAME? | DQ29: 785604 | DS29: =DQ29-Detailed[[#This Row],[Column66]] -> 785604 | DW29: 450 | DX29: 440 | DY29: =DX29*DW29 -> 198000 | EA29: 2907 | EC29: =EA29*DW29 -> 1308150
A30: Dorsch food | B30: 1 | C30: Jeddah 2 - Food Cluster - RBF 450 & 900 m2 | G30: JDH2-01-016 | H30: 877779 | I30: 45225 | J30: 416905 | K30: =J30*15% -> 62535.75 | L30: =J30+K30 -> 479440.75 | Q30: 45398 | R30: 368699 | S30: =R30*15% -> 55304.85 | T30: =R30+S30 -> 424003.85 | DF30: =H30 -> 877779 | DG30: =DF30*15% -> 131666.85 | DH30: =DF30+DG30 -> 1009445.8 | DI30: =SUM(J30,N30,R30,V30,Z30,AD30,AH30,AL30,AP30,AT30,AX30,BB30,BF30,BJ30,BN30,BR30,BV30,BZ30,CD30,CH30,CL30,CP30,CT30,CX30,DB30) -> 785604 | DJ30: =L30+P30+T30+X30+AB30+AF30+AN30 -> 903444.6 | DK30: 1 | DL30: =DK30*DF30 -> 877779 | DM30: =DL30-DI30 -> 92175 | DN30: =SUMPRODUCT(COLUMN(I:DD)-COLUMN(i),2) -> #NAME? | DQ30: 1403611 | DS30: =DQ30-Detailed[[#This Row],[Column66]] -> 618007 | DW30: 333 | DX30: 1416 | DY30: =DX30*DW30 -> 471528 | EA30: 4548 | EC30: =EA30*DW30 -> 1514484
A31: Dorsch food | B31: 2 | C31: Jeddah Food Cluster - Masterplan Update & Lands Selection at Jeddah 2nd & 3rd Ind. Cities | G31: MLTX-01-093 | H31: 1403611 | I31: 45225 | J31: 1403611 | K31: =J31*15% -> 210541.65 | L31: =J31+K31 -> 1614152.6 | DF31: =H31 -> 1403611 | DG31: =DF31*15% -> 210541.65 | DH31: =DF31+DG31 -> 1614152.6 | DI31: =SUM(J31,N31,R31,V31,Z31,AD31,AH31,AL31,AP31,AT31,AX31,BB31,BF31,BJ31,BN31,BR31,BV31,BZ31,CD31,CH31,CL31,CP31,CT31,CX31,DB31) -> 1403611 | DJ31: =L31+P31+T31+X31+AB31+AF31+AN31 -> 1614152.6 | DK31: 1 | DL31: =DK31*DF31 -> 1403611 | DM31: =DL31-DI31 -> 0 | DN31: =SUMPRODUCT(COLUMN(I:DD)-COLUMN(i),2) -> #NAME? | DQ31: 2675323 | DS31: =DQ31-Detailed[[#This Row],[Column66]] -> 1271712 | DW31: 266 | DX31: 2024 | DY31: =DX31*DW31 -> 538384 | EA31: 6170 | EC31: =EA31*DW31 -> 1641220
A32: Dorsch food | B32: 3 | C32: Jeddah 3 - Design of Shared Dry & Cold Storage Warehouses in Jeddah 3 Ind. City | G32: JDH3-01-021 | H32: 2999654 | I32: 45225 | J32: 1377997 | K32: =J32*15% -> 206699.55 | L32: =J32+K32 -> 1584696.6 | Q32: 45398 | R32: 1297326 | S32: =R32*15% -> 194598.9 | T32: =R32+S32 -> 1491924.9 | DF32: =H32 -> 2999654 | DG32: =DF32*15% -> 449948.1 | DH32: =DF32+DG32 -> 3449602.1 | DI32: =SUM(J32,N32,R32,V32,Z32,AD32,AH32,AL32,AP32,AT32,AX32,BB32,BF32,BJ32,BN32,BR32,BV32,BZ32,CD32,CH32,CL32,CP32,CT32,CX32,DB32) -> 2675323 | DJ32: =L32+P32+T32+X32+AB32+AF32+AN32 -> 3076621.5 | DK32: 1 | DL32: =DK32*DF32 -> 2999654 | DM32: =DL32-DI32 -> 324331 | DN32: =SUMPRODUCT(COLUMN(I:DD)-COLUMN(i),2) -> #NAME? | DQ32: 4125000 | DS32: =DQ32-Detailed[[#This Row],[Column66]] -> 1449677 | DW32: 135 | DX32: 2060 | DY32: =DX32*DW32 -> 278100 | EA32: 7544 | EC32: =EA32*DW32 -> 1018440
A33: Dorsch food | B33: 4 | C33: Master planning a logistic area in Dammam 2 | G33: DAM2-01-026 | H33: 4125000 | M33: 45370 | N33: 682683 | O33: =N33*15% -> 102402.45 | P33: =N33+O33 -> 785085.45 | U33: 45435 | V33: 1379810.1 | W33: =V33*15% -> 206971.52 | X33: =V33+W33 -> 1586781.6 | AC33: 45471 | AD33: 2062506.5 | AE33: =AD33*15% -> 309375.98 | AF33: =AD33+AE33 -> 2371882.5 | DF33: =H33 -> 4125000 | DG33: =DF33*15% -> 618750 | DH33: =DF33+DG33 -> 4743750 | DI33: =SUM(J33,N33,R33,V33,Z33,AD33,AH33,AL33,AP33,AT33,AX33,BB33,BF33,BJ33,BN33,BR33,BV33,BZ33,CD33,CH33,CL33,CP33,CT33,CX33,DB33) -> 4124999.6 | DJ33: =L33+P33+T33+X33+AB33+AF33+AN33 -> 4743749.6 | DK33: 1 | DL33: =DK33*DF33 -> 4125000 | DM33: =DL33-DI33 -> 0.37 | DN33: =SUMPRODUCT(COLUMN(I:DD)-COLUMN(i),2) -> #NAME? | DQ33: 404258 | DS33: =DQ33-Detailed[[#This Row],[Column66]] -> -3720741.6 | DY33: =SUM(DY29:DY32) -> 1486012 | EC33: =SUM(EC29:EC32) -> 5482294
A34: Dorsch food | B34: 5 | C34: Hydrology Study for preventing Jeddah 4th Industrial City from floods and stormwater | G34: JDH4-01-040 | H34: 404258 | U34: 45435 | V34: 125226 | W34: =V34*15% -> 18783.9 | X34: =V34+W34 -> 144009.9 | AG34: 45537 | AH34: 279032 | AI34: =AH34*15% -> 41854.8 | AJ34: =AH34+AI34 -> 320886.8 | DF34: =H34 -> 404258 | DG34: =DF34*15% -> 60638.7 | DH34: =DF34+DG34 -> 464896.7 | DI34: =SUM(J34,N34,R34,V34,Z34,AD34,AH34,AL34,AP34,AT34,AX34,BB34,BF34,BJ34,BN34,BR34,BV34,BZ34,CD34,CH34,CL34,CP34,CT34,CX34,DB34) -> 404258 | DJ34: =L34+P34+T34+X34+AB34+AF34+AN34 -> 144009.9 | DK34: 1 | DL34: =DK34*DF34 -> 404258 | DM34: =DL34-DI34 -> 0 | DN34: Was 5,482,294 (task order= 1,486,012) | DQ34: 6968307 | DS34: =DQ34-Detailed[[#This Row],[Column66]] -> 6564049 | DY34: 5478244
A35: Dorsch food | B35: 6 | C35: Completing the infrastructure networks and residential neighborhood in the 2nd industrial city in Dammam | G35: DAM2-02-027 | H35: 6968306 | Y35: 45451 | Z35: 2539503 | AA35: =Z35*15% -> 380925.45 | AB35: =Z35+AA35 -> 2920428.5 | AK35: 45540 | AL35: 1602086 | AM35: =AL35*15% -> 240312.9 | AN35: =AL35+AM35 -> 1842398.9 | BE35: 45728 | BF35: 2826718 | BG35: =BF35*15% -> 424007.69 | BH35: =BF35+BG35 -> 3250725.6 | DF35: =H35 -> 6968306 | DG35: =DF35*15% -> 1045245.9 | DH35: =DF35+DG35 -> 8013551.9 | DI35: =SUM(J35,N35,R35,V35,Z35,AD35,AH35,AL35,AP35,AT35,AX35,BB35,BF35,BJ35,BN35,BR35,BV35,BZ35,CD35,CH35,CL35,CP35,CT35,CX35,DB35) -> 6968307 | DJ35: =Detailed[[#This Row],[Column28]]+Detailed[[#This Row],[Column40]]+Detailed[[#This Row],[Column60]] -> 8013553 | DK35: 1 | DL35: =DK35*DF35 -> 6968306 | DM35: =DL35-DI35 -> -0.95 | DQ35: 174000 | DS35: =DQ35-Detailed[[#This Row],[Column66]] -> -6794307
A36: Dorsch food | B36: 7 | C36: Reviewing the masterplan for alkhrj nd. City | H36: 174000 | Y36: 45451 | Z36: 58000.11 | AA36: =Z36*15% -> 8700.0165 | AB36: =Z36+AA36 -> 66700.126 | AC36: 45471 | AD36: 115999.89 | AE36: =AD36*15% -> 17399.983 | AF36: =AD36+AE36 -> 133399.87 | DF36: =H36 -> 174000 | DG36: =DF36*15% -> 26100 | DH36: =DF36+DG36 -> 200100 | DI36: =SUM(J36,N36,R36,V36,Z36,AD36,AH36,AL36,AP36,AT36,AX36,BB36,BF36,BJ36,BN36,BR36,BV36,BZ36,CD36,CH36,CL36,CP36,CT36,CX36,DB36) -> 174000 | DJ36: =Detailed[[#This Row],[Column28]]+Detailed[[#This Row],[Column32]] -> 200100 | DK36: 1 | DL36: =DK36*DF36 -> 174000 | DM36: =DL36-DI36 -> 0 | DQ36: 836000 | DS36: =DQ36-Detailed[[#This Row],[Column66]] -> 662000 | EA36: =EC33-DY34 -> 4050
A37: Dorsch food | B37: 8 | C37: Detail MPL and infra Design for the multi-use area in Dammam2 | G37: DAM2-01-029 | H37: 836000 | AO37: 45572 | AP37: 302500.8 | AQ37: =AP37*15% -> 45375.12 | AR37: =AP37+AQ37 -> 347875.92 | AS37: 45650 | AT37: 533499.2 | AU37: =AT37*15% -> 80024.88 | AV37: =AT37+AU37 -> 613524.08 | DF37: =H37 -> 836000 | DG37: =DF37*15% -> 125400 | DH37: =DF37+DG37 -> 961400 | DI37: =SUM(J37,N37,R37,V37,Z37,AD37,AH37,AL37,AP37,AT37,AX37,BB37,BF37,BJ37,BN37,BR37,BV37,BZ37,CD37,CH37,CL37,CP37,CT37,CX37,DB37) -> 836000 | DJ37: =Detailed[[#This Row],[Column44]]+Detailed[[#This Row],[Column48]] -> 961400 | DK37: 1 | DL37: =DK37*DF37 -> 836000 | DM37: =DL37-DI37 -> 0 | DN37: with addendum | DQ37: 1254658 | DS37: =DQ37-Detailed[[#This Row],[Column66]] -> 418658
A38: Dorsch food | B38: 9 | C38: Design shared services center - Food cluster | G38: JDH2-01-023 | H38: 1505768 | AO38: 45572 | AP38: 499280 | AQ38: =AP38*15% -> 74892 | AR38: =AP38+AQ38 -> 574172 | AW38: 45693 | AX38: 500302 | AY38: =AX38*15% -> 75045.3 | AZ38: =AX38+AY38 -> 575347.3 | BA38: 45720 | BB38: 255076 | BC38: =BB38*15% -> 38261.4 | BD38: =BB38+BC38 -> 293337.4 | DF38: =H38 -> 1505768 | DG38: =DF38*15% -> 225865.2 | DH38: =DF38+DG38 -> 1731633.2 | DI38: =SUM(J38,N38,R38,V38,Z38,AD38,AH38,AL38,AP38,AT38,AX38,BB38,BF38,BJ38,BN38,BR38,BV38,BZ38,CD38,CH38,CL38,CP38,CT38,CX38,DB38) -> 1254658 | DJ38: =Detailed[[#This Row],[Column44]]+Detailed[[#This Row],[Column48]]+Detailed[[#This Row],[Column52]]+Detailed[[#This Row],[Column56]] -> 1442856.7 | DK38: 1 | DL38: =DK38*DF38 -> 1505768 | DM38: =DL38-DI38 -> 251110 | DQ38: 264505 | DS38: =DQ38-Detailed[[#This Row],[Column66]] -> -990153
A39: Dorsch food | B39: 10 | C39: الدراسه القيميه لمشاريع المصانع الجاهزة | H39: 264505 | AS39: 45650 | AT39: 264505 | AU39: =AT39*15% -> 39675.75 | AV39: =AT39+AU39 -> 304180.75 | DF39: =H39 -> 264505 | DG39: =DF39*15% -> 39675.75 | DH39: =DF39+DG39 -> 304180.75 | DI39: =SUM(J39,N39,R39,V39,Z39,AD39,AH39,AL39,AP39,AT39,AX39,BB39,BF39,BJ39,BN39,BR39,BV39,BZ39,CD39,CH39,CL39,CP39,CT39,CX39,DB39) -> 264505 | DJ39: =Detailed[[#This Row],[Column44]]+Detailed[[#This Row],[Column48]]+Detailed[[#This Row],[Column52]] -> 304180.75 | DK39: 1 | DL39: =DK39*DF39 -> 264505 | DM39: =DL39-DI39 -> 0 | DS39: =DQ39-Detailed[[#This Row],[Column66]] -> -264505
A40: Dorsch food | DF40: =H40 -> 0 | DG40: =DF40*15% -> 0 | DH40: =DF40+DG40 -> 0 | DI40: =SUM(J40,N40,R40,V40,Z40,AD40,AH40,AL40,AP40,AT40,AX40,BB40,BF40,BJ40,BN40,BR40,BV40,BZ40,CD40,CH40,CL40,CP40,CT40,CX40,DB40) -> 0 | DK40: 1 | DL40: =DK40*DF40 -> 0 | DM40: =DL40-DI40 -> 0 | DS40: =DQ40-Detailed[[#This Row],[Column66]] -> 0
A41: Dorsch food | DI41: =SUM(J41,N41,R41,V41,Z41,AD41,AH41,AL41,AP41,AT41,AX41,BB41,BF41,BJ41,BN41,BR41,BV41,BZ41,CD41,CH41,CL41,CP41,CT41,CX41,DB41) -> 0 | DQ41: 18891266 | DS41: =DQ41-Detailed[[#This Row],[Column66]] -> 18891266
A42: Dorsch food | J42: =SUM(J30:J39) -> 3198513 | L42: =SUM(L30:L39) -> 3678290 | N42: =SUM(N30:N39) -> 682683 | P42: =SUM(P30:P39) -> 785085.45 | Q42: 2082531 | R42: =SUM(R30:R39) -> 1666025 | T42: =SUM(T30:T39) -> 1915928.8 | V42: =SUM(V30:V39) -> 1505036.1 | X42: =SUM(X30:X39) -> 1730791.5 | Z42: =SUM(Z30:Z39) -> 2597503.1 | AB42: =SUM(AB30:AB39) -> 2987128.6 | AD42: =SUM(AD30:AD39) -> 2178506.4 | AF42: =SUM(AF30:AF39) -> 2505282.4 | AH42: =SUM(AH30:AH39) -> 279032 | AJ42: =SUM(AJ30:AJ39) -> 320886.8 | AL42: =SUM(AL30:AL39) -> 1602086 | AN42: =SUM(AN30:AN39) -> 1842398.9 | AP42: =SUM(AP30:AP39) -> 801780.8 | AR42: =SUM(AR30:AR39) -> 922047.92 | AT42: =SUM(AT30:AT40) -> 798004.2 | AV42: =SUM(AV30:AV40) -> 917704.83 | AX42: =SUM(AX30:AX40) -> 500302 | AZ42: =SUM(AZ30:AZ40) -> 575347.3 | BB42: =SUM(BB30:BB40) -> 255076 | BD42: =SUM(BD30:BD40) -> 293337.4 | BF42: =SUM(BF30:BF40) -> 2826718 | BH42: =SUM(BH30:BH40) -> 3250725.6 | DF42: =SUM(DF29:DF40) -> 19558881 | DG42: =SUM(DG29:DG40) -> 2933832.2 | DH42: =SUM(DH29:DH40) -> 22492713 | DI42: =SUM(J42,N42,R42,V42,Z42,AD42,AH42,AL42,AP42,AT42,AX42,BB42,BF42,BJ42,BN42,BR42,BV42,BZ42,CD42,CH42,CL42,CP42,CT42,CX42,DB42) -> 18891266 | DJ42: =SUM(DJ29:DJ40) -> 21404069 | DL42: =SUM(DL29:DL40) -> 19558881 | DM42: =SUM(DM29:DM40) -> 667615.42 | DS42: =DQ42-Detailed[[#This Row],[Column66]] -> -18891266
A43: SYSTRA | G43: MLTX-01-102 | H43: =F8 -> 15054089 | DI43: =SUM(J43,N43,R43,V43,Z43,AD43,AH43,AL43,AP43,AT43,AX43,BB43,BF43,BJ43,BN43,BR43,BV43,BZ43,CD43,CH43,CL43,CP43,CT43,CX43,DB43) -> 0 | DO43: =COLUMN(I45:DD45) -> 9 | DQ43: 5381577.6 | DS43: =DQ43-Detailed[[#This Row],[Column66]] -> 5381577.6
A44: SYSTRA | B44: 1 | C44: Masterplan & Infrstructure Detailed Design For Technology Zones (Jenadryah) | G44: JNDT-01-001 | H44: 6726972 | I44: 45504 | J44: =SYSTRA!H12 -> 672697.82 | K44: =J44*15% -> 100904.67 | L44: =J44+K44 -> 773602.49 | M44: 45511 | N44: =SYSTRA!J12 -> 1681772 | O44: =N44*15% -> 252265.8 | P44: =N44+O44 -> 1934037.8 | Q44: 45641 | R44: =SYSTRA!L12 -> 1345449 | S44: =R44*15% -> 201817.35 | T44: =R44+S44 -> 1547266.4 | U44: 45727 | V44: =SYSTRA!N12 -> 1681658.8 | W44: =V44*15% -> 252248.82 | X44: =V44+W44 -> 1933907.6 | AC44: 45839 | AD44: =SYSTRA!R12 -> 1345394.4 | AE44: =AD44*15% -> 201809.16 | AF44: =AD44+AE44 -> 1547203.6 | DF44: =H44 -> 6726972 | DG44: =DF44*15% -> 1009045.8 | DH44: =DF44+DG44 -> 7736017.8 | DI44: =SUM(J44,N44,R44,V44,Z44,AD44,AH44,AL44,AP44,AT44,AX44,BB44,BF44,BJ44,BN44,BR44,BV44,BZ44,CD44,CH44,CL44,CP44,CT44,CX44,DB44) -> 6726972 | DJ44: =Detailed[[#This Row],[Column12]]+Detailed[[#This Row],[Column16]]+Detailed[[#This Row],[Column20]]+Detailed[[#This Row],[Column24]]+Detailed[[#This Row],[Column28]]+Detailed[[#This Row],[Column32]]+Detailed[[#This Row],[Column36]]+Detailed[[#This Row],[Column40]]+Detailed[[#This Row],[Column44]]+Detailed[[#This Row],[Column48]]+Detailed[[#This Row],[Column52]] -> 7736017.8 | DK44: 1 | DL44: =DK44*DF44 -> 6726972 | DM44: =DL44-DI44 -> 0 | DQ44: 330043.5 | DS44: =DQ44-Detailed[[#This Row],[Column66]] -> -6396928.5
A45: SYSTRA | B45: 2 | C45: Masterplan & Infrstructure Detailed Design For Technology Zones (Dammam) | G45: DAMT-01-001 | H45: 3300435 | U45: 45727 | V45: =SYSTRA!N27 -> 330043.5 | W45: =V45*15% -> 49506.525 | X45: =V45+W45 -> 379550.03 | Y45: 45788 | Z45: =SYSTRA!P27 -> 1072641.4 | AA45: =Z45*15% -> 160896.21 | AB45: =Z45+AA45 -> 1233537.6 | AC45: 45839 | AD45: =SYSTRA!R27 -> 577576.13 | AE45: =AD45*15% -> 86636.42 | AF45: =AD45+AE45 -> 664212.55 | DF45: =H45 -> 3300435 | DG45: =DF45*15% -> 495065.25 | DH45: =DF45+DG45 -> 3795500.2 | DI45: =SUMPRODUCT((MOD(COLUMN(I45:DD45)-COLUMN(I45),4)=1)*I45:DD45) -> 1980261 | DJ45: =SUMPRODUCT((MOD(COLUMN(I45:DD45)-COLUMN(J45),4)=2)*I45:DD45) -> 2277300.1 | DK45: 1 | DL45: =DK45*DF45 -> 3300435 | DM45: =DL45-DI45 -> 1320174 | DO45: =SUMPRODUCT((MOD(COLUMN(I45:DD45)-COLUMN(I45),4)=1)*I45:DD45) -> 1980261 | DP45: =DO45-Detailed[[#This Row],[Column66]] -> 0 | DQ45: 330043.5 | DS45: =DQ45-Detailed[[#This Row],[Column66]] -> -1650217.5
A46: SYSTRA | B46: 3 | C46: Masterplan & Infrstructure Detailed Design For Technology Zones (Dhahran) | G46: DHRT-01-001 | H46: 3300435 | U46: 45727 | V46: =SYSTRA!N42 -> 330043.5 | W46: =V46*15% -> 49506.525 | X46: =V46+W46 -> 379550.03 | Y46: 45788 | Z46: =SYSTRA!P42 -> 1072641.4 | AA46: =Z46*15% -> 160896.21 | AB46: =Z46+AA46 -> 1233537.6 | AC46: 45839 | AD46: =SYSTRA!R42 -> 577576.12 | AE46: =AD46*15% -> 86636.418 | AF46: =AD46+AE46 -> 664212.54 | DF46: =H46 -> 3300435 | DG46: =DF46*15% -> 495065.25 | DH46: =DF46+DG46 -> 3795500.2 | DI46: =SUMPRODUCT((MOD(COLUMN(I46:DD46)-COLUMN(I46),4)=1)*I46:DD46) -> 1980261 | DJ46: =SUMPRODUCT((MOD(COLUMN(I46:DD46)-COLUMN(J46),4)=2)*I46:DD46) -> 2277300.1 | DK46: 1 | DL46: =DK46*DF46 -> 3300435 | DM46: =DL46-DI46 -> 1320174 | DO46: =SUMPRODUCT((MOD(COLUMN(I46:DD46)-COLUMN(I46),4)=1)*I46:DD46) -> 1980261 | DP46: =DO46-Detailed[[#This Row],[Column66]] -> 0 | DS46: =DQ46-Detailed[[#This Row],[Column66]] -> -1980261
A47: SYSTRA | B47: 4 | C47: Technical review and transport planning expertise support for Riyadh Industrial cities 1 & 4 | G47: MLTX-01-111 | H47: 1726247 | Y47: 45788 | Z47: =SYSTRA!P57 -> 1208358 | AA47: =Z47*15% -> 181253.7 | AB47: =Z47+AA47 -> 1389611.7 | AC47: 45839 | AD47: =SYSTRA!R57 -> 517889.02 | AE47: =AD47*15% -> 77683.353 | AF47: =AD47+AE47 -> 595572.37 | DF47: =H47 -> 1726247 | DG47: =DF47*15% -> 258937.05 | DH47: =DF47+DG47 -> 1985184.1 | DI47: =SUM(J47,N47,R47,V47,Z47,AD47,AH47,AL47,AP47,AT47,AX47,BB47,BF47,BJ47,BN47,BR47,BV47,BZ47,CD47,CH47,CL47,CP47,CT47,CX47,DB47) -> 1726247 | DJ47: =Detailed[[#This Row],[Column12]]+Detailed[[#This Row],[Column16]]+Detailed[[#This Row],[Column20]]+Detailed[[#This Row],[Column24]]+Detailed[[#This Row],[Column28]]+Detailed[[#This Row],[Column32]]+Detailed[[#This Row],[Column36]]+Detailed[[#This Row],[Column40]]+Detailed[[#This Row],[Column44]]+Detailed[[#This Row],[Column48]]+Detailed[[#This Row],[Column52]] -> 1985184 | DK47: 1 | DL47: =DK47*DF47 -> 1726247 | DM47: =DL47-DI47 -> 0 | DP47: =DO47-Detailed[[#This Row],[Column66]] -> -1726247 | DS47: =DQ47-Detailed[[#This Row],[Column66]] -> -1726247
A48: SYSTRA | DI48: =SUM(J48,N48,R48,V48,Z48,AD48,AH48,AL48,AP48,AT48,AX48,BB48,BF48,BJ48,BN48,BR48,BV48,BZ48,CD48,CH48,CL48,CP48,CT48,CX48,DB48) -> 0 | DP48: =DO48-Detailed[[#This Row],[Column66]] -> 0 | DQ48: 6041664.6 | DS48: =DQ48-Detailed[[#This Row],[Column66]] -> 6041664.6
A49: SYSTRA | J49: =SUM(J43:J48) -> 672697.82 | L49: =SUM(L43:L48) -> 773602.49 | N49: =SUM(N43:N48) -> 1681772 | P49: =SUM(P43:P48) -> 1934037.8 | R49: =SUM(R43:R48) -> 1345449 | T49: =SUM(T43:T48) -> 1547266.4 | V49: =SUM(V43:V48) -> 2341745.8 | X49: =SUM(X43:X48) -> 2693007.6 | Z49: =SUM(Z43:Z48) -> 3353640.7 | AB49: =SUM(AB43:AB48) -> 3856686.8 | AD49: =SUM(AD43:AD48) -> 3018435.7 | AF49: =SUM(AF43:AF48) -> 3471201 | DF49: =SUM(DF43:DF47) -> 15054089 | DG49: =SUM(DG43:DG47) -> 2258113.3 | DH49: =SUM(DH43:DH47) -> 17312202 | DI49: =SUM(J49,N49,R49,V49,Z49,AD49,AH49,AL49,AP49,AT49,AX49,BB49,BF49,BJ49,BN49,BR49,BV49,BZ49,CD49,CH49,CL49,CP49,CT49,CX49,DB49) -> 12413741 | DJ49: =SUM(DJ43:DJ47) -> 14275802 | DL49: =SUM(DL43:DL47) -> 15054089 | DM49: =SUM(DM43:DM47) -> 2640348 | DS49: =DQ49-Detailed[[#This Row],[Column66]] -> -12413741
A50: EGEC - NIS2 | G50: MLTX-01-099 | H50: =F9 -> 19979840 | DI50: =SUM(J50,N50,R50,V50,Z50,AD50,AH50,AL50,AP50,AT50,AX50,BB50,BF50,BJ50,BN50,BR50,BV50,BZ50,CD50,CH50,CL50,CP50,CT50,CX50,DB50) -> 0 | DP50: =DO50-Detailed[[#This Row],[Column66]] -> 0 | DQ50: 4360270 | DS50: =DQ50-Detailed[[#This Row],[Column66]] -> 4360270
A51: EGEC - NIS2 | B51: 1 | C51: Updated concept masterplan & Infrastructure designs for Tabouk ind. City | G51: TAB-01-009 | H51: 4360270 | I51: 45496 | J51: ='EGEC - NIS2'!M17 -> 1395290.5 | K51: =J51*15% -> 209293.57 | L51: =J51+K51 -> 1604584.1 | M51: 45532 | N51: ='EGEC - NIS2'!O17 -> 1874916.4 | O51: =N51*15% -> 281237.46 | P51: =N51+O51 -> 2156153.8 | Y51: 45626 | Z51: ='EGEC - NIS2'!Q17 -> 872049.61 | AA51: =Z51*15% -> 130807.44 | AB51: =Z51+AA51 -> 1002857.1 | AC51: 45651 | AD51: ='EGEC - NIS2'!S17 -> 218013.5 | AE51: =AD51*15% -> 32702.025 | AF51: =AD51+AE51 -> 250715.52 | DF51: =H51 -> 4360270 | DG51: =DF51*15% -> 654040.5 | DH51: =DF51+DG51 -> 5014310.5 | DI51: =SUM(J51,N51,R51,V51,Z51,AD51,AH51,AL51,AP51,AT51,AX51,BB51,BF51,BJ51,BN51,BR51,BV51,BZ51,CD51,CH51,CL51,CP51,CT51,CX51,DB51) -> 4360270 | DJ51: =L51+P51+T51+X51+AB51+AF51+AJ51+AN51+AR51+Detailed[[#This Row],[Column48]]+Detailed[[#This Row],[Column52]]+Detailed[[#This Row],[Column56]]+Detailed[[#This Row],[Column60]]+Detailed[[#This Row],[Column64]]+Detailed[[#This Row],[Column71]]+Detailed[[#This Row],[Column75]]+Detailed[[#This Row],[Column80]] -> 5014310.5 | DK51: 1 | DL51: =DK51*DF51 -> 4360270 | DM51: =DL51-DI51 -> 5.0002709e-06 | DP51: =DO51-Detailed[[#This Row],[Column66]] -> -4360270 | DQ51: 1116225 | DS51: =DQ51-Detailed[[#This Row],[Column66]] -> -3244045
A52: EGEC - NIS2 | B52: 2 | C52: Project support services (6 months) (Masterplan) | H52: 744150 | M52: 45532 | N52: ='EGEC - NIS2'!O32 -> 372075 | O52: =N52*15% -> 55811.25 | P52: =N52+O52 -> 427886.25 | U52: 45596 | V52: ='EGEC - NIS2'!Q32 -> 372075 | W52: =V52*15% -> 55811.25 | X52: =V52+W52 -> 427886.25 | DF52: =H52 -> 744150 | DG52: =DF52*15% -> 111622.5 | DH52: =DF52+DG52 -> 855772.5 | DI52: =SUM(J52,N52,R52,V52,Z52,AD52,AH52,AL52,AP52,AT52,AX52,BB52,BF52,BJ52,BN52,BR52,BV52,BZ52,CD52,CH52,CL52,CP52,CT52,CX52,DB52) -> 744150 | DJ52: =L52+P52+T52+X52+AB52+AF52+AJ52+AN52+AV52 -> 855772.5 | DK52: 1 | DL52: =DK52*DF52 -> 744150 | DM52: =DL52-DI52 -> 0 | DP52: =DO52-Detailed[[#This Row],[Column66]] -> -744150 | DQ52: 0 | DS52: =DQ52-Detailed[[#This Row],[Column66]] -> -744150
A53: EGEC - NIS2 | B53: 3 | C53: Project support services (6 months) (VRO) | H53: 744150 | AG53: 45688 | AH53: ='EGEC - NIS2'!U32 -> 372075 | AI53: =AH53*15% -> 55811.25 | AJ53: =AH53+AI53 -> 427886.25 | AW53: 45807 | AX53: ='EGEC - NIS2'!W32 -> 372075 | AY53: =AX53*15% -> 55811.25 | AZ53: =AX53+AY53 -> 427886.25 | DF53: =H53 -> 744150 | DG53: =DF53*15% -> 111622.5 | DH53: =DF53+DG53 -> 855772.5 | DI53: =SUM(J53,N53,R53,V53,Z53,AD53,AH53,AL53,AP53,AT53,AX53,BB53,BF53,BJ53,BN53,BR53,BV53,BZ53,CD53,CH53,CL53,CP53,CT53,CX53,DB53) -> 744150 | DJ53: =L53+P53+T53+X53+AB53+AF53+AJ53+AN53+AV53+Detailed[[#This Row],[Column52]] -> 855772.5 | DK53: 1 | DL53: =DK53*DF53 -> 744150 | DM53: =DL53-DI53 -> 0 | DP53: =DO53-Detailed[[#This Row],[Column66]] -> -744150 | DQ53: 153002.2 | DS53: =DQ53-Detailed[[#This Row],[Column66]] -> -591147.8
A54: EGEC - NIS2 | B54: 4 | C54: Testing and evaluating concrete structure | H54: 153002 | M54: 45532 | N54: ='EGEC - NIS2'!O47 -> 107101.54 | O54: =N54*15% -> 16065.231 | P54: =N54+O54 -> 123166.77 | Q54: 45586 | R54: ='EGEC - NIS2'!Q47 -> 45900.66 | S54: =R54*15% -> 6885.099 | T54: =R54+S54 -> 52785.759 | DF54: =H54 -> 153002 | DG54: =DF54*15% -> 22950.3 | DH54: =DF54+DG54 -> 175952.3 | DI54: =SUM(J54,N54,R54,V54,Z54,AD54,AH54,AL54,AP54,AT54,AX54,BB54,BF54,BJ54,BN54,BR54,BV54,BZ54,CD54,CH54,CL54,CP54,CT54,CX54,DB54) -> 153002.2 | DJ54: =L54+P54+T54+X54+AB54+AF54+AJ54+AN54+AV54 -> 175952.53 | DK54: 1 | DL54: =DK54*DF54 -> 153002 | DM54: =DL54-DI54 -> -0.2 | DP54: =DO54-Detailed[[#This Row],[Column66]] -> -153002.2 | DQ54: 156177 | DS54: =DQ54-Detailed[[#This Row],[Column66]] -> 3174.8
A55: EGEC - NIS2 | B55: 5 | C55: Preliminary designs for the expansion of the industrial city in riyadh | H55: 156177 | Q55: 45586 | R55: ='EGEC - NIS2'!Q64 -> 109323.9 | S55: =R55*15% -> 16398.585 | T55: =R55+S55 -> 125722.48 | Y55: 45626 | Z55: 46853.1 | AA55: =Z55*15% -> 7027.965 | AB55: =Z55+AA55 -> 53881.065 | DF55: =H55 -> 156177 | DG55: =DF55*15% -> 23426.55 | DH55: =DF55+DG55 -> 179603.55 | DI55: =SUM(J55,N55,R55,V55,Z55,AD55,AH55,AL55,AP55,AT55,AX55,BB55,BF55,BJ55,BN55,BR55,BV55,BZ55,CD55,CH55,CL55,CP55,CT55,CX55,DB55) -> 156177 | DJ55: =L55+P55+T55+X55+AB55+AF55+AJ55+AN55+AV55 -> 179603.55 | DK55: 1 | DL55: =DK55*DF55 -> 156177 | DM55: =DL55-DI55 -> 0 | DP55: =DO55-Detailed[[#This Row],[Column66]] -> -156177 | DQ55: 1656100 | DS55: =DQ55-Detailed[[#This Row],[Column66]] -> 1499923
A56: EGEC - NIS2 | B56: 6 | C56: Incubators in Al-Qassim Oasis | G56: QSM3-01-014 | H56: 1656100 | Y56: 45626 | Z56: 248415 | AA56: =Z56*15% -> 37262.25 | AB56: =Z56+AA56 -> 285677.25 | AC56: 45651 | AD56: ='EGEC - NIS2'!M82 -> 828050 | AE56: =AD56*15% -> 124207.5 | AF56: =AD56+AE56 -> 952257.5 | AG56: 45688 | AH56: ='EGEC - NIS2'!O82 -> 579635 | AI56: =AH56*15% -> 86945.25 | AJ56: =AH56+AI56 -> 666580.25 | DF56: =H56 -> 1656100 | DG56: =DF56*15% -> 248415 | DH56: =DF56+DG56 -> 1904515 | DI56: =SUM(J56,N56,R56,V56,Z56,AD56,AH56,AL56,AP56,AT56,AX56,BB56,BF56,BJ56,BN56,BR56,BV56,BZ56,CD56,CH56,CL56,CP56,CT56,CX56,DB56) -> 1656100 | DJ56: =Detailed[[#This Row],[Column28]]+Detailed[[#This Row],[Column32]]+Detailed[[#This Row],[Column36]] -> 1904515 | DK56: 1 | DL56: =DK56*DF56 -> 1656100 | DM56: =DL56-DI56 -> 0 | DP56: =DO56-Detailed[[#This Row],[Column66]] -> -1656100 | DQ56: 768027 | DS56: =DQ56-Detailed[[#This Row],[Column66]] -> -888073
A57: EGEC - NIS2 | B57: 7 | C57: Site development and infrastructure design works for expansion in Jeddah 1 | G57: JDH1-01-021 | H57: 2560090 | AG57: 45688 | AH57: ='EGEC - NIS2'!O101 -> 384013.5 | AI57: =AH57*15% -> 57602.025 | AJ57: =AH57+AI57 -> 441615.53 | AO57: 45760 | AP57: ='EGEC - NIS2'!S101 -> 384013.5 | AQ57: =AP57*15% -> 57602.025 | AR57: =AP57+AQ57 -> 441615.53 | AS57: 45777 | AT57: ='EGEC - NIS2'!U101 -> 640022.5 | AU57: =AT57*15% -> 96003.375 | AV57: =AT57+AU57 -> 736025.88 | AW57: 45807 | AX57: ='EGEC - NIS2'!W101 -> 896032 | AY57: =AX57*15% -> 134404.8 | AZ57: =AX57+AY57 -> 1030436.8 | BA57: 45865 | BB57: ='EGEC - NIS2'!Y101 -> 256008.5 | BC57: =BB57*15% -> 38401.275 | BD57: =BB57+BC57 -> 294409.78 | DF57: =H57 -> 2560090 | DG57: =DF57*15% -> 384013.5 | DH57: =DF57+DG57 -> 2944103.5 | DI57: =SUM(J57,N57,R57,V57,Z57,AD57,AH57,AL57,AP57,AT57,AX57,BB57,BF57,BJ57,BN57,BR57,BV57,BZ57,CD57,CH57,CL57,CP57,CT57,CX57,DB57) -> 2560090 | DJ57: =Detailed[[#This Row],[Column36]]+Detailed[[#This Row],[Column44]]+Detailed[[#This Row],[Column48]]+Detailed[[#This Row],[Column52]] -> 2649693.7 | DK57: 1 | DL57: =DK57*DF57 -> 2560090 | DM57: =DL57-DI57 -> 0 | DP57: =DO57-Detailed[[#This Row],[Column66]] -> -2560090 | DQ57: 693000 | DS57: =DQ57-Detailed[[#This Row],[Column66]] -> -1867090
A58: EGEC - NIS2 | B58: 8 | C58: Detailed design of connection road (Fly Over) in Dammam 2 | G58: DAM2-01-033 | H58: 2310000 | AO58: 45760 | AP58: ='EGEC - NIS2'!S165 -> 693000 | AQ58: =AP58*15% -> 103950 | AR58: =AP58+AQ58 -> 796950 | DF58: =H58 -> 2310000 | DG58: =DF58*15% -> 346500 | DH58: =DF58+DG58 -> 2656500 | DI58: =SUM(J58,N58,R58,V58,Z58,AD58,AH58,AL58,AP58,AT58,AX58,BB58,BF58,BJ58,BN58,BR58,BV58,BZ58,CD58,CH58,CL58,CP58,CT58,CX58,DB58) -> 693000 | DJ58: =Detailed[[#This Row],[Column44]] -> 796950 | DK58: 0.3 | DL58: =DK58*DF58 -> 693000 | DM58: =DL58-DI58 -> 0 | DP58: =DO58-Detailed[[#This Row],[Column66]] -> -693000 | DQ58: 350000 | DS58: =DQ58-Detailed[[#This Row],[Column66]] -> -343000
A59: EGEC - NIS2 | B59: 9 | C59: Labour camp masterplan and infrastructure development in AlKharj | G59: KHJ-01-025 | H59: 350000 | AK59: 45718 | AL59: ='EGEC - NIS2'!Q124 -> 175000 | AM59: =AL59*15% -> 26250 | AN59: =AL59+AM59 -> 201250 | AO59: 45760 | AP59: ='EGEC - NIS2'!S124 -> 175000 | AQ59: =AP59*15% -> 26250 | AR59: =AP59+AQ59 -> 201250 | DF59: =H59 -> 350000 | DG59: =DF59*15% -> 52500 | DH59: =DF59+DG59 -> 402500 | DI59: =SUM(J59,N59,R59,V59,Z59,AD59,AH59,AL59,AP59,AT59,AX59,BB59,BF59,BJ59,BN59,BR59,BV59,BZ59,CD59,CH59,CL59,CP59,CT59,CX59,DB59) -> 350000 | DJ59: =Detailed[[#This Row],[Column40]]+Detailed[[#This Row],[Column44]] -> 402500 | DK59: 1 | DL59: =DK59*DF59 -> 350000 | DM59: =DL59-DI59 -> 0 | DP59: =DO59-Detailed[[#This Row],[Column66]] -> -350000 | DQ59: 210000 | DS59: =DQ59-Detailed[[#This Row],[Column66]] -> -140000
A60: EGEC - NIS2 | B60: 10 | C60: Potable water pipeline supply and connection to alkharj 1st ind. City | G60: KHJ-01-026 | H60: 700000 | AO60: 45760 | AP60: ='EGEC - NIS2'!S146 -> 210000 | AQ60: =AP60*15% -> 31500 | AR60: =AP60+AQ60 -> 241500 | BE60: 45907 | BF60: ='EGEC - NIS2'!U146 -> 175000.64 | BG60: =BF60*15% -> 26250.096 | BH60: =BF60+BG60 -> 201250.74 | BQ60: 45994 | BR60: ='EGEC - NIS2'!W146 -> 140000 | BS60: =Detailed[[#This Row],[Column78]]*15% -> 21000 | BT60: =Detailed[[#This Row],[Column76]]+Detailed[[#This Row],[Column78]] -> 161000 | DF60: =H60 -> 700000 | DG60: =DF60*15% -> 105000 | DH60: =DF60+DG60 -> 805000 | DI60: =SUMPRODUCT((MOD(COLUMN(I60:DD60)-COLUMN(I60),4)=1)*I60:DD60) -> 525000.64 | DJ60: =SUMPRODUCT((MOD(COLUMN(I60:DD60)-COLUMN(J60),4)=2)*I60:DD60) -> 603750.74 | DK60: 0.86 | DL60: =DK60*DF60 -> 602000 | DM60: =DL60-DI60 -> 76999.36 | DO60: =SUMPRODUCT((MOD(COLUMN(I60:DD60)-COLUMN(I60),4)=1)*I60:DD60) -> 525000.64 | DP60: =DO60-Detailed[[#This Row],[Column66]] -> 0 | DQ60: 85000 | DS60: =DQ60-Detailed[[#This Row],[Column66]] -> -440000.64
A61: EGEC - NIS2 | B61: 11 | C61: Study design RBFs 900 & 450m2 SFDA requirements | H61: 170000 | AO61: 45760 | AP61: ='EGEC - NIS2'!S183 -> 85000 | AQ61: =AP61*15% -> 12750 | AR61: =AP61+AQ61 -> 97750 | BI61: 45929 | BJ61: ='EGEC - NIS2'!W183 -> 85000 | BK61: =Detailed[[#This Row],[Column62]]*15% -> 12750 | BL61: =Detailed[[#This Row],[Column62]]+Detailed[[#This Row],[Column63]] -> 97750 | DF61: =H61 -> 170000 | DG61: =DF61*15% -> 25500 | DH61: =DF61+DG61 -> 195500 | DI61: =SUM(J61,N61,R61,V61,Z61,AD61,AH61,AL61,AP61,AT61,AX61,BB61,BF61,BJ61,BN61,BR61,BV61,BZ61,CD61,CH61,CL61,CP61,CT61,CX61,DB61) -> 170000 | DJ61: =Detailed[[#This Row],[Column44]] -> 97750 | DK61: 1 | DL61: =DK61*DF61 -> 170000 | DM61: =DL61-DI61 -> 0 | DP61: =DO61-Detailed[[#This Row],[Column66]] -> -170000
A62: EGEC - NIS2 | B62: 12 | C62: Improving the entrances and exit points for Jeddah 1 | G62: JDH1-01-028 | H62: 1590000 | BM62: 45956 | BN62: ='EGEC - NIS2'!M247 -> 794999.1 | BO62: =Detailed[[#This Row],[Column72]]*15% -> 119249.87 | BP62: =Detailed[[#This Row],[Column72]]+Detailed[[#This Row],[Column74]] -> 914248.97 | DF62: =H62 -> 1590000 | DG62: =DF62*15% -> 238500 | DH62: =DF62+DG62 -> 1828500 | DI62: =SUMPRODUCT((MOD(COLUMN(I62:DD62)-COLUMN(I62),4)=1)*I62:DD62) -> 794999.1 | DJ62: =SUMPRODUCT((MOD(COLUMN(I62:DD62)-COLUMN(J62),4)=2)*I62:DD62) -> 914248.97 | DK62: 0.85 | DL62: =DK62*DF62 -> 1351500 | DM62: =DL62-DI62 -> 556500.9 | DO62: =SUMPRODUCT((MOD(COLUMN(I62:DD62)-COLUMN(I62),4)=1)*I62:DD62) -> 794999.1 | DP62: =DO62-Detailed[[#This Row],[Column66]] -> 0 | DS62: =DQ62-Detailed[[#This Row],[Column66]] -> -794999.1
A63: EGEC - NIS2 | B63: 13 | C63: Hydrology study for Jeddah 2 | H63: 110500 | BM63: 45956 | BN63: ='EGEC - NIS2'!M232 -> 44199.17 | BO63: =Detailed[[#This Row],[Column72]]*15% -> 6629.8755 | BP63: =Detailed[[#This Row],[Column72]]+Detailed[[#This Row],[Column74]] -> 50829.046 | DF63: =H63 -> 110500 | DG63: =DF63*15% -> 16575 | DH63: =DF63+DG63 -> 127075 | DI63: =SUMPRODUCT((MOD(COLUMN(I63:DD63)-COLUMN(I63),4)=1)*I63:DD63) -> 44199.17 | DJ63: =SUMPRODUCT((MOD(COLUMN(I63:DD63)-COLUMN(J63),4)=2)*I63:DD63) -> 50829.046 | DK63: 0.98 | DL63: =DK63*DF63 -> 108290 | DM63: =DL63-DI63 -> 64090.83 | DO63: =SUMPRODUCT((MOD(COLUMN(I63:DD63)-COLUMN(I63),4)=1)*I63:DD63) -> 44199.17 | DP63: =DO63-Detailed[[#This Row],[Column66]] -> 0
A64: EGEC - NIS2 | B64: 14 | C64: Jenadriyadh Business Incubators | G64: JNDT-01-002 | H64: 500000 | BQ64: 45994 | BR64: ='EGEC - NIS2'!M262 -> 100000 | BS64: =Detailed[[#This Row],[Column78]]*15% -> 15000 | BT64: =Detailed[[#This Row],[Column76]]+Detailed[[#This Row],[Column78]] -> 115000 | DF64: =H64 -> 500000 | DG64: =DF64*15% -> 75000 | DH64: =DF64+DG64 -> 575000 | DI64: =SUMPRODUCT((MOD(COLUMN(I64:DD64)-COLUMN(I64),4)=1)*I64:DD64) -> 100000 | DJ64: =SUMPRODUCT((MOD(COLUMN(I64:DD64)-COLUMN(J64),4)=2)*I64:DD64) -> 115000 | DK64: 0.25 | DL64: =DK64*DF64 -> 125000 | DM64: =DL64-DI64 -> 25000 | DO64: =SUMPRODUCT((MOD(COLUMN(I64:DD64)-COLUMN(I64),4)=1)*I64:DD64) -> 100000 | DP64: =DO64-Detailed[[#This Row],[Column66]] -> 0
A65: EGEC - NIS2 | B65: 15 | C65: Project support services 3 | H65: 1798340 | BE65: 45907 | BF65: ='EGEC - NIS2'!M202 -> 449585 | BG65: =BF65*15% -> 67437.75 | BH65: =BF65+BG65 -> 517022.75 | BI65: 45929 | BJ65: ='EGEC - NIS2'!O202 -> 449585 | BK65: =Detailed[[#This Row],[Column62]]*15% -> 67437.75 | BL65: =Detailed[[#This Row],[Column62]]+Detailed[[#This Row],[Column63]] -> 517022.75 | DF65: =Detailed[[#This Row],[Column8]] -> 1798340 | DG65: =DF65*15% -> 269751 | DH65: =DF65+DG65 -> 2068091 | DI65: =SUMPRODUCT((MOD(COLUMN(I65:DD65)-COLUMN(I65),4)=1)*I65:DD65) -> 899170 | DJ65: =SUMPRODUCT((MOD(COLUMN(I65:DD65)-COLUMN(J65),4)=2)*I65:DD65) -> 1034045.5 | DK65: 1 | DL65: =DK65*DF65 -> 1798340 | DM65: =DL65-DI65 -> 899170 | DO65: =SUMPRODUCT((MOD(COLUMN(I65:DD65)-COLUMN(I65),4)=1)*I65:DD65) -> 899170 | DP65: =DO65-Detailed[[#This Row],[Column66]] -> 0
A66: EGEC - NIS2 | B66: 16 | C66: Adaptation and Design of an Administrative Building Humanization in Riyadh 2 | H66: 590000 | BI66: 45929 | BJ66: ='EGEC - NIS2'!M217 -> 471999.23 | BK66: =Detailed[[#This Row],[Column62]]*15% -> 70799.885 | BL66: =Detailed[[#This Row],[Column62]]+Detailed[[#This Row],[Column63]] -> 542799.11 | BQ66: 45994 | BR66: ='EGEC - NIS2'!O217 -> 59000 | BS66: =Detailed[[#This Row],[Column78]]*15% -> 8850 | BT66: =Detailed[[#This Row],[Column76]]+Detailed[[#This Row],[Column78]] -> 67850 | DF66: =Detailed[[#This Row],[Column8]] -> 590000 | DG66: =DF66*15% -> 88500 | DH66: =DF66+DG66 -> 678500 | DI66: =SUMPRODUCT((MOD(COLUMN(I66:DD66)-COLUMN(I66),4)=1)*I66:DD66) -> 530999.23 | DJ66: =SUMPRODUCT((MOD(COLUMN(I66:DD66)-COLUMN(J66),4)=2)*I66:DD66) -> 610649.11 | DK66: 0.8 | DL66: =DK66*DF66 -> 472000 | DM66: =DL66-DI66 -> -58999.23 | DO66: =SUMPRODUCT((MOD(COLUMN(I66:DD66)-COLUMN(I66),4)=1)*I66:DD66) -> 530999.23 | DP66: =DO66-Detailed[[#This Row],[Column66]] -> 0
A67: EGEC - NIS2 | DO67: =SUMPRODUCT((MOD(COLUMN(I67:DD67)-COLUMN(I67),4)=1)*I67:DD67) -> 0 | DP67: =DO67-Detailed[[#This Row],[Column66]] -> 0 | DQ67: 9547801.2 | DS67: =DQ67-Detailed[[#This Row],[Column66]] -> 9547801.2
A68: EGEC - NIS2 | J68: =SUM(J50:J56) -> 1395290.5 | L68: =SUM(L50:L56) -> 1604584.1 | N68: =SUM(N50:N56) -> 2354092.9 | P68: =SUM(P50:P56) -> 2707206.9 | R68: =SUM(R50:R56) -> 155224.56 | T68: =SUM(T50:T56) -> 178508.24 | V68: =SUM(V50:V56) -> 372075 | X68: =SUM(X50:X56) -> 427886.25 | Z68: =SUM(Z50:Z56) -> 1167317.7 | AB68: =SUM(AB50:AB56) -> 1342415.4 | AD68: =SUM(AD50:AD56) -> 1046063.5 | AF68: =SUM(AF50:AF56) -> 1202973 | AH68: =SUM(AH50:AH57) -> 1335723.5 | AJ68: =SUM(AJ50:AJ57) -> 1536082 | AL68: =SUM(AL50:AL63) -> 175000 | AN68: =SUM(AN50:AN59) -> 201250 | AP68: =SUM(AP50:AP63) -> 1547013.5 | AR68: =SUM(AR50:AR59) -> 1439815.5 | AT68: =SUM(AT50:AT63) -> 640022.5 | AV68: =SUM(AV50:AV59) -> 736025.88 | AX68: =SUM(AX50:AX63) -> 1268107 | AZ68: =SUM(AZ50:AZ59) -> 1458323.1 | BB68: =SUM(BB50:BB63) -> 256008.5 | BD68: =SUM(BD50:BD59) -> 294409.78 | BF68: =SUM(BF50:BF65) -> 624585.64 | BH68: =SUM(BH50:BH65) -> 718273.49 | BJ68: =SUM(BJ54:BJ66) -> 1006584.2 | BK68: =Detailed[[#This Row],[Column62]]*15% -> 150987.63 | BL68: =SUM(BL50:BL66) -> 1157571.9 | BN68: =SUM(BN54:BN66) -> 839198.27 | BO68: =Detailed[[#This Row],[Column72]]*15% -> 125879.74 | BP68: =Detailed[[#This Row],[Column74]]+Detailed[[#This Row],[Column72]] -> 965078.01 | BR68: =SUM(BR54:BR66) -> 299000 | BS68: =SUM(BS54:BS66) -> 44850 | BT68: =Detailed[[#This Row],[Column76]]+Detailed[[#This Row],[Column78]] -> 343850 | DF68: =SUM(DF50:DF66) -> 18492779 | DG68: =SUM(DG50:DG66) -> 2773916.9 | DH68: =SUM(DH50:DH66) -> 21266696 | DI68: =SUM(J68,N68,R68,V68,Z68,AD68,AH68,AL68,AP68,AT68,AX68,BB68,BF68,BJ68,BN68,BR68,BV68,BZ68,CD68,CH68,CL68,CP68,CT68,CX68,DB68) -> 14481307 | DJ68: =SUM(DJ50:DJ66) -> 16261344 | DL68: =SUM(DL50:DL65) -> 15572069 | DM68: =SUM(DM50:DM65) -> 1621760.9 | DO68: =SUMPRODUCT((MOD(COLUMN(I68:DD68)-COLUMN(I68),4)=1)*I68:DD68) -> 14481307 | DP68: =DO68-Detailed[[#This Row],[Column66]] -> 0 | DS68: =DQ68-Detailed[[#This Row],[Column66]] -> -14481307
A69: ENGICON | G69: RDH4-00-001 | H69: =F10 -> 27837620 | DI69: =SUM(J69,N69,R69,V69,Z69,AD69,AH69,AL69,AP69,AT69,AX69,BB69,BF69,BJ69,BN69,BR69,BV69,BZ69,CD69,CH69,CL69,CP69,CT69,CX69,DB69) -> 0 | DN69: الضمان | DO69: =SUMPRODUCT((MOD(COLUMN(I69:DD69)-COLUMN(I69),4)=1)*I69:DD69) -> 0 | DP69: =DO69-Detailed[[#This Row],[Column66]] -> 0 | DQ69: 18468720 | DS69: =DQ69-Detailed[[#This Row],[Column66]] -> 18468720
A70: ENGICON | B70: 1 | C70: Riyadh 4 Masterplan and Infrastructure concept design | H70: 27837620 | I70: 45480 | J70: =ENGICON!F45 -> 2361050.1 | K70: =J70*15% -> 354157.52 | L70: =J70+K70 -> 2715207.6 | M70: 45511 | N70: =ENGICON!H45 -> 3157746.7 | O70: =N70*15% -> 473662 | P70: =N70+O70 -> 3631408.6 | Q70: 45535 | R70: =ENGICON!J45 -> 3983985.9 | S70: =R70*15% -> 597597.89 | T70: =R70+S70 -> 4581583.8 | U70: 45567 | V70: =ENGICON!L45 -> 3449998.3 | W70: =V70*15% -> 517499.74 | X70: =V70+W70 -> 3967498 | Y70: 45636 | Z70: =ENGICON!N45 -> 1820099.7 | AA70: =Z70*15% -> 273014.96 | AB70: =Z70+AA70 -> 2093114.7 | AC70: 45685 | AD70: =ENGICON!P45 -> 1000000 | AE70: =AD70*15% -> 150000 | AF70: =AD70+AE70 -> 1150000 | AG70: 45720 | AH70: =ENGICON!R45 -> 2695839.6 | AI70: =AH70*15% -> 404375.94 | AJ70: =AH70+AI70 -> 3100215.6 | AK70: 45767 | AL70: =ENGICON!T45 -> 2223402.9 | AM70: =AL70*15% -> 333510.43 | AN70: =AL70+AM70 -> 2556913.3 | AO70: 45789 | AP70: 1742432.4 | AQ70: =AP70*15% -> 261364.86 | AR70: =AP70+AQ70 -> 2003797.3 | AS70: 45809 | AT70: 2619302.4 | AU70: =AT70*15% -> 392895.37 | AV70: =AT70+AU70 -> 3012197.8 | DF70: =H70 -> 27837620 | DG70: =DF70*15% -> 4175643 | DH70: =DF70+DG70 -> 32013263 | DI70: =SUMPRODUCT((MOD(COLUMN(I70:DD70)-COLUMN(I70),4)=1)*I70:DD70) -> 25053858 | DJ70: =SUMPRODUCT((MOD(COLUMN(I70:DD70)-COLUMN(J70),4)=2)*I70:DD70) -> 28811937 | DK70: 1 | DL70: =DK70*DF70 -> 27837620 | DO70: =SUMPRODUCT((MOD(COLUMN(I70:DD70)-COLUMN(I70),4)=1)*I70:DD70) -> 25053858 | DP70: =DO70-Detailed[[#This Row],[Column66]] -> 0 | DS70: =DQ70-Detailed[[#This Row],[Column66]] -> -25053858
